Workbook
Name 切片器_是否属三无消费: #N/A
Name 切片器_姓名: #N/A
Name 切片器_账龄区间: #N/A
Name 切片器_账龄区间1: #N/A

Sheet 汇总-1月
A1: 结算系统酒店名称 | B1: 酒店简称 | C1: 收入 | H1: 经营毛利（行业口径） | M1: 业主利润返还（上报口径） | R1: 整体 | T1: 客房 | Y1: 餐饮 | AB1: 未分配
C2: 完成 | D2: 指标 | E2: 完成率 | F2: 同期 | G2: 同比率 | H2: 完成 | I2: 指标 | J2: 完成率 | K2: 同期 | L2: 同比率 | M2: 完成 | N2: 指标 | O2: 完成率 | P2: 同期 | Q2: 同比率 | R2: 元均创收（元） | S2: GOP率 | T2: OCC | U2: ADR（元） | V2: RevPAR（元） | W2: 元均创收（元） | X2: 客房利润率 | Y2: 毛利率 | Z2: 元均创收（元） | AA2: 餐饮利润率 | AB2: 能耗占比 | AC2: 元均创收（元） | AD2: 营销费用率 | AE2: 未分配费用占比
B3: 汇总 | C3: =SUM(C5:C7) -> 409.74156 | D3: =SUM(D5:D7) -> 448.34059 | E3: =C3/D3 -> 0.91390691 | F3: =SUM(F5:F7) -> 500.19513 | G3: =C3/F3-1 -> -0.18083656 | H3: =SUM(H5:H7) -> -64.698091 | I3: =SUM(I5:I7) -> -46.843093 | J3: =H3/I3 -> 1.3811661 | K3: =SUM(K5:K7) -> -71.212733 | L3: =IF(K3>0,H3/K3-1,IF(K3<0,1-H3/K3,"")) -> 0.091481421 | M3: =SUM(M5:M7) -> -102.33954 | N3: =SUM(N5:N7) -> -85.370055 | O3: =IF(N3<0,2-M3/N3,M3/N3) -> 0.80122434 | P3: =SUM(P5:P7) -> -116.62855 | Q3: =IF(P3>0,M3/P3-1,IF(P3<0,1-M3/P3,"")) -> 0.1225172 | R3: ='汇总明细-1月'!R3 -> 2.1563777 | S3: ='汇总明细-1月'!S3 -> -0.15789975 | T3: ='汇总明细-1月'!T3 -> 0.21552663 | W3: ='汇总明细-1月'!W3 -> 3.6946797 | X3: ='汇总明细-1月'!X3 -> 0.54364998 | Y3: ='汇总明细-1月'!Y3 -> 0.55209861 | Z3: ='汇总明细-1月'!Z3 -> 3.9033234 | AA3: ='汇总明细-1月'!AA3 -> 0.26807803 | AB3: ='汇总明细-1月'!AB3 -> 0.29535062 | AC3: ='汇总明细-1月'!AC3 -> 4.7004373 | AD3: ='汇总明细-1月'!AD3 -> 0.027139483 | AE3: ='汇总明细-1月'!AE3 -> 0.56572205
B4: 凤悦事业部合计： | C4: =SUM(C5:C7) -> 409.74156 | D4: =SUM(D5:D7) -> 448.34059 | E4: =C4/D4 -> 0.91390691 | F4: =SUM(F5:F7) -> 500.19513 | G4: =C4/F4-1 -> -0.18083656 | H4: =SUM(H5:H7) -> -64.698091 | I4: =SUM(I5:I7) -> -46.843093 | J4: =H4/I4 -> 1.3811661 | K4: =SUM(K5:K7) -> -71.212733 | L4: =IF(K4>0,H4/K4-1,IF(K4<0,1-H4/K4,"")) -> 0.091481421 | M4: =SUM(M5:M7) -> -102.33954 | N4: =SUM(N5:N7) -> -85.370055 | O4: =IF(N4<0,2-M4/N4,M4/N4) -> 0.80122434 | P4: =SUM(P5:P7) -> -116.62855 | Q4: =IF(P4>0,M4/P4-1,IF(P4<0,1-M4/P4,"")) -> 0.1225172 | R4: ='汇总明细-1月'!R4 -> 2.1563777 | S4: ='汇总明细-1月'!S4 -> -0.15789975 | T4: ='汇总明细-1月'!T4 -> 0.21552663 | W4: ='汇总明细-1月'!W4 -> 3.6946797 | X4: ='汇总明细-1月'!X4 -> 0.54364998 | Y4: ='汇总明细-1月'!Y4 -> 0.55209861 | Z4: ='汇总明细-1月'!Z4 -> 3.9033234 | AA4: ='汇总明细-1月'!AA4 -> 0.26807803 | AB4: ='汇总明细-1月'!AB4 -> 0.29535062 | AC4: ='汇总明细-1月'!AC4 -> 4.7004373 | AD4: ='汇总明细-1月'!AD4 -> 0.027139483 | AE4: ='汇总明细-1月'!AE4 -> 0.56572205
A5: 沈阳诺翰酒店 | B5: 于洪酒店 | C5: =VLOOKUP($B5,'汇总明细-1月'!$A$5:$AE$7,3,0)/10000 -> 283.18159 | D5: =VLOOKUP($B5,'汇总明细-1月'!$A$5:$AE$7,4,0)/10000 -> 269.12814 | E5: =VLOOKUP($B5,'汇总明细-1月'!$A$5:$AE$7,5,0) -> 1.0522184 | F5: =VLOOKUP($B5,'汇总明细-1月'!$A$5:$AE$7,6,0)/10000 -> 294.17345 | G5: =VLOOKUP($B5,'汇总明细-1月'!$A$5:$AE$7,7,0) -> -0.037365231 | H5: =VLOOKUP($B5,'汇总明细-1月'!$A$5:$AE$7,8,0)/10000 -> -34.304774 | I5: =VLOOKUP($B5,'汇总明细-1月'!$A$5:$AE$7,9,0)/10000 -> -25.19102 | J5: =VLOOKUP($B5,'汇总明细-1月'!$A$5:$AE$7,10,0) -> 0.63821417 | K5: =VLOOKUP($B5,'汇总明细-1月'!$A$5:$AE$7,11,0)/10000 -> -55.666638 | L5: =VLOOKUP($B5,'汇总明细-1月'!$A$5:$AE$7,12,0) -> 0.38374626 | M5: =VLOOKUP($B5,'汇总明细-1月'!$A$5:$AE$7,13,0)/10000 -> -58.735147 | N5: =VLOOKUP($B5,'汇总明细-1月'!$A$5:$AE$7,14,0)/10000 -> -51.220325 | O5: =VLOOKUP($B5,'汇总明细-1月'!$A$5:$AE$7,15,0) -> 0.85328437 | P5: =VLOOKUP($B5,'汇总明细-1月'!$A$5:$AE$7,16,0)/10000 -> -84.799468 | Q5: =VLOOKUP($B5,'汇总明细-1月'!$A$5:$AE$7,17,0) -> 0.3073642 | R5: =VLOOKUP($B5,'汇总明细-1月'!$A$5:$AE$7,18,0) -> 2.5475392 | S5: =VLOOKUP($B5,'汇总明细-1月'!$A$5:$AE$7,19,0) -> -0.12114055 | T5: =VLOOKUP($B5,'汇总明细-1月'!$A$5:$AE$7,20,0) -> 0.31282051 | U5: =VLOOKUP($B5,'汇总明细-1月'!$A$5:$AE$7,21,0) -> 199.24168 | V5: =VLOOKUP($B5,'汇总明细-1月'!$A$5:$AE$7,22,0) -> 62.326886 | W5: =VLOOKUP($B5,'汇总明细-1月'!$A$5:$AE$7,23,0) -> 3.9706353 | X5: =VLOOKUP($B5,'汇总明细-1月'!$A$5:$AE$7,24,0) -> 0.56916345 | Y5: =VLOOKUP($B5,'汇总明细-1月'!$A$5:$AE$7,25,0) -> 0.53898494 | Z5: =VLOOKUP($B5,'汇总明细-1月'!$A$5:$AE$7,26,0) -> 5.0071107 | AA5: =VLOOKUP($B5,'汇总明细-1月'!$A$5:$AE$7,27,0) -> 0.311165 | AB5: =VLOOKUP($B5,'汇总明细-1月'!$A$5:$AE$7,28,0) -> 0.33181395 | AC5: =VLOOKUP($B5,'汇总明细-1月'!$A$5:$AE$7,29,0) -> 5.5028084 | AD5: =VLOOKUP($B5,'汇总明细-1月'!$A$5:$AE$7,30,0) -> 0.02304718 | AE5: =VLOOKUP($B5,'汇总明细-1月'!$A$5:$AE$7,31,0) -> 0.55986208
A6: 碧桂园欧洲城凤凰酒店 | B6: 滁州酒店 | C6: =VLOOKUP($B6,'汇总明细-1月'!$A$5:$AE$7,3,0)/10000 -> 12.903087 | D6: =VLOOKUP($B6,'汇总明细-1月'!$A$5:$AE$7,4,0)/10000 -> 63.129571 | E6: =VLOOKUP($B6,'汇总明细-1月'!$A$5:$AE$7,5,0) -> 0.20439054 | F6: =VLOOKUP($B6,'汇总明细-1月'!$A$5:$AE$7,6,0)/10000 -> 80.842754 | G6: =VLOOKUP($B6,'汇总明细-1月'!$A$5:$AE$7,7,0) -> -0.84039278 | H6: =VLOOKUP($B6,'汇总明细-1月'!$A$5:$AE$7,8,0)/10000 -> -36.195544 | I6: =VLOOKUP($B6,'汇总明细-1月'!$A$5:$AE$7,9,0)/10000 -> -12.672792 | J6: =VLOOKUP($B6,'汇总明细-1月'!$A$5:$AE$7,10,0) -> -0.85616177 | K6: =VLOOKUP($B6,'汇总明细-1月'!$A$5:$AE$7,11,0)/10000 -> 2.398807 | L6: =VLOOKUP($B6,'汇总明细-1月'!$A$5:$AE$7,12,0) -> -16.088977 | M6: =VLOOKUP($B6,'汇总明细-1月'!$A$5:$AE$7,13,0)/10000 -> -40.646245 | N6: =VLOOKUP($B6,'汇总明细-1月'!$A$5:$AE$7,14,0)/10000 -> -17.685606 | O6: =VLOOKUP($B6,'汇总明细-1月'!$A$5:$AE$7,15,0) -> -0.29826702 | P6: =VLOOKUP($B6,'汇总明细-1月'!$A$5:$AE$7,16,0)/10000 -> -4.925041 | Q6: =VLOOKUP($B6,'汇总明细-1月'!$A$5:$AE$7,17,0) -> -7.252976 | R6: =VLOOKUP($B6,'汇总明细-1月'!$A$5:$AE$7,18,0) -> 0.51806265 | S6: =VLOOKUP($B6,'汇总明细-1月'!$A$5:$AE$7,19,0) -> -2.8051848 | T6: =VLOOKUP($B6,'汇总明细-1月'!$A$5:$AE$7,20,0) -> 0.032112758 | U6: =VLOOKUP($B6,'汇总明细-1月'!$A$5:$AE$7,21,0) -> 165.84338 | V6: =VLOOKUP($B6,'汇总明细-1月'!$A$5:$AE$7,22,0) -> 5.3256883 | W6: =VLOOKUP($B6,'汇总明细-1月'!$A$5:$AE$7,23,0) -> 0.81298809 | X6: =VLOOKUP($B6,'汇总明细-1月'!$A$5:$AE$7,24,0) -> -0.59771863 | Y6: =VLOOKUP($B6,'汇总明细-1月'!$A$5:$AE$7,25,0) -> 0.47804757 | Z6: =VLOOKUP($B6,'汇总明细-1月'!$A$5:$AE$7,26,0) -> 0.98638897 | AA6: =VLOOKUP($B6,'汇总明细-1月'!$A$5:$AE$7,27,0) -> -0.5975288 | AB6: =VLOOKUP($B6,'汇总明细-1月'!$A$5:$AE$7,28,0) -> 1.0659493 | AC6: =VLOOKUP($B6,'汇总明细-1月'!$A$5:$AE$7,29,0) -> 1.1984064 | AD6: =VLOOKUP($B6,'汇总明细-1月'!$A$5:$AE$7,30,0) -> 0.0016072898 | AE6: =VLOOKUP($B6,'汇总明细-1月'!$A$5:$AE$7,31,0) -> 2.2241329
A7: 武汉碧桂园凤凰酒店 | B7: 武汉酒店 | C7: =VLOOKUP($B7,'汇总明细-1月'!$A$5:$AE$7,3,0)/10000 -> 113.65688 | D7: =VLOOKUP($B7,'汇总明细-1月'!$A$5:$AE$7,4,0)/10000 -> 116.08287 | E7: =VLOOKUP($B7,'汇总明细-1月'!$A$5:$AE$7,5,0) -> 0.97910122 | F7: =VLOOKUP($B7,'汇总明细-1月'!$A$5:$AE$7,6,0)/10000 -> 125.17893 | G7: =VLOOKUP($B7,'汇总明细-1月'!$A$5:$AE$7,7,0) -> -0.092044583 | H7: =VLOOKUP($B7,'汇总明细-1月'!$A$5:$AE$7,8,0)/10000 -> 5.802227 | I7: =VLOOKUP($B7,'汇总明细-1月'!$A$5:$AE$7,9,0)/10000 -> -8.979281 | J7: =VLOOKUP($B7,'汇总明细-1月'!$A$5:$AE$7,10,0) -> 2.6461795 | K7: =VLOOKUP($B7,'汇总明细-1月'!$A$5:$AE$7,11,0)/10000 -> -17.944902 | L7: =VLOOKUP($B7,'汇总明细-1月'!$A$5:$AE$7,12,0) -> 1.3233357 | M7: =VLOOKUP($B7,'汇总明细-1月'!$A$5:$AE$7,13,0)/10000 -> -2.958152 | N7: =VLOOKUP($B7,'汇总明细-1月'!$A$5:$AE$7,14,0)/10000 -> -16.464124 | O7: =VLOOKUP($B7,'汇总明细-1月'!$A$5:$AE$7,15,0) -> 1.8203274 | P7: =VLOOKUP($B7,'汇总明细-1月'!$A$5:$AE$7,16,0)/10000 -> -26.904038 | Q7: =VLOOKUP($B7,'汇总明细-1月'!$A$5:$AE$7,17,0) -> 0.89004803 | R7: =VLOOKUP($B7,'汇总明细-1月'!$A$5:$AE$7,18,0) -> 2.1067655 | S7: =VLOOKUP($B7,'汇总明细-1月'!$A$5:$AE$7,19,0) -> 0.051050379 | T7: =VLOOKUP($B7,'汇总明细-1月'!$A$5:$AE$7,20,0) -> 0.22488062 | U7: =VLOOKUP($B7,'汇总明细-1月'!$A$5:$AE$7,21,0) -> 221.8789 | V7: =VLOOKUP($B7,'汇总明细-1月'!$A$5:$AE$7,22,0) -> 49.896264 | W7: =VLOOKUP($B7,'汇总明细-1月'!$A$5:$AE$7,23,0) -> 4.7829935 | X7: =VLOOKUP($B7,'汇总明细-1月'!$A$5:$AE$7,24,0) -> 0.60995125 | Y7: =VLOOKUP($B7,'汇总明细-1月'!$A$5:$AE$7,25,0) -> 0.59600743 | Z7: =VLOOKUP($B7,'汇总明细-1月'!$A$5:$AE$7,26,0) -> 3.2034786 | AA7: =VLOOKUP($B7,'汇总明细-1月'!$A$5:$AE$7,27,0) -> 0.26094614 | AB7: =VLOOKUP($B7,'汇总明细-1月'!$A$5:$AE$7,28,0) -> 0.117017 | AC7: =VLOOKUP($B7,'汇总明细-1月'!$A$5:$AE$7,29,0) -> 4.5567032 | AD7: =VLOOKUP($B7,'汇总明细-1月'!$A$5:$AE$7,30,0) -> 0.040234237 | AE7: =VLOOKUP($B7,'汇总明细-1月'!$A$5:$AE$7,31,0) -> 0.39204858

Sheet 汇总-累计
A1: 结算系统酒店名称 | B1: 酒店简称 | C1: 收入 | I1: 经营毛利（行业口径） | O1: 业主利润返还（上报口径） | U1: 整体 | W1: 客房 | AB1: 餐饮 | AE1: 未分配
C2: 完成 | D2: 指标 | E2: 完成率 | F2: 同期 | G2: 同比率 | H2: 全年完成率 | I2: 完成 | J2: 指标 | K2: 完成率 | L2: 同期 | M2: 同比率 | N2: 全年完成率 | O2: 完成 | P2: 指标 | Q2: 完成率 | R2: 同期 | S2: 同比率 | T2: 全年完成率 | U2: 元均创收（元） | V2: GOP率 | W2: OCC | X2: ADR（元） | Y2: RevPAR（元） | Z2: 元均创收（元） | AA2: 客房利润率 | AB2: 毛利率 | AC2: 元均创收（元） | AD2: 餐饮利润率 | AE2: 能耗占比 | AF2: 元均创收（元） | AG2: 营销费用率 | AH2: 未分配费用占比
B3: 汇总 | C3: =SUM(C5:C7) -> 409.74156 | D3: =SUM(D5:D7) -> 448.34059 | E3: =C3/D3 -> 0.91390691 | F3: =SUM(F5:F7) -> 500.19513 | G3: =C3/F3-1 -> -0.18083656 | H3: ='汇总明细-累计'!I3 -> 0.062357272 | I3: =SUM(I5:I7) -> -64.698091 | J3: =SUM(J5:J7) -> -46.843093 | K3: =I3/J3 -> 1.3811661 | L3: =SUM(L5:L7) -> -71.212733 | M3: =IF(L3>0,I3/L3-1,IF(L3<0,1-I3/L3,"")) -> 0.091481421 | N3: ='汇总明细-累计'!P3 -> -0.10734263 | O3: =SUM(O5:O7) -> -102.33954 | P3: =SUM(P5:P7) -> -85.370055 | Q3: =IF(P3<0,2-O3/P3,O3/P3) -> 0.80122434 | R3: =SUM(R5:R7) -> -116.62855 | S3: =IF(R3>0,O3/R3-1,IF(R3<0,1-O3/R3,"")) -> 0.1225172 | T3: ='汇总明细-累计'!W3 -> -0.76813958 | U3: ='汇总明细-累计'!X3 -> 2.1563777 | V3: ='汇总明细-累计'!Y3 -> -0.15789975 | W3: ='汇总明细-累计'!Z3 -> 0.21552663 | Z3: ='汇总明细-累计'!AC3 -> 3.6946797 | AA3: ='汇总明细-累计'!AD3 -> 0.54364998 | AB3: ='汇总明细-累计'!AE3 -> 0.55209861 | AC3: ='汇总明细-累计'!AF3 -> 3.9033234 | AD3: ='汇总明细-累计'!AG3 -> 0.26807803 | AE3: ='汇总明细-累计'!AH3 -> 0.29535062 | AF3: ='汇总明细-累计'!AI3 -> 4.7004373 | AG3: ='汇总明细-累计'!AJ3 -> 0.027139483 | AH3: ='汇总明细-累计'!AK3 -> 0.56572205
B4: 凤悦事业部合计： | C4: =SUM(C5:C7) -> 409.74156 | D4: =SUM(D5:D7) -> 448.34059 | E4: =C4/D4 -> 0.91390691 | F4: =SUM(F5:F7) -> 500.19513 | G4: =C4/F4-1 -> -0.18083656 | H4: ='汇总明细-累计'!I4 -> 0.062357272 | I4: =SUM(I5:I7) -> -64.698091 | J4: =SUM(J5:J7) -> -46.843093 | K4: =I4/J4 -> 1.3811661 | L4: =SUM(L5:L7) -> -71.212733 | M4: =IF(L4>0,I4/L4-1,IF(L4<0,1-I4/L4,"")) -> 0.091481421 | N4: ='汇总明细-累计'!P4 -> -0.10734263 | O4: =SUM(O5:O7) -> -102.33954 | P4: =SUM(P5:P7) -> -85.370055 | Q4: =IF(P4<0,2-O4/P4,O4/P4) -> 0.80122434 | R4: =SUM(R5:R7) -> -116.62855 | S4: =IF(R4>0,O4/R4-1,IF(R4<0,1-O4/R4,"")) -> 0.1225172 | T4: ='汇总明细-累计'!W4 -> -0.76813958 | U4: ='汇总明细-累计'!X4 -> 2.1563777 | V4: ='汇总明细-累计'!Y4 -> -0.15789975 | W4: ='汇总明细-累计'!Z4 -> 0.21552663 | Z4: ='汇总明细-累计'!AC4 -> 3.6946797 | AA4: ='汇总明细-累计'!AD4 -> 0.54364998 | AB4: ='汇总明细-累计'!AE4 -> 0.55209861 | AC4: ='汇总明细-累计'!AF4 -> 3.9033234 | AD4: ='汇总明细-累计'!AG4 -> 0.26807803 | AE4: ='汇总明细-累计'!AH4 -> 0.29535062 | AF4: ='汇总明细-累计'!AI4 -> 4.7004373 | AG4: ='汇总明细-累计'!AJ4 -> 0.027139483 | AH4: ='汇总明细-累计'!AK4 -> 0.56572205
A5: 沈阳诺翰酒店 | B5: 于洪酒店 | C5: =VLOOKUP($B5,'汇总明细-累计'!$A$5:$AK$23,3,0)/10000 -> 283.18159 | D5: =VLOOKUP($B5,'汇总明细-累计'!$A$5:$AK$23,4,0)/10000 -> 269.12814 | E5: =VLOOKUP($B5,'汇总明细-累计'!$A$5:$AK$23,5,0) -> 1.0522184 | F5: =VLOOKUP($B5,'汇总明细-累计'!$A$5:$AK$23,6,0)/10000 -> 294.17345 | G5: =VLOOKUP($B5,'汇总明细-累计'!$A$5:$AK$23,7,0) -> -0.037365231 | H5: =VLOOKUP($B5,'汇总明细-累计'!$A$5:$AK$23,9,0) -> 0.077214013 | I5: =VLOOKUP($B5,'汇总明细-累计'!$A$5:$AK$23,10,0)/10000 -> -34.304774 | J5: =VLOOKUP($B5,'汇总明细-累计'!$A$5:$AK$23,11,0)/10000 -> -25.19102 | K5: =VLOOKUP($B5,'汇总明细-累计'!$A$5:$AK$23,12,0) -> 0.63821417 | L5: =VLOOKUP($B5,'汇总明细-累计'!$A$5:$AK$23,13,0)/10000 -> -55.666638 | M5: =VLOOKUP($B5,'汇总明细-累计'!$A$5:$AK$23,14,0) -> 0.38374626 | N5: =VLOOKUP($B5,'汇总明细-累计'!$A$5:$AK$23,16,0) -> -0.10395386 | O5: =VLOOKUP($B5,'汇总明细-累计'!$A$5:$AK$23,17,0)/10000 -> -58.735147 | P5: =VLOOKUP($B5,'汇总明细-累计'!$A$5:$AK$23,18,0)/10000 -> -51.220325 | Q5: =VLOOKUP($B5,'汇总明细-累计'!$A$5:$AK$23,19,0) -> 0.85328437 | R5: =VLOOKUP($B5,'汇总明细-累计'!$A$5:$AK$23,20,0)/10000 -> -84.799468 | S5: =VLOOKUP($B5,'汇总明细-累计'!$A$5:$AK$23,21,0) -> 0.3073642 | T5: =VLOOKUP($B5,'汇总明细-累计'!$A$5:$AK$23,23,0) -> -2.39417 | U5: =VLOOKUP($B5,'汇总明细-累计'!$A$5:$AK$23,24,0) -> 2.5475392 | V5: =VLOOKUP($B5,'汇总明细-累计'!$A$5:$AK$23,25,0) -> -0.12114055 | W5: =VLOOKUP($B5,'汇总明细-累计'!$A$5:$AK$23,26,0) -> 0.31282051 | X5: =VLOOKUP($B5,'汇总明细-累计'!$A$5:$AK$23,27,0) -> 199.24168 | Y5: =VLOOKUP($B5,'汇总明细-累计'!$A$5:$AK$23,28,0) -> 62.326886 | Z5: =VLOOKUP($B5,'汇总明细-累计'!$A$5:$AK$23,29,0) -> 3.9706353 | AA5: =VLOOKUP($B5,'汇总明细-累计'!$A$5:$AK$23,30,0) -> 0.56916345 | AB5: =VLOOKUP($B5,'汇总明细-累计'!$A$5:$AK$23,31,0) -> 0.53898494 | AC5: =VLOOKUP($B5,'汇总明细-累计'!$A$5:$AK$23,32,0) -> 5.0071107 | AD5: =VLOOKUP($B5,'汇总明细-累计'!$A$5:$AK$23,33,0) -> 0.311165 | AE5: =VLOOKUP($B5,'汇总明细-累计'!$A$5:$AK$23,34,0) -> 0.33181395 | AF5: =VLOOKUP($B5,'汇总明细-累计'!$A$5:$AK$23,35,0) -> 5.5028084 | AG5: =VLOOKUP($B5,'汇总明细-累计'!$A$5:$AK$23,36,0) -> 0.02304718 | AH5: =VLOOKUP($B5,'汇总明细-累计'!$A$5:$AK$23,37,0) -> 0.55986208
A6: 碧桂园欧洲城凤凰酒店 | B6: 滁州酒店 | C6: =VLOOKUP($B6,'汇总明细-累计'!$A$5:$AK$23,3,0)/10000 -> 12.903087 | D6: =VLOOKUP($B6,'汇总明细-累计'!$A$5:$AK$23,4,0)/10000 -> 63.129571 | E6: =VLOOKUP($B6,'汇总明细-累计'!$A$5:$AK$23,5,0) -> 0.20439054 | F6: =VLOOKUP($B6,'汇总明细-累计'!$A$5:$AK$23,6,0)/10000 -> 80.842754 | G6: =VLOOKUP($B6,'汇总明细-累计'!$A$5:$AK$23,7,0) -> -0.84039278 | H6: =VLOOKUP($B6,'汇总明细-累计'!$A$5:$AK$23,9,0) -> 0.011502979 | I6: =VLOOKUP($B6,'汇总明细-累计'!$A$5:$AK$23,10,0)/10000 -> -36.195544 | J6: =VLOOKUP($B6,'汇总明细-累计'!$A$5:$AK$23,11,0)/10000 -> -12.672792 | K6: =VLOOKUP($B6,'汇总明细-累计'!$A$5:$AK$23,12,0) -> -0.85616177 | L6: =VLOOKUP($B6,'汇总明细-累计'!$A$5:$AK$23,13,0)/10000 -> 2.398807 | M6: =VLOOKUP($B6,'汇总明细-累计'!$A$5:$AK$23,14,0) -> -16.088977 | N6: =VLOOKUP($B6,'汇总明细-累计'!$A$5:$AK$23,16,0) -> -0.47625696 | O6: =VLOOKUP($B6,'汇总明细-累计'!$A$5:$AK$23,17,0)/10000 -> -40.646245 | P6: =VLOOKUP($B6,'汇总明细-累计'!$A$5:$AK$23,18,0)/10000 -> -17.685606 | Q6: =VLOOKUP($B6,'汇总明细-累计'!$A$5:$AK$23,19,0) -> -0.29826702 | R6: =VLOOKUP($B6,'汇总明细-累计'!$A$5:$AK$23,20,0)/10000 -> -4.925041 | S6: =VLOOKUP($B6,'汇总明细-累计'!$A$5:$AK$23,21,0) -> -7.252976 | T6: =VLOOKUP($B6,'汇总明细-累计'!$A$5:$AK$23,23,0) -> -3.9143876 | U6: =VLOOKUP($B6,'汇总明细-累计'!$A$5:$AK$23,24,0) -> 0.51806265 | V6: =VLOOKUP($B6,'汇总明细-累计'!$A$5:$AK$23,25,0) -> -2.8051848 | W6: =VLOOKUP($B6,'汇总明细-累计'!$A$5:$AK$23,26,0) -> 0.032112758 | X6: =VLOOKUP($B6,'汇总明细-累计'!$A$5:$AK$23,27,0) -> 165.84338 | Y6: =VLOOKUP($B6,'汇总明细-累计'!$A$5:$AK$23,28,0) -> 5.3256883 | Z6: =VLOOKUP($B6,'汇总明细-累计'!$A$5:$AK$23,29,0) -> 0.81298809 | AA6: =VLOOKUP($B6,'汇总明细-累计'!$A$5:$AK$23,30,0) -> -0.59771863 | AB6: =VLOOKUP($B6,'汇总明细-累计'!$A$5:$AK$23,31,0) -> 0.47804757 | AC6: =VLOOKUP($B6,'汇总明细-累计'!$A$5:$AK$23,32,0) -> 0.98638897 | AD6: =VLOOKUP($B6,'汇总明细-累计'!$A$5:$AK$23,33,0) -> -0.5975288 | AE6: =VLOOKUP($B6,'汇总明细-累计'!$A$5:$AK$23,34,0) -> 1.0659493 | AF6: =VLOOKUP($B6,'汇总明细-累计'!$A$5:$AK$23,35,0) -> 1.1984064 | AG6: =VLOOKUP($B6,'汇总明细-累计'!$A$5:$AK$23,36,0) -> 0.0016072898 | AH6: =VLOOKUP($B6,'汇总明细-累计'!$A$5:$AK$23,37,0) -> 2.2241329
A7: 武汉碧桂园凤凰酒店 | B7: 武汉酒店 | C7: =VLOOKUP($B7,'汇总明细-累计'!$A$5:$AK$23,3,0)/10000 -> 113.65688 | D7: =VLOOKUP($B7,'汇总明细-累计'!$A$5:$AK$23,4,0)/10000 -> 116.08287 | E7: =VLOOKUP($B7,'汇总明细-累计'!$A$5:$AK$23,5,0) -> 0.97910122 | F7: =VLOOKUP($B7,'汇总明细-累计'!$A$5:$AK$23,6,0)/10000 -> 125.17893 | G7: =VLOOKUP($B7,'汇总明细-累计'!$A$5:$AK$23,7,0) -> -0.092044583 | H7: =VLOOKUP($B7,'汇总明细-累计'!$A$5:$AK$23,9,0) -> 0.063792549 | I7: =VLOOKUP($B7,'汇总明细-累计'!$A$5:$AK$23,10,0)/10000 -> 5.802227 | J7: =VLOOKUP($B7,'汇总明细-累计'!$A$5:$AK$23,11,0)/10000 -> -8.979281 | K7: =VLOOKUP($B7,'汇总明细-累计'!$A$5:$AK$23,12,0) -> 2.6461795 | L7: =VLOOKUP($B7,'汇总明细-累计'!$A$5:$AK$23,13,0)/10000 -> -17.944902 | M7: =VLOOKUP($B7,'汇总明细-累计'!$A$5:$AK$23,14,0) -> 1.3233357 | N7: =VLOOKUP($B7,'汇总明细-累计'!$A$5:$AK$23,16,0) -> 0.029494095 | O7: =VLOOKUP($B7,'汇总明细-累计'!$A$5:$AK$23,17,0)/10000 -> -2.958152 | P7: =VLOOKUP($B7,'汇总明细-累计'!$A$5:$AK$23,18,0)/10000 -> -16.464124 | Q7: =VLOOKUP($B7,'汇总明细-累计'!$A$5:$AK$23,19,0) -> 1.8203274 | R7: =VLOOKUP($B7,'汇总明细-累计'!$A$5:$AK$23,20,0)/10000 -> -26.904038 | S7: =VLOOKUP($B7,'汇总明细-累计'!$A$5:$AK$23,21,0) -> 0.89004803 | T7: =VLOOKUP($B7,'汇总明细-累计'!$A$5:$AK$23,23,0) -> -0.030088811 | U7: =VLOOKUP($B7,'汇总明细-累计'!$A$5:$AK$23,24,0) -> 2.1067655 | V7: =VLOOKUP($B7,'汇总明细-累计'!$A$5:$AK$23,25,0) -> 0.051050379 | W7: =VLOOKUP($B7,'汇总明细-累计'!$A$5:$AK$23,26,0) -> 0.22488062 | X7: =VLOOKUP($B7,'汇总明细-累计'!$A$5:$AK$23,27,0) -> 221.8789 | Y7: =VLOOKUP($B7,'汇总明细-累计'!$A$5:$AK$23,28,0) -> 49.896264 | Z7: =VLOOKUP($B7,'汇总明细-累计'!$A$5:$AK$23,29,0) -> 4.7829935 | AA7: =VLOOKUP($B7,'汇总明细-累计'!$A$5:$AK$23,30,0) -> 0.60995125 | AB7: =VLOOKUP($B7,'汇总明细-累计'!$A$5:$AK$23,31,0) -> 0.59600743 | AC7: =VLOOKUP($B7,'汇总明细-累计'!$A$5:$AK$23,32,0) -> 3.2034786 | AD7: =VLOOKUP($B7,'汇总明细-累计'!$A$5:$AK$23,33,0) -> 0.26094614 | AE7: =VLOOKUP($B7,'汇总明细-累计'!$A$5:$AK$23,34,0) -> 0.117017 | AF7: =VLOOKUP($B7,'汇总明细-累计'!$A$5:$AK$23,35,0) -> 4.5567032 | AG7: =VLOOKUP($B7,'汇总明细-累计'!$A$5:$AK$23,36,0) -> 0.040234237 | AH7: =VLOOKUP($B7,'汇总明细-累计'!$A$5:$AK$23,37,0) -> 0.39204858

Sheet 资管部
G1: 2025年经营收入分类—万元 | H1: 2025年经营收入分类—万元 | I1: 2025年经营收入分类—万元 | J1: 2025年经营收入分类—万元 | K1: 2025年经营收入分类—万元 | L1: 2025年经营收入分类—万元 | M1: 2025年经营收入分类—万元 | N1: 2025年经营收入分类—万元 | O1: 2025年经营收入分类—万元 | P1: 核心成本项情况 | Q1: 核心成本项情况 | R1: 核心成本项情况 | S1: 核心成本项情况 | T1: 核心成本项情况 | U1: 核心成本项情况 | V1: 核心成本项情况 | W1: 核心成本项情况 | X1: 核心成本项情况 | Y1: 2025年经营成本（直接成本）—万元 | Z1: 2025年经营成本（直接成本）—万元 | AA1: 2025年经营成本（直接成本）—万元 | AB1: 2025年经营成本（直接成本）—万元 | AC1: 2025年经营成本（直接成本）—万元 | AD1: 2025年经营成本（直接成本）—万元 | AE1: 2025年经营成本（直接成本）—万元 | AF1: 2025年经营成本（直接成本）—万元 | AG1: 2025年经营成本（直接成本）—万元 | AH1: 2025年经营成本（直接成本）—万元 | AI1: 2025年经营成本（直接成本）—万元 | AJ1: 2025年经营成本（直接成本）—万元 | AK1: 2025年经营成本（直接成本）—万元 | AL1: 2025年经营成本（直接成本）—万元 | AM1: 2025年经营成本（直接成本）—万元 | AN1: 2025年经营成本（直接成本）—万元 | AP1: 2025年经营成本（未分配费）—万元 | AQ1: 2025年经营成本（未分配费）—万元 | AR1: 2025年经营成本（未分配费）—万元 | AS1: 2025年经营成本（未分配费）—万元 | AT1: 2025年经营成本（未分配费）—万元 | AU1: 2025年经营成本（未分配费）—万元 | AV1: 2025年经营成本（未分配费）—万元 | AW1: 2025年经营成本（未分配费）—万元 | AX1: 2025年经营成本（未分配费）—万元 | AY1: 2025年经营成本（未分配费）—万元 | AZ1: 2025年经营成本（未分配费）—万元 | BA1: 2025年经营成本（未分配费）—万元 | BB1: 2025年经营成本（未分配费）—万元 | BC1: 2025年经营成本（未分配费）—万元 | BD1: 2025年经营成本（未分配费）—万元 | BE1: 2025年经营成本（未分配费）—万元 | BF1: 2025年经营成本（未分配费）—万元 | BG1: 非经营支出 | BH1: 非经营支出 | BI1: 非经营支出 | BJ1: 非经营支出 | BK1: 非经营支出 | BL1: 非经营支出 | BM1: 非经营支出 | BN1: 非经营支出 | BO1: 非经营支出 | BP1: 非经营支出
G2: 客房 | H2: 餐饮 | I2: 餐饮 | J2: 餐饮 | K2: 其他经营收入 | L2: 其他经营收入 | M2: 其他经营收入 | N2: 营业外收入 | O2: 合计 | P2: 薪酬及相关 | Q2: 薪酬及相关 | R2: 能耗 | S2: 能耗 | T2: 洗涤费 | U2: 洗涤费 | V2: 洗涤费 | W2: 维修费 | X2: 维修费 | Y2: 客房 | Z2: 客房 | AA2: 客房 | AB2: 客房 | AC2: 客房 | AD2: 客房 | AE2: 餐饮 | AF2: 餐饮 | AG2: 餐饮 | AH2: 餐饮 | AI2: 餐饮 | AJ2: 餐饮 | AK2: 新零售 | AL2: 康乐 | AM2: 租赁收入 | AN2: 租赁收入 | AO2: 合计 | AP2: 行政费用 | AQ2: 行政费用 | AR2: 营销费用 | AS2: 营销费用 | AT2: 营销费用 | AU2: 物业运营及保养 | AV2: 物业运营及保养 | AW2: 物业运营及保养 | AX2: 能耗 | AY2: 能耗 | AZ2: 能耗 | BA2: 能耗 | BB2: 能耗 | BE2: 能源优化 | BG2: 业主相关费用 | BH2: 业主相关费用 | BI2: 租金费用 | BJ2: 租金费用 | BK2: FFE | BL2: FFE | BM2: 非经营税费 | BN2: 其他非经营支出 | BO2: 其他非经营支出
B3: 酒店简称 | C3: 酒店简称2 | D3: 酒店全称 | E3: 收入check | F3: 总收入 | G3: 客房 | H3: 餐饮 | I3: 会议 | J3: 零售 | K3: 租赁收入 | L3: 康乐温泉收入 | M3: 其他经营收入 | P3: 薪酬及相关总额 | Q3: 薪酬及相关占比收入 | R3: 能耗总额 | S3: 能耗及相关占比收入 | T3: 洗涤费总额 | U3: 是否外洗 | V3: 洗涤占比收入 | W3: 维修费用总额 | X3: 维修费用占比收入 | Y3: 平均渠道费用 | Z3: 销售成本 | AA3: 运营费用-薪酬及相关 | AB3: 运营费用-洗涤费用 | AC3: 运营费用-其他 | AD3: 客房费用-check | AE3: 平均渠道费用 | AF3: 销售成本 | AG3: 运营费用-薪酬及相关 | AH3: 运营费用-洗涤费用 | AI3: 运营费用-其他 | AJ3: 费用-check | AK3: 购入成本 | AL3: 运营费用 | AM3: 佣金 | AN3: 其他 | AP3: 薪酬及相关 | AQ3: 其他 | AR3: 薪酬及相关 | AS3: 营销及推广 | AT3: 其他 | AU3: 薪酬及相关 | AV3: 维修费用 | AW3: 其他 | AX3: 电 | AY3: 水 | AZ3: 燃气 | BA3: 暖气 | BB3: 合计 | BC3: % | BD3: 能耗check | BE3: 是否安装 光伏、储能 | BF3: 是否有计划 安装光伏、储能 | BG3: 业主费用总额 | BH3: 情况说明 （主要项目、金额和发生原因） | BI3: 租金费用总额 | BJ3: 情况说明 （租赁原因、租赁成本、原因） | BK3: FFE总额 | BL3: 情况说明 （1、年度投入说明；2、费用超额和差额使用的原因） | BM3: 房产税及其他税费 | BN3: 金额 | BO3: 特殊情况说明 （如有） | BP3: 非经营check
F4: =SUM(F5:F38) -> #REF! | G4: =SUM(G5:G38) -> #REF! | H4: =SUM(H5:H38) -> #REF! | I4: =SUM(I5:I38) -> #REF! | J4: =SUM(J5:J38) -> #REF! | K4: =SUM(K5:K38) -> #REF! | L4: =SUM(L5:L38) -> #REF! | M4: =SUM(M5:M38) -> #REF! | ... O4: =SUM(O5:O38) -> #REF! | P4: =SUM(P5:P36) -> #REF! | Q4: =P4/F4 -> #REF! | R4: =SUM(R5:R36) -> #REF! | S4: =R4/F4 -> #REF! | T4: =SUM(T5:T36) -> #REF! | V4: =T4/F4 -> #REF! | W4: =SUM(W5:W36) -> #REF! | X4: =W4/F4 -> #REF! | Y4: =SUM(Y5:Y36) -> #VALUE! | Z4: =SUM(Z5:Z36) -> #VALUE! | AA4: =SUM(AA5:AA36) -> #REF! | AB4: =SUM(AB5:AB36) -> #VALUE! | AC4: =SUM(AC5:AC36) -> #VALUE! | AD4: =SUM(AD5:AD36) -> #VALUE! | AE4: =SUM(AE5:AE36) -> 0 | AF4: =SUM(AF5:AF36) -> #REF! | ... BA4: =SUM(BA5:BA36) -> #VALUE! | BB4: =SUM(BB5:BB40) -> #VALUE! | BC4: =BB4/F4 -> #VALUE! | BD4: =SUM(BD5:BD36) -> #VALUE! | BG4: =SUM(BG5:BG39) -> #REF! | BI4: =SUM(BI5:BI36) -> #REF! | BK4: =SUM(BK5:BK36) -> #REF! | BM4: =SUM(BM5:BM36) -> #REF! | BN4: =SUM(BN5:BN36) -> #REF! | BP4: =SUM(BP5:BP36) -> #REF!
A5: 于洪酒店 | B5: 于洪 | C5: 于洪酒店 | D5: 沈阳于洪碧桂园凤凰酒店有限公司 | E5: =SUM(G5:M5)-F5 -> 0 | F5: {=INDIRECT($B5&"!M16")} -> 2831815.9 | G5: {=INDIRECT($B5&"!M43")} -> 1138840.1 | H5: {=INDIRECT($B5&"!M52")+INDIRECT($B5&"!M53")} -> 1292584 | I5: {=INDIRECT($B5&"!M55")} -> 257360.45 | J5: {=INDIRECT($B5&"!M54")} -> 3062.53 | K5: {=INDIRECT($B5&"!M75")} -> 69952.73 | L5: {=INDIRECT($B5&"!M69")+INDIRECT($B5&"!M70")} -> 0 | M5: {=INDIRECT($B5&"!M77")-INDIRECT($B5&"!M75")-INDIRECT($B5&"!M69")-INDIRECT($B5&"!M70")} -> 70016.02 | N5: {=INDIRECT($B5&"!M115")} -> 1293.29 | O5: =SUM(G5:N5) -> 2833109.2 | P5: {=INDIRECT($B5&"!M31")} -> 1111588.8 | Q5: =P5/F5 -> 0.39253567 | R5: {=INDIRECT($B5&"!M34")} -> 939636.01 | S5: =R5/F5 -> 0.33181395 | T5: {=INDIRECT($B5&"!M38")} -> 61100.13 | V5: =T5/F5 -> 0.021576307 | W5: {=INDIRECT($B5&"!M36")} -> 46717.47 | X5: =W5/F5 -> 0.016497354 | Y5: =SUMIFS([1]客房!D:D,[1]客房!B:B,D5,[1]客房!C:C,"Reservation Fees 预订成本") -> #VALUE! | Z5: =SUMIFS([1]客房!D:D,[1]客房!B:B,D5,[1]客房!C:C," Total Cost of Sales 总销售成本") -> #VALUE! | AA5: {=INDIRECT($B5&"!M44")+INDIRECT($B5&"!M45")} -> 286815.6 | AB5: =SUMIFS([1]客房!D:D,[1]客房!B:B,D5,[1]客房!C:C,"Laundry 洗涤费") -> #VALUE! | AC5: {=INDIRECT($B5&"!M46")-Y5-Z5-AB5} -> #VALUE! | AD5: {=INDIRECT($B5&"!M47")-SUM(Y5:AC5)} -> #VALUE! | AF5: {=INDIRECT($B5&"!M60")} -> 715959.62 | AG5: {=INDIRECT($B5&"!M61")+INDIRECT($B5&"!M62")} -> 310160.31 | AH5: =SUMIFS([1]餐饮!D:D,[1]餐饮!B:B,D5,[1]餐饮!C:C,"Laundry 洗涤费") -> #VALUE! | AI5: {=INDIRECT($B5&"!M63")-AH5} -> #VALUE! | AJ5: {=INDIRECT($B5&"!M64")-SUM(AE5:AI5)} -> #VALUE! | AK5: =SUMIFS([1]新零售!D:D,[1]新零售!B:B,D5,[1]新零售!C:C,"Total Cost of Sales 总销售成本") -> #VALUE! | AL5: =SUMIFS([1]康乐温泉!C:C,[1]康乐温泉!A:A,D5,[1]康乐温泉!B:B,"Total Cost of Sales 总销售成本")+SUMIFS([1]康乐温泉!C:C,[1]康乐温泉!A:A,D5,[1]康乐温泉!B:B,"Total Other Expenses 其他费用合计") -> #VALUE! | AP5: {=INDIRECT($B5&"!M91")+INDIRECT($B5&"!M92")} -> 230985.86 | AQ5: {=INDIRECT($B5&"!M93")+INDIRECT($B5&"!M94")+INDIRECT($B5&"!M95")+INDIRECT($B5&"!M96")} -> 36049.66 | AR5: {=INDIRECT($B5&"!M98")+INDIRECT($B5&"!M99")} -> 147121.97 | AT5: {=INDIRECT($B5&"!M100")} -> 22962.37 | AU5: {=INDIRECT($B5&"!M103")+INDIRECT($B5&"!M104")} -> 136505.02 | AV5: {=INDIRECT($B5&"!M36")} -> 46717.47 | AW5: {=INDIRECT($B5&"!M105")-AV5} -> 25447.99 | AX5: =SUMIFS([1]能源!C:C,[1]能源!A:A,D5,[1]能源!B:B,"Electricity 电费") -> #VALUE! | AY5: =SUMIFS([1]能源!C:C,[1]能源!A:A,D5,[1]能源!B:B,"Steam 蒸汽费")+SUMIFS([1]能源!C:C,[1]能源!A:A,D5,[1]能源!B:B,"Geothermal water 地热水")+SUMIFS([1]能源!C:C,[1]能源!A:A,D5,[1]能源!B:B,"Water 水费") -> #VALUE! | AZ5: =SUMIFS([1]能源!C:C,[1]能源!A:A,D5,[1]能源!B:B,"Gas 煤气费")+SUMIFS([1]能源!C:C,[1]能源!A:A,D5,[1]能源!B:B,"Oil 燃油费") -> #VALUE! | BA5: =SUMIFS([1]能源!C:C,[1]能源!A:A,D5,[1]能源!B:B,"Heating 暖气") -> #VALUE! | BB5: =SUM(AX5:BA5) -> #VALUE! | BC5: =BB5/F5 -> #VALUE! | BD5: {=INDIRECT($B5&"!M101")-SUM(AX5:BA5)} -> #VALUE! | BG5: {=INDIRECT($B5&"!M119")} -> 0 | BI5: {=INDIRECT($B5&"!M116")} -> 418282.09 | BK5: {=INDIRECT($B5&"!M123")} -> 103771.04 | BM5: {=INDIRECT($B5&"!M117")} -> 0 | BN5: {=INDIRECT($B5&"!M118")+INDIRECT($B5&"!M120")} -> 3.84 | BP5: {=-INDIRECT($B5&"!M114")+INDIRECT($B5&"!M115")-BG5-BI5-BM5-BN5} -> -3.2596148e-11
A6: 滁州酒店 | B6: 滁州 | C6: 滁州酒店 | D6: 滁州碧桂园凤凰酒店管理有限公司 | E6: =SUM(G6:M6)-F6 -> 0 | F6: {=INDIRECT($B6&"!M16")} -> 129030.87 | G6: {=INDIRECT($B6&"!M43")} -> 55218.59 | H6: {=INDIRECT($B6&"!M52")+INDIRECT($B6&"!M53")} -> 60025.47 | I6: {=INDIRECT($B6&"!M55")} -> 1226.42 | J6: {=INDIRECT($B6&"!M54")} -> 11223.01 | K6: {=INDIRECT($B6&"!M75")} -> 1070.34 | L6: {=INDIRECT($B6&"!M69")+INDIRECT($B6&"!M70")} -> 0 | M6: {=INDIRECT($B6&"!M77")-INDIRECT($B6&"!M75")-INDIRECT($B6&"!M69")-INDIRECT($B6&"!M70")} -> 267.04 | N6: {=INDIRECT($B6&"!M115")} -> 236.25 | O6: =SUM(G6:N6) -> 129267.12 | P6: {=INDIRECT($B6&"!M31")} -> 249064.22 | Q6: =P6/F6 -> 1.9302685 | R6: {=INDIRECT($B6&"!M34")} -> 137540.37 | S6: =R6/F6 -> 1.0659493 | T6: {=INDIRECT($B6&"!M38")} -> 5609.22 | V6: =T6/F6 -> 0.043471923 | W6: {=INDIRECT($B6&"!M36")} -> 16743.95 | X6: =W6/F6 -> 0.12976701 | Y6: =SUMIFS([1]客房!D:D,[1]客房!B:B,D6,[1]客房!C:C,"Reservation Fees 预订成本") -> #VALUE! | Z6: =SUMIFS([1]客房!D:D,[1]客房!B:B,D6,[1]客房!C:C," Total Cost of Sales 总销售成本") -> #VALUE! | AA6: {=INDIRECT($B6&"!M44")+INDIRECT($B6&"!M45")} -> 67920.54 | AB6: =SUMIFS([1]客房!D:D,[1]客房!B:B,D6,[1]客房!C:C,"Laundry 洗涤费") -> #VALUE! | AC6: {=INDIRECT($B6&"!M46")-Y6-Z6-AB6} -> #VALUE! | AD6: {=INDIRECT($B6&"!M47")-SUM(Y6:AC6)} -> #VALUE! | AF6: {=INDIRECT($B6&"!M60")} -> 37828.45 | AG6: {=INDIRECT($B6&"!M61")+INDIRECT($B6&"!M62")} -> 73474.97 | AH6: =SUMIFS([1]餐饮!D:D,[1]餐饮!B:B,D6,[1]餐饮!C:C,"Laundry 洗涤费") -> #VALUE! | AI6: {=INDIRECT($B6&"!M63")-AH6} -> #VALUE! | AJ6: {=INDIRECT($B6&"!M64")-SUM(AE6:AI6)} -> #VALUE! | AK6: =SUMIFS([1]新零售!D:D,[1]新零售!B:B,D6,[1]新零售!C:C,"Total Cost of Sales 总销售成本") -> #VALUE! | AL6: =SUMIFS([1]康乐温泉!C:C,[1]康乐温泉!A:A,D6,[1]康乐温泉!B:B,"Total Cost of Sales 总销售成本")+SUMIFS([1]康乐温泉!C:C,[1]康乐温泉!A:A,D6,[1]康乐温泉!B:B,"Total Other Expenses 其他费用合计") -> #VALUE! | AP6: {=INDIRECT($B6&"!M91")+INDIRECT($B6&"!M92")} -> 40424.31 | AQ6: {=INDIRECT($B6&"!M93")+INDIRECT($B6&"!M94")+INDIRECT($B6&"!M95")+INDIRECT($B6&"!M96")} -> 23036.61 | AR6: {=INDIRECT($B6&"!M98")+INDIRECT($B6&"!M99")} -> 28150.53 | AT6: {=INDIRECT($B6&"!M100")} -> 2906.95 | AU6: {=INDIRECT($B6&"!M103")+INDIRECT($B6&"!M104")} -> 39093.87 | AV6: {=INDIRECT($B6&"!M36")} -> 16743.95 | AW6: {=INDIRECT($B6&"!M105")-AV6} -> -914.79 | AX6: =SUMIFS([1]能源!C:C,[1]能源!A:A,D6,[1]能源!B:B,"Electricity 电费") -> #VALUE! | AY6: =SUMIFS([1]能源!C:C,[1]能源!A:A,D6,[1]能源!B:B,"Steam 蒸汽费")+SUMIFS([1]能源!C:C,[1]能源!A:A,D6,[1]能源!B:B,"Geothermal water 地热水")+SUMIFS([1]能源!C:C,[1]能源!A:A,D6,[1]能源!B:B,"Water 水费") -> #VALUE! | AZ6: =SUMIFS([1]能源!C:C,[1]能源!A:A,D6,[1]能源!B:B,"Gas 煤气费")+SUMIFS([1]能源!C:C,[1]能源!A:A,D6,[1]能源!B:B,"Oil 燃油费") -> #VALUE! | BA6: =SUMIFS([1]能源!C:C,[1]能源!A:A,D6,[1]能源!B:B,"Heating 暖气") -> #VALUE! | BB6: =SUM(AX6:BA6) -> #VALUE! | BC6: =BB6/F6 -> #VALUE! | BD6: {=INDIRECT($B6&"!M101")-SUM(AX6:BA6)} -> #VALUE! | BG6: {=INDIRECT($B6&"!M119")} -> 0 | BI6: {=INDIRECT($B6&"!M116")} -> 146702.15 | BK6: {=INDIRECT($B6&"!M123")} -> 0 | BM6: {=INDIRECT($B6&"!M117")} -> 0 | BN6: {=INDIRECT($B6&"!M118")+INDIRECT($B6&"!M120")} -> 0 | BP6: {=-INDIRECT($B6&"!M114")+INDIRECT($B6&"!M115")-BG6-BI6-BM6-BN6} -> 0
A7: 武汉酒店 | B7: 武汉 | C7: 武汉酒店 | D7: 武汉市碧桂园凤凰酒店有限公司 | E7: =SUM(G7:M7)-F7 -> 0 | F7: {=INDIRECT($B7&"!M16")} -> 1136568.8 | G7: {=INDIRECT($B7&"!M43")} -> 512343.26 | H7: {=INDIRECT($B7&"!M52")+INDIRECT($B7&"!M53")} -> 506449.08 | I7: {=INDIRECT($B7&"!M55")} -> 72357.85 | J7: {=INDIRECT($B7&"!M54")} -> 7236.3 | K7: {=INDIRECT($B7&"!M75")} -> 36757.13 | L7: {=INDIRECT($B7&"!M69")+INDIRECT($B7&"!M70")} -> 0 | M7: {=INDIRECT($B7&"!M77")-INDIRECT($B7&"!M75")-INDIRECT($B7&"!M69")-INDIRECT($B7&"!M70")} -> 1425.21 | N7: {=INDIRECT($B7&"!M115")} -> 201.07 | O7: =SUM(G7:N7) -> 1136769.9 | P7: {=INDIRECT($B7&"!M31")} -> 539485.22 | Q7: =P7/F7 -> 0.47466128 | R7: {=INDIRECT($B7&"!M34")} -> 132997.87 | S7: =R7/F7 -> 0.117017 | T7: {=INDIRECT($B7&"!M38")} -> 16269.54 | V7: =T7/F7 -> 0.01431461 | W7: {=INDIRECT($B7&"!M36")} -> 18239.38 | X7: =W7/F7 -> 0.016047757 | Y7: =SUMIFS([1]客房!D:D,[1]客房!B:B,D7,[1]客房!C:C,"Reservation Fees 预订成本") -> #VALUE! | Z7: =SUMIFS([1]客房!D:D,[1]客房!B:B,D7,[1]客房!C:C," Total Cost of Sales 总销售成本") -> #VALUE! | AA7: {=INDIRECT($B7&"!M44")+INDIRECT($B7&"!M45")} -> 107117.7 | AB7: =SUMIFS([1]客房!D:D,[1]客房!B:B,D7,[1]客房!C:C,"Laundry 洗涤费") -> #VALUE! | AC7: {=INDIRECT($B7&"!M46")-Y7-Z7-AB7} -> #VALUE! | AD7: {=INDIRECT($B7&"!M47")-SUM(Y7:AC7)} -> #VALUE! | AF7: {=INDIRECT($B7&"!M60")} -> 236757.11 | AG7: {=INDIRECT($B7&"!M61")+INDIRECT($B7&"!M62")} -> 182939.64 | AH7: =SUMIFS([1]餐饮!D:D,[1]餐饮!B:B,D7,[1]餐饮!C:C,"Laundry 洗涤费") -> #VALUE! | AI7: {=INDIRECT($B7&"!M63")-AH7} -> #VALUE! | AJ7: {=INDIRECT($B7&"!M64")-SUM(AE7:AI7)} -> #VALUE! | AK7: =SUMIFS([1]新零售!D:D,[1]新零售!B:B,D7,[1]新零售!C:C,"Total Cost of Sales 总销售成本") -> #VALUE! | AL7: =SUMIFS([1]康乐温泉!C:C,[1]康乐温泉!A:A,D7,[1]康乐温泉!B:B,"Total Cost of Sales 总销售成本")+SUMIFS([1]康乐温泉!C:C,[1]康乐温泉!A:A,D7,[1]康乐温泉!B:B,"Total Other Expenses 其他费用合计") -> #VALUE! | AP7: {=INDIRECT($B7&"!M91")+INDIRECT($B7&"!M92")} -> 103554.28 | AQ7: {=INDIRECT($B7&"!M93")+INDIRECT($B7&"!M94")+INDIRECT($B7&"!M95")+INDIRECT($B7&"!M96")} -> 25160.42 | AR7: {=INDIRECT($B7&"!M98")+INDIRECT($B7&"!M99")} -> 79186.35 | AT7: {=INDIRECT($B7&"!M100")} -> 15316.58 | AU7: {=INDIRECT($B7&"!M103")+INDIRECT($B7&"!M104")} -> 66687.25 | AV7: {=INDIRECT($B7&"!M36")} -> 18239.38 | AW7: {=INDIRECT($B7&"!M105")-AV7} -> 4448.07 | AX7: =SUMIFS([1]能源!C:C,[1]能源!A:A,D7,[1]能源!B:B,"Electricity 电费") -> #VALUE! | AY7: =SUMIFS([1]能源!C:C,[1]能源!A:A,D7,[1]能源!B:B,"Steam 蒸汽费")+SUMIFS([1]能源!C:C,[1]能源!A:A,D7,[1]能源!B:B,"Geothermal water 地热水")+SUMIFS([1]能源!C:C,[1]能源!A:A,D7,[1]能源!B:B,"Water 水费") -> #VALUE! | AZ7: =SUMIFS([1]能源!C:C,[1]能源!A:A,D7,[1]能源!B:B,"Gas 煤气费")+SUMIFS([1]能源!C:C,[1]能源!A:A,D7,[1]能源!B:B,"Oil 燃油费") -> #VALUE! | BA7: =SUMIFS([1]能源!C:C,[1]能源!A:A,D7,[1]能源!B:B,"Heating 暖气") -> #VALUE! | BB7: =SUM(AX7:BA7) -> #VALUE! | BC7: =BB7/F7 -> #VALUE! | BD7: {=INDIRECT($B7&"!M101")-SUM(AX7:BA7)} -> #VALUE! | BG7: {=INDIRECT($B7&"!M119")} -> 0 | BI7: {=INDIRECT($B7&"!M116")} -> 0 | BK7: {=INDIRECT($B7&"!M123")} -> 0 | BM7: {=INDIRECT($B7&"!M117")} -> 139147.03 | BN7: {=INDIRECT($B7&"!M118")+INDIRECT($B7&"!M120")} -> 0 | BP7: {=-INDIRECT($B7&"!M114")+INDIRECT($B7&"!M115")-BG7-BI7-BM7-BN7} -> 0
A8: 海南临高 | B8: 临高 | C8: 临高酒店 | D8: 临高金碧酒店管理有限公司 | E8: =SUM(G8:M8)-F8 -> #REF! | F8: {=INDIRECT($B8&"!M16")} -> #REF! | G8: {=INDIRECT($B8&"!M43")} -> #REF! | H8: {=INDIRECT($B8&"!M52")+INDIRECT($B8&"!M53")} -> #REF! | I8: {=INDIRECT($B8&"!M55")} -> #REF! | J8: {=INDIRECT($B8&"!M54")} -> #REF! | K8: {=INDIRECT($B8&"!M75")} -> #REF! | L8: {=INDIRECT($B8&"!M69")+INDIRECT($B8&"!M70")} -> #REF! | M8: {=INDIRECT($B8&"!M77")-INDIRECT($B8&"!M75")-INDIRECT($B8&"!M69")-INDIRECT($B8&"!M70")} -> #REF! | N8: {=INDIRECT($B8&"!M115")} -> #REF! | O8: =SUM(G8:N8) -> #REF! | P8: {=INDIRECT($B8&"!M31")} -> #REF! | Q8: =P8/F8 -> #REF! | R8: {=INDIRECT($B8&"!M34")} -> #REF! | S8: =R8/F8 -> #REF! | T8: {=INDIRECT($B8&"!M38")} -> #REF! | V8: =T8/F8 -> #REF! | W8: {=INDIRECT($B8&"!M36")} -> #REF! | X8: =W8/F8 -> #REF! | Y8: =SUMIFS([1]客房!D:D,[1]客房!B:B,D8,[1]客房!C:C,"Reservation Fees 预订成本")+SUMIFS([1]客房!D:D,[1]客房!B:B,"海南临高碧桂园房地产开发有限公司酒店分公司",[1]客房!C:C,"Reservation Fees 预订成本") -> #VALUE! | Z8: =SUMIFS([1]客房!D:D,[1]客房!B:B,D8,[1]客房!C:C," Total Cost of Sales 总销售成本")+SUMIFS([1]客房!D:D,[1]客房!B:B,"海南临高碧桂园房地产开发有限公司酒店分公司",[1]客房!C:C," Total Cost of Sales 总销售成本") -> #VALUE! | AA8: {=INDIRECT($B8&"!M44")+INDIRECT($B8&"!M45")} -> #REF! | AB8: =SUMIFS([1]客房!D:D,[1]客房!B:B,D8,[1]客房!C:C,"Laundry 洗涤费")+SUMIFS([1]客房!D:D,[1]客房!B:B,"海南临高碧桂园房地产开发有限公司酒店分公司",[1]客房!C:C,"Laundry 洗涤费") -> #VALUE! | AC8: {=INDIRECT($B8&"!M46")-Y8-Z8-AB8} -> #REF! | AD8: {=INDIRECT($B8&"!M47")-SUM(Y8:AC8)} -> #REF! | AF8: {=INDIRECT($B8&"!M60")} -> #REF! | AG8: {=INDIRECT($B8&"!M61")+INDIRECT($B8&"!M62")} -> #REF! | AH8: =SUMIFS([1]餐饮!D:D,[1]餐饮!B:B,D8,[1]餐饮!C:C,"Laundry 洗涤费")+SUMIFS([1]餐饮!D:D,[1]餐饮!B:B,"海南临高碧桂园房地产开发有限公司酒店分公司",[1]餐饮!C:C,"Laundry 洗涤费") -> #VALUE! | AI8: {=INDIRECT($B8&"!M63")-AH8} -> #REF! | AJ8: {=INDIRECT($B8&"!M64")-SUM(AE8:AI8)} -> #REF! | AK8: =SUMIFS([1]新零售!D:D,[1]新零售!B:B,D8,[1]新零售!C:C,"Total Cost of Sales 总销售成本")+SUMIFS([1]新零售!D:D,[1]新零售!B:B,"海南临高碧桂园房地产开发有限公司酒店分公司",[1]新零售!C:C,"Total Cost of Sales 总销售成本") -> #VALUE! | AL8: =SUMIFS([1]康乐温泉!C:C,[1]康乐温泉!A:A,D8,[1]康乐温泉!B:B,"Total Cost of Sales 总销售成本")+SUMIFS([1]康乐温泉!C:C,[1]康乐温泉!A:A,D8,[1]康乐温泉!B:B,"Total Other Expenses 其他费用合计")+SUMIFS([1]康乐温泉!C:C,[1]康乐温泉!A:A,"海南临高碧桂园房地产开发有限公司酒店分公司",[1]康乐温泉!B:B,"Total Cost of Sales 总销售成本")+SUMIFS([1]康乐温泉!C:C,[1]康乐温泉!A:A,"海南临高碧桂园房地产开发有限公司酒店分公司",[1]康乐温泉!B:B,"Total Other Expenses 其他费用合计") -> #VALUE! | AP8: {=INDIRECT($B8&"!M91")+INDIRECT($B8&"!M92")} -> #REF! | AQ8: {=INDIRECT($B8&"!M93")+INDIRECT($B8&"!M94")+INDIRECT($B8&"!M95")+INDIRECT($B8&"!M96")} -> #REF! | AR8: {=INDIRECT($B8&"!M98")+INDIRECT($B8&"!M99")} -> #REF! | AT8: {=INDIRECT($B8&"!M100")} -> #REF! | AU8: {=INDIRECT($B8&"!M103")+INDIRECT($B8&"!M104")} -> #REF! | AV8: {=INDIRECT($B8&"!M36")} -> #REF! | AW8: {=INDIRECT($B8&"!M105")-AV8} -> #REF! | AX8: =SUMIFS([1]能源!C:C,[1]能源!A:A,D8,[1]能源!B:B,"Electricity 电费")+SUMIFS([1]能源!C:C,[1]能源!A:A,"海南临高碧桂园房地产开发有限公司酒店分公司",[1]能源!B:B,"Electricity 电费") -> #VALUE! | AY8: =SUMIFS([1]能源!C:C,[1]能源!A:A,D8,[1]能源!B:B,"Steam 蒸汽费")+SUMIFS([1]能源!C:C,[1]能源!A:A,D8,[1]能源!B:B,"Geothermal water 地热水")+SUMIFS([1]能源!C:C,[1]能源!A:A,D8,[1]能源!B:B,"Water 水费")+SUMIFS([1]能源!C:C,[1]能源!A:A,"海南临高碧桂园房地产开发有限公司酒店分公司",[1]能源!B:B,"Steam 蒸汽费")+SUMIFS([1]能源!C:C,[1]能源!A:A,"海南临高碧桂园房地产开发有限公司酒店分公司",[1]能源!B:B,"Geothermal water 地热水")+SUMIFS([1]能源!C:C,[1]能源!A:A,"海南临高碧桂园房地产开发有限公司酒店分公司",[1]能源!B:B,"Water 水费") -> #VALUE! | AZ8: =SUMIFS([1]能源!C:C,[1]能源!A:A,D8,[1]能源!B:B,"Gas 煤气费")+SUMIFS([1]能源!C:C,[1]能源!A:A,D8,[1]能源!B:B,"Oil 燃油费")+SUMIFS([1]能源!C:C,[1]能源!A:A,"海南临高碧桂园房地产开发有限公司酒店分公司",[1]能源!B:B,"Gas 煤气费")+SUMIFS([1]能源!C:C,[1]能源!A:A,"海南临高碧桂园房地产开发有限公司酒店分公司",[1]能源!B:B,"Oil 燃油费") -> #VALUE! | BA8: =SUMIFS([1]能源!C:C,[1]能源!A:A,D8,[1]能源!B:B,"Heating 暖气")+SUMIFS([1]能源!C:C,[1]能源!A:A,"海南临高碧桂园房地产开发有限公司酒店分公司",[1]能源!B:B,"Heating 暖气") -> #VALUE! | BB8: =SUM(AX8:BA8) -> #VALUE! | BC8: =BB8/F8 -> #VALUE! | BD8: {=INDIRECT($B8&"!M101")-SUM(AX8:BA8)} -> #REF! | BG8: {=INDIRECT($B8&"!M119")} -> #REF! | BI8: {=INDIRECT($B8&"!M116")} -> #REF! | BK8: {=INDIRECT($B8&"!M123")} -> #REF! | BM8: {=INDIRECT($B8&"!M117")} -> #REF! | BN8: {=INDIRECT($B8&"!M118")+INDIRECT($B8&"!M120")} -> #REF! | BP8: {=-INDIRECT($B8&"!M114")+INDIRECT($B8&"!M115")-BG8-BI8-BM8-BN8} -> #REF!
A9: 三水酒店 | B9: 三水 | C9: 三水酒店 | D9: 佛山市芯林瑚酒店管理有限公司 | E9: =SUM(G9:M9)-F9 -> #REF! | F9: {=INDIRECT($B9&"!M16")} -> #REF! | G9: {=INDIRECT($B9&"!M43")} -> #REF! | H9: {=INDIRECT($B9&"!M52")+INDIRECT($B9&"!M53")} -> #REF! | I9: {=INDIRECT($B9&"!M55")} -> #REF! | J9: {=INDIRECT($B9&"!M54")} -> #REF! | K9: {=INDIRECT($B9&"!M75")} -> #REF! | L9: {=INDIRECT($B9&"!M69")+INDIRECT($B9&"!M70")} -> #REF! | M9: {=INDIRECT($B9&"!M77")-INDIRECT($B9&"!M75")-INDIRECT($B9&"!M69")-INDIRECT($B9&"!M70")} -> #REF! | N9: {=INDIRECT($B9&"!M115")} -> #REF! | O9: =SUM(G9:N9) -> #REF! | P9: {=INDIRECT($B9&"!M31")} -> #REF! | Q9: =P9/F9 -> #REF! | R9: {=INDIRECT($B9&"!M34")} -> #REF! | S9: =R9/F9 -> #REF! | T9: {=INDIRECT($B9&"!M38")} -> #REF! | V9: =T9/F9 -> #REF! | W9: {=INDIRECT($B9&"!M36")} -> #REF! | X9: =W9/F9 -> #REF! | Y9: =SUMIFS([1]客房!D:D,[1]客房!B:B,D9,[1]客房!C:C,"Reservation Fees 预订成本") -> #VALUE! | Z9: =SUMIFS([1]客房!D:D,[1]客房!B:B,D9,[1]客房!C:C," Total Cost of Sales 总销售成本") -> #VALUE! | AA9: {=INDIRECT($B9&"!M44")+INDIRECT($B9&"!M45")} -> #REF! | AB9: =SUMIFS([1]客房!D:D,[1]客房!B:B,D9,[1]客房!C:C,"Laundry 洗涤费") -> #VALUE! | AC9: {=INDIRECT($B9&"!M46")-Y9-Z9-AB9} -> #REF! | AD9: {=INDIRECT($B9&"!M47")-SUM(Y9:AC9)} -> #REF! | AF9: {=INDIRECT($B9&"!M60")} -> #REF! | AG9: {=INDIRECT($B9&"!M61")+INDIRECT($B9&"!M62")} -> #REF! | AH9: =SUMIFS([1]餐饮!D:D,[1]餐饮!B:B,D9,[1]餐饮!C:C,"Laundry 洗涤费") -> #VALUE! | AI9: {=INDIRECT($B9&"!M63")-AH9} -> #REF! | AJ9: {=INDIRECT($B9&"!M64")-SUM(AE9:AI9)} -> #REF! | AK9: =SUMIFS([1]新零售!D:D,[1]新零售!B:B,D9,[1]新零售!C:C,"Total Cost of Sales 总销售成本") -> #VALUE! | AL9: =SUMIFS([1]康乐温泉!C:C,[1]康乐温泉!A:A,D9,[1]康乐温泉!B:B,"Total Cost of Sales 总销售成本")+SUMIFS([1]康乐温泉!C:C,[1]康乐温泉!A:A,D9,[1]康乐温泉!B:B,"Total Other Expenses 其他费用合计") -> #VALUE! | AP9: {=INDIRECT($B9&"!M91")+INDIRECT($B9&"!M92")} -> #REF! | AQ9: {=INDIRECT($B9&"!M93")+INDIRECT($B9&"!M94")+INDIRECT($B9&"!M95")+INDIRECT($B9&"!M96")} -> #REF! | AR9: {=INDIRECT($B9&"!M98")+INDIRECT($B9&"!M99")} -> #REF! | AT9: {=INDIRECT($B9&"!M100")} -> #REF! | AU9: {=INDIRECT($B9&"!M103")+INDIRECT($B9&"!M104")} -> #REF! | AV9: {=INDIRECT($B9&"!M36")} -> #REF! | AW9: {=INDIRECT($B9&"!M105")-AV9} -> #REF! | AX9: =SUMIFS([1]能源!C:C,[1]能源!A:A,D9,[1]能源!B:B,"Electricity 电费") -> #VALUE! | AY9: =SUMIFS([1]能源!C:C,[1]能源!A:A,D9,[1]能源!B:B,"Steam 蒸汽费")+SUMIFS([1]能源!C:C,[1]能源!A:A,D9,[1]能源!B:B,"Geothermal water 地热水")+SUMIFS([1]能源!C:C,[1]能源!A:A,D9,[1]能源!B:B,"Water 水费") -> #VALUE! | AZ9: =SUMIFS([1]能源!C:C,[1]能源!A:A,D9,[1]能源!B:B,"Gas 煤气费")+SUMIFS([1]能源!C:C,[1]能源!A:A,D9,[1]能源!B:B,"Oil 燃油费") -> #VALUE! | BA9: =SUMIFS([1]能源!C:C,[1]能源!A:A,D9,[1]能源!B:B,"Heating 暖气") -> #VALUE! | BB9: =SUM(AX9:BA9) -> #VALUE! | BC9: =BB9/F9 -> #VALUE! | BD9: {=INDIRECT($B9&"!M101")-SUM(AX9:BA9)} -> #REF! | BG9: {=INDIRECT($B9&"!M119")} -> #REF! | BI9: {=INDIRECT($B9&"!M116")} -> #REF! | BK9: {=INDIRECT($B9&"!M123")} -> #REF! | BM9: {=INDIRECT($B9&"!M117")} -> #REF! | BN9: {=INDIRECT($B9&"!M118")+INDIRECT($B9&"!M120")} -> #REF! | BP9: {=-INDIRECT($B9&"!M114")+INDIRECT($B9&"!M115")-BG9-BI9-BM9-BN9} -> #REF!
A10: 泰州酒店 | B10: 泰州 | C10: 泰州酒店 | D10: 泰州市碧桂园凤凰酒店有限公司 | E10: =SUM(G10:M10)-F10 -> #REF! | F10: {=INDIRECT($B10&"!M16")} -> #REF! | G10: {=INDIRECT($B10&"!M43")} -> #REF! | H10: {=INDIRECT($B10&"!M52")+INDIRECT($B10&"!M53")} -> #REF! | I10: {=INDIRECT($B10&"!M55")} -> #REF! | J10: {=INDIRECT($B10&"!M54")} -> #REF! | K10: {=INDIRECT($B10&"!M75")} -> #REF! | L10: {=INDIRECT($B10&"!M69")+INDIRECT($B10&"!M70")} -> #REF! | M10: {=INDIRECT($B10&"!M77")-INDIRECT($B10&"!M75")-INDIRECT($B10&"!M69")-INDIRECT($B10&"!M70")} -> #REF! | N10: {=INDIRECT($B10&"!M115")} -> #REF! | O10: =SUM(G10:N10) -> #REF! | P10: {=INDIRECT($B10&"!M31")} -> #REF! | Q10: =P10/F10 -> #REF! | R10: {=INDIRECT($B10&"!M34")} -> #REF! | S10: =R10/F10 -> #REF! | T10: {=INDIRECT($B10&"!M38")} -> #REF! | V10: =T10/F10 -> #REF! | W10: {=INDIRECT($B10&"!M36")} -> #REF! | X10: =W10/F10 -> #REF! | Y10: =SUMIFS([1]客房!D:D,[1]客房!B:B,D10,[1]客房!C:C,"Reservation Fees 预订成本") -> #VALUE! | Z10: =SUMIFS([1]客房!D:D,[1]客房!B:B,D10,[1]客房!C:C," Total Cost of Sales 总销售成本") -> #VALUE! | AA10: {=INDIRECT($B10&"!M44")+INDIRECT($B10&"!M45")} -> #REF! | AB10: =SUMIFS([1]客房!D:D,[1]客房!B:B,D10,[1]客房!C:C,"Laundry 洗涤费") -> #VALUE! | AC10: {=INDIRECT($B10&"!M46")-Y10-Z10-AB10} -> #REF! | AD10: {=INDIRECT($B10&"!M47")-SUM(Y10:AC10)} -> #REF! | AF10: {=INDIRECT($B10&"!M60")} -> #REF! | AG10: {=INDIRECT($B10&"!M61")+INDIRECT($B10&"!M62")} -> #REF! | AH10: =SUMIFS([1]餐饮!D:D,[1]餐饮!B:B,D10,[1]餐饮!C:C,"Laundry 洗涤费") -> #VALUE! | AI10: {=INDIRECT($B10&"!M63")-AH10} -> #REF! | AJ10: {=INDIRECT($B10&"!M64")-SUM(AE10:AI10)} -> #REF! | AK10: =SUMIFS([1]新零售!D:D,[1]新零售!B:B,D10,[1]新零售!C:C,"Total Cost of Sales 总销售成本") -> #VALUE! | AL10: =SUMIFS([1]康乐温泉!C:C,[1]康乐温泉!A:A,D10,[1]康乐温泉!B:B,"Total Cost of Sales 总销售成本")+SUMIFS([1]康乐温泉!C:C,[1]康乐温泉!A:A,D10,[1]康乐温泉!B:B,"Total Other Expenses 其他费用合计") -> #VALUE! | AP10: {=INDIRECT($B10&"!M91")+INDIRECT($B10&"!M92")} -> #REF! | AQ10: {=INDIRECT($B10&"!M93")+INDIRECT($B10&"!M94")+INDIRECT($B10&"!M95")+INDIRECT($B10&"!M96")} -> #REF! | AR10: {=INDIRECT($B10&"!M98")+INDIRECT($B10&"!M99")} -> #REF! | AT10: {=INDIRECT($B10&"!M100")} -> #REF! | AU10: {=INDIRECT($B10&"!M103")+INDIRECT($B10&"!M104")} -> #REF! | AV10: {=INDIRECT($B10&"!M36")} -> #REF! | AW10: {=INDIRECT($B10&"!M105")-AV10} -> #REF! | AX10: =SUMIFS([1]能源!C:C,[1]能源!A:A,D10,[1]能源!B:B,"Electricity 电费") -> #VALUE! | AY10: =SUMIFS([1]能源!C:C,[1]能源!A:A,D10,[1]能源!B:B,"Steam 蒸汽费")+SUMIFS([1]能源!C:C,[1]能源!A:A,D10,[1]能源!B:B,"Geothermal water 地热水")+SUMIFS([1]能源!C:C,[1]能源!A:A,D10,[1]能源!B:B,"Water 水费") -> #VALUE! | AZ10: =SUMIFS([1]能源!C:C,[1]能源!A:A,D10,[1]能源!B:B,"Gas 煤气费")+SUMIFS([1]能源!C:C,[1]能源!A:A,D10,[1]能源!B:B,"Oil 燃油费") -> #VALUE! | BA10: =SUMIFS([1]能源!C:C,[1]能源!A:A,D10,[1]能源!B:B,"Heating 暖气") -> #VALUE! | BB10: =SUM(AX10:BA10) -> #VALUE! | BC10: =BB10/F10 -> #VALUE! | BD10: {=INDIRECT($B10&"!M101")-SUM(AX10:BA10)} -> #REF! | BG10: {=INDIRECT($B10&"!M119")} -> #REF! | BI10: {=INDIRECT($B10&"!M116")} -> #REF! | BK10: {=INDIRECT($B10&"!M123")} -> #REF! | BM10: {=INDIRECT($B10&"!M117")} -> #REF! | BN10: {=INDIRECT($B10&"!M118")+INDIRECT($B10&"!M120")} -> #REF! | BP10: {=-INDIRECT($B10&"!M114")+INDIRECT($B10&"!M115")-BG10-BI10-BM10-BN10} -> #REF!
A11: 安庆酒店 | B11: 安庆 | C11: 安庆酒店 | D11: 安庆碧桂园凤凰酒店有限公司 | E11: =SUM(G11:M11)-F11 -> #REF! | F11: {=INDIRECT($B11&"!M16")} -> #REF! | G11: {=INDIRECT($B11&"!M43")} -> #REF! | H11: {=INDIRECT($B11&"!M52")+INDIRECT($B11&"!M53")} -> #REF! | I11: {=INDIRECT($B11&"!M55")} -> #REF! | J11: {=INDIRECT($B11&"!M54")} -> #REF! | K11: {=INDIRECT($B11&"!M75")} -> #REF! | L11: {=INDIRECT($B11&"!M69")+INDIRECT($B11&"!M70")} -> #REF! | M11: {=INDIRECT($B11&"!M77")-INDIRECT($B11&"!M75")-INDIRECT($B11&"!M69")-INDIRECT($B11&"!M70")} -> #REF! | N11: {=INDIRECT($B11&"!M115")} -> #REF! | O11: =SUM(G11:N11) -> #REF! | P11: {=INDIRECT($B11&"!M31")} -> #REF! | Q11: =P11/F11 -> #REF! | R11: {=INDIRECT($B11&"!M34")} -> #REF! | S11: =R11/F11 -> #REF! | T11: {=INDIRECT($B11&"!M38")} -> #REF! | V11: =T11/F11 -> #REF! | W11: {=INDIRECT($B11&"!M36")} -> #REF! | X11: =W11/F11 -> #REF! | Y11: =SUMIFS([1]客房!D:D,[1]客房!B:B,D11,[1]客房!C:C,"Reservation Fees 预订成本") -> #VALUE! | Z11: =SUMIFS([1]客房!D:D,[1]客房!B:B,D11,[1]客房!C:C," Total Cost of Sales 总销售成本") -> #VALUE! | AA11: {=INDIRECT($B11&"!M44")+INDIRECT($B11&"!M45")} -> #REF! | AB11: =SUMIFS([1]客房!D:D,[1]客房!B:B,D11,[1]客房!C:C,"Laundry 洗涤费") -> #VALUE! | AC11: {=INDIRECT($B11&"!M46")-Y11-Z11-AB11} -> #REF! | AD11: {=INDIRECT($B11&"!M47")-SUM(Y11:AC11)} -> #REF! | AF11: {=INDIRECT($B11&"!M60")} -> #REF! | AG11: {=INDIRECT($B11&"!M61")+INDIRECT($B11&"!M62")} -> #REF! | AH11: =SUMIFS([1]餐饮!D:D,[1]餐饮!B:B,D11,[1]餐饮!C:C,"Laundry 洗涤费") -> #VALUE! | AI11: {=INDIRECT($B11&"!M63")-AH11} -> #REF! | AJ11: {=INDIRECT($B11&"!M64")-SUM(AE11:AI11)} -> #REF! | AK11: =SUMIFS([1]新零售!D:D,[1]新零售!B:B,D11,[1]新零售!C:C,"Total Cost of Sales 总销售成本") -> #VALUE! | AL11: =SUMIFS([1]康乐温泉!C:C,[1]康乐温泉!A:A,D11,[1]康乐温泉!B:B,"Total Cost of Sales 总销售成本")+SUMIFS([1]康乐温泉!C:C,[1]康乐温泉!A:A,D11,[1]康乐温泉!B:B,"Total Other Expenses 其他费用合计") -> #VALUE! | AP11: {=INDIRECT($B11&"!M91")+INDIRECT($B11&"!M92")} -> #REF! | AQ11: {=INDIRECT($B11&"!M93")+INDIRECT($B11&"!M94")+INDIRECT($B11&"!M95")+INDIRECT($B11&"!M96")} -> #REF! | AR11: {=INDIRECT($B11&"!M98")+INDIRECT($B11&"!M99")} -> #REF! | AT11: {=INDIRECT($B11&"!M100")} -> #REF! | AU11: {=INDIRECT($B11&"!M103")+INDIRECT($B11&"!M104")} -> #REF! | AV11: {=INDIRECT($B11&"!M36")} -> #REF! | AW11: {=INDIRECT($B11&"!M105")-AV11} -> #REF! | AX11: =SUMIFS([1]能源!C:C,[1]能源!A:A,D11,[1]能源!B:B,"Electricity 电费") -> #VALUE! | AY11: =SUMIFS([1]能源!C:C,[1]能源!A:A,D11,[1]能源!B:B,"Steam 蒸汽费")+SUMIFS([1]能源!C:C,[1]能源!A:A,D11,[1]能源!B:B,"Geothermal water 地热水")+SUMIFS([1]能源!C:C,[1]能源!A:A,D11,[1]能源!B:B,"Water 水费") -> #VALUE! | AZ11: =SUMIFS([1]能源!C:C,[1]能源!A:A,D11,[1]能源!B:B,"Gas 煤气费")+SUMIFS([1]能源!C:C,[1]能源!A:A,D11,[1]能源!B:B,"Oil 燃油费") -> #VALUE! | BA11: =SUMIFS([1]能源!C:C,[1]能源!A:A,D11,[1]能源!B:B,"Heating 暖气") -> #VALUE! | BB11: =SUM(AX11:BA11) -> #VALUE! | BC11: =BB11/F11 -> #VALUE! | BD11: {=INDIRECT($B11&"!M101")-SUM(AX11:BA11)} -> #REF! | BG11: {=INDIRECT($B11&"!M119")} -> #REF! | BI11: {=INDIRECT($B11&"!M116")} -> #REF! | BK11: {=INDIRECT($B11&"!M123")} -> #REF! | BM11: {=INDIRECT($B11&"!M117")} -> #REF! | BN11: {=INDIRECT($B11&"!M118")+INDIRECT($B11&"!M120")} -> #REF! | BP11: {=-INDIRECT($B11&"!M114")+INDIRECT($B11&"!M115")-BG11-BI11-BM11-BN11} -> #REF!
A12: 张家界酒店 | B12: 张家界 | C12: 张家界酒店 | D12: 张家界碧桂园凤凰酒店管理有限公司 | E12: =SUM(G12:M12)-F12 -> #REF! | F12: {=INDIRECT($B12&"!M16")} -> #REF! | G12: {=INDIRECT($B12&"!M43")} -> #REF! | H12: {=INDIRECT($B12&"!M52")+INDIRECT($B12&"!M53")} -> #REF! | I12: {=INDIRECT($B12&"!M55")} -> #REF! | J12: {=INDIRECT($B12&"!M54")} -> #REF! | K12: {=INDIRECT($B12&"!M75")} -> #REF! | L12: {=INDIRECT($B12&"!M69")+INDIRECT($B12&"!M70")} -> #REF! | M12: {=INDIRECT($B12&"!M77")-INDIRECT($B12&"!M75")-INDIRECT($B12&"!M69")-INDIRECT($B12&"!M70")} -> #REF! | N12: {=INDIRECT($B12&"!M115")} -> #REF! | O12: =SUM(G12:N12) -> #REF! | P12: {=INDIRECT($B12&"!M31")} -> #REF! | Q12: =P12/F12 -> #REF! | R12: {=INDIRECT($B12&"!M34")} -> #REF! | S12: =R12/F12 -> #REF! | T12: {=INDIRECT($B12&"!M38")} -> #REF! | V12: =T12/F12 -> #REF! | W12: {=INDIRECT($B12&"!M36")} -> #REF! | X12: =W12/F12 -> #REF! | Y12: =SUMIFS([1]客房!D:D,[1]客房!B:B,D12,[1]客房!C:C,"Reservation Fees 预订成本") -> #VALUE! | Z12: =SUMIFS([1]客房!D:D,[1]客房!B:B,D12,[1]客房!C:C," Total Cost of Sales 总销售成本") -> #VALUE! | AA12: {=INDIRECT($B12&"!M44")+INDIRECT($B12&"!M45")} -> #REF! | AB12: =SUMIFS([1]客房!D:D,[1]客房!B:B,D12,[1]客房!C:C,"Laundry 洗涤费") -> #VALUE! | AC12: {=INDIRECT($B12&"!M46")-Y12-Z12-AB12} -> #REF! | AD12: {=INDIRECT($B12&"!M47")-SUM(Y12:AC12)} -> #REF! | AF12: {=INDIRECT($B12&"!M60")} -> #REF! | AG12: {=INDIRECT($B12&"!M61")+INDIRECT($B12&"!M62")} -> #REF! | AH12: =SUMIFS([1]餐饮!D:D,[1]餐饮!B:B,D12,[1]餐饮!C:C,"Laundry 洗涤费") -> #VALUE! | AI12: {=INDIRECT($B12&"!M63")-AH12} -> #REF! | AJ12: {=INDIRECT($B12&"!M64")-SUM(AE12:AI12)} -> #REF! | AK12: =SUMIFS([1]新零售!D:D,[1]新零售!B:B,D12,[1]新零售!C:C,"Total Cost of Sales 总销售成本") -> #VALUE! | AL12: =SUMIFS([1]康乐温泉!C:C,[1]康乐温泉!A:A,D12,[1]康乐温泉!B:B,"Total Cost of Sales 总销售成本")+SUMIFS([1]康乐温泉!C:C,[1]康乐温泉!A:A,D12,[1]康乐温泉!B:B,"Total Other Expenses 其他费用合计") -> #VALUE! | AP12: {=INDIRECT($B12&"!M91")+INDIRECT($B12&"!M92")} -> #REF! | AQ12: {=INDIRECT($B12&"!M93")+INDIRECT($B12&"!M94")+INDIRECT($B12&"!M95")+INDIRECT($B12&"!M96")} -> #REF! | AR12: {=INDIRECT($B12&"!M98")+INDIRECT($B12&"!M99")} -> #REF! | AT12: {=INDIRECT($B12&"!M100")} -> #REF! | AU12: {=INDIRECT($B12&"!M103")+INDIRECT($B12&"!M104")} -> #REF! | AV12: {=INDIRECT($B12&"!M36")} -> #REF! | AW12: {=INDIRECT($B12&"!M105")-AV12} -> #REF! | AX12: =SUMIFS([1]能源!C:C,[1]能源!A:A,D12,[1]能源!B:B,"Electricity 电费") -> #VALUE! | AY12: =SUMIFS([1]能源!C:C,[1]能源!A:A,D12,[1]能源!B:B,"Steam 蒸汽费")+SUMIFS([1]能源!C:C,[1]能源!A:A,D12,[1]能源!B:B,"Geothermal water 地热水")+SUMIFS([1]能源!C:C,[1]能源!A:A,D12,[1]能源!B:B,"Water 水费") -> #VALUE! | AZ12: =SUMIFS([1]能源!C:C,[1]能源!A:A,D12,[1]能源!B:B,"Gas 煤气费")+SUMIFS([1]能源!C:C,[1]能源!A:A,D12,[1]能源!B:B,"Oil 燃油费") -> #VALUE! | BA12: =SUMIFS([1]能源!C:C,[1]能源!A:A,D12,[1]能源!B:B,"Heating 暖气") -> #VALUE! | BB12: =SUM(AX12:BA12) -> #VALUE! | BC12: =BB12/F12 -> #VALUE! | BD12: {=INDIRECT($B12&"!M101")-SUM(AX12:BA12)} -> #REF! | BG12: {=INDIRECT($B12&"!M119")} -> #REF! | BI12: {=INDIRECT($B12&"!M116")} -> #REF! | BK12: {=INDIRECT($B12&"!M123")} -> #REF! | BM12: {=INDIRECT($B12&"!M117")} -> #REF! | BN12: {=INDIRECT($B12&"!M118")+INDIRECT($B12&"!M120")} -> #REF! | BP12: {=-INDIRECT($B12&"!M114")+INDIRECT($B12&"!M115")-BG12-BI12-BM12-BN12} -> #REF!
A13: 句容酒店 | B13: 句容 | C13: 句容酒店 | D13: 句容碧桂园凤凰城酒店管理有限公司 | E13: =SUM(G13:M13)-F13 -> #REF! | F13: {=INDIRECT($B13&"!M16")} -> #REF! | G13: {=INDIRECT($B13&"!M43")} -> #REF! | H13: {=INDIRECT($B13&"!M52")+INDIRECT($B13&"!M53")} -> #REF! | I13: {=INDIRECT($B13&"!M55")} -> #REF! | J13: {=INDIRECT($B13&"!M54")} -> #REF! | K13: {=INDIRECT($B13&"!M75")} -> #REF! | L13: {=INDIRECT($B13&"!M69")+INDIRECT($B13&"!M70")} -> #REF! | M13: {=INDIRECT($B13&"!M77")-INDIRECT($B13&"!M75")-INDIRECT($B13&"!M69")-INDIRECT($B13&"!M70")} -> #REF! | N13: {=INDIRECT($B13&"!M115")} -> #REF! | O13: =SUM(G13:N13) -> #REF! | P13: {=INDIRECT($B13&"!M31")} -> #REF! | Q13: =P13/F13 -> #REF! | R13: {=INDIRECT($B13&"!M34")} -> #REF! | S13: =R13/F13 -> #REF! | T13: {=INDIRECT($B13&"!M38")} -> #REF! | V13: =T13/F13 -> #REF! | W13: {=INDIRECT($B13&"!M36")} -> #REF! | X13: =W13/F13 -> #REF! | Y13: =SUMIFS([1]客房!D:D,[1]客房!B:B,D13,[1]客房!C:C,"Reservation Fees 预订成本") -> #VALUE! | Z13: =SUMIFS([1]客房!D:D,[1]客房!B:B,D13,[1]客房!C:C," Total Cost of Sales 总销售成本") -> #VALUE! | AA13: {=INDIRECT($B13&"!M44")+INDIRECT($B13&"!M45")} -> #REF! | AB13: =SUMIFS([1]客房!D:D,[1]客房!B:B,D13,[1]客房!C:C,"Laundry 洗涤费") -> #VALUE! | AC13: {=INDIRECT($B13&"!M46")-Y13-Z13-AB13} -> #REF! | AD13: {=INDIRECT($B13&"!M47")-SUM(Y13:AC13)} -> #REF! | AF13: {=INDIRECT($B13&"!M60")} -> #REF! | AG13: {=INDIRECT($B13&"!M61")+INDIRECT($B13&"!M62")} -> #REF! | AH13: =SUMIFS([1]餐饮!D:D,[1]餐饮!B:B,D13,[1]餐饮!C:C,"Laundry 洗涤费") -> #VALUE! | AI13: {=INDIRECT($B13&"!M63")-AH13} -> #REF! | AJ13: {=INDIRECT($B13&"!M64")-SUM(AE13:AI13)} -> #REF! | AK13: =SUMIFS([1]新零售!D:D,[1]新零售!B:B,D13,[1]新零售!C:C,"Total Cost of Sales 总销售成本") -> #VALUE! | AL13: =SUMIFS([1]康乐温泉!C:C,[1]康乐温泉!A:A,D13,[1]康乐温泉!B:B,"Total Cost of Sales 总销售成本")+SUMIFS([1]康乐温泉!C:C,[1]康乐温泉!A:A,D13,[1]康乐温泉!B:B,"Total Other Expenses 其他费用合计") -> #VALUE! | AP13: {=INDIRECT($B13&"!M91")+INDIRECT($B13&"!M92")} -> #REF! | AQ13: {=INDIRECT($B13&"!M93")+INDIRECT($B13&"!M94")+INDIRECT($B13&"!M95")+INDIRECT($B13&"!M96")} -> #REF! | AR13: {=INDIRECT($B13&"!M98")+INDIRECT($B13&"!M99")} -> #REF! | AT13: {=INDIRECT($B13&"!M100")} -> #REF! | AU13: {=INDIRECT($B13&"!M103")+INDIRECT($B13&"!M104")} -> #REF! | AV13: {=INDIRECT($B13&"!M36")} -> #REF! | AW13: {=INDIRECT($B13&"!M105")-AV13} -> #REF! | AX13: =SUMIFS([1]能源!C:C,[1]能源!A:A,D13,[1]能源!B:B,"Electricity 电费") -> #VALUE! | AY13: =SUMIFS([1]能源!C:C,[1]能源!A:A,D13,[1]能源!B:B,"Steam 蒸汽费")+SUMIFS([1]能源!C:C,[1]能源!A:A,D13,[1]能源!B:B,"Geothermal water 地热水")+SUMIFS([1]能源!C:C,[1]能源!A:A,D13,[1]能源!B:B,"Water 水费") -> #VALUE! | AZ13: =SUMIFS([1]能源!C:C,[1]能源!A:A,D13,[1]能源!B:B,"Gas 煤气费")+SUMIFS([1]能源!C:C,[1]能源!A:A,D13,[1]能源!B:B,"Oil 燃油费") -> #VALUE! | BA13: =SUMIFS([1]能源!C:C,[1]能源!A:A,D13,[1]能源!B:B,"Heating 暖气") -> #VALUE! | BB13: =SUM(AX13:BA13) -> #VALUE! | BC13: =BB13/F13 -> #VALUE! | BD13: {=INDIRECT($B13&"!M101")-SUM(AX13:BA13)} -> #REF! | BG13: {=INDIRECT($B13&"!M119")} -> #REF! | BI13: {=INDIRECT($B13&"!M116")} -> #REF! | BK13: {=INDIRECT($B13&"!M123")} -> #REF! | BM13: {=INDIRECT($B13&"!M117")} -> #REF! | BN13: {=INDIRECT($B13&"!M118")+INDIRECT($B13&"!M120")} -> #REF! | BP13: {=-INDIRECT($B13&"!M114")+INDIRECT($B13&"!M115")-BG13-BI13-BM13-BN13} -> #REF!
A14: 增城逸林酒店 | B14: 逸林 | C14: 增城逸林酒店 | D14: 广州市荔碧凤悦酒店有限公司 | E14: =SUM(G14:M14)-F14 -> #REF! | F14: {=INDIRECT($B14&"!M16")} -> #REF! | G14: {=INDIRECT($B14&"!M43")} -> #REF! | H14: {=INDIRECT($B14&"!M52")+INDIRECT($B14&"!M53")} -> #REF! | I14: {=INDIRECT($B14&"!M55")} -> #REF! | J14: {=INDIRECT($B14&"!M54")} -> #REF! | K14: {=INDIRECT($B14&"!M75")} -> #REF! | L14: {=INDIRECT($B14&"!M69")+INDIRECT($B14&"!M70")} -> #REF! | M14: {=INDIRECT($B14&"!M77")-INDIRECT($B14&"!M75")-INDIRECT($B14&"!M69")-INDIRECT($B14&"!M70")} -> #REF! | N14: {=INDIRECT($B14&"!M115")} -> #REF! | O14: =SUM(G14:N14) -> #REF! | P14: {=INDIRECT($B14&"!M31")} -> #REF! | Q14: =P14/F14 -> #REF! | R14: {=INDIRECT($B14&"!M34")} -> #REF! | S14: =R14/F14 -> #REF! | T14: {=INDIRECT($B14&"!M38")} -> #REF! | V14: =T14/F14 -> #REF! | W14: {=INDIRECT($B14&"!M36")} -> #REF! | X14: =W14/F14 -> #REF! | Y14: =SUMIFS([1]客房!D:D,[1]客房!B:B,D14,[1]客房!C:C,"Reservation Fees 预订成本") -> #VALUE! | Z14: =SUMIFS([1]客房!D:D,[1]客房!B:B,D14,[1]客房!C:C," Total Cost of Sales 总销售成本") -> #VALUE! | AA14: {=INDIRECT($B14&"!M44")+INDIRECT($B14&"!M45")} -> #REF! | AB14: =SUMIFS([1]客房!D:D,[1]客房!B:B,D14,[1]客房!C:C,"Laundry 洗涤费") -> #VALUE! | AC14: {=INDIRECT($B14&"!M46")-Y14-Z14-AB14} -> #REF! | AD14: {=INDIRECT($B14&"!M47")-SUM(Y14:AC14)} -> #REF! | AF14: {=INDIRECT($B14&"!M60")} -> #REF! | AG14: {=INDIRECT($B14&"!M61")+INDIRECT($B14&"!M62")} -> #REF! | AH14: =SUMIFS([1]餐饮!D:D,[1]餐饮!B:B,D14,[1]餐饮!C:C,"Laundry 洗涤费") -> #VALUE! | AI14: {=INDIRECT($B14&"!M63")-AH14} -> #REF! | AJ14: {=INDIRECT($B14&"!M64")-SUM(AE14:AI14)} -> #REF! | AK14: =SUMIFS([1]新零售!D:D,[1]新零售!B:B,D14,[1]新零售!C:C,"Total Cost of Sales 总销售成本") -> #VALUE! | AL14: =SUMIFS([1]康乐温泉!C:C,[1]康乐温泉!A:A,D14,[1]康乐温泉!B:B,"Total Cost of Sales 总销售成本")+SUMIFS([1]康乐温泉!C:C,[1]康乐温泉!A:A,D14,[1]康乐温泉!B:B,"Total Other Expenses 其他费用合计") -> #VALUE! | AP14: {=INDIRECT($B14&"!M91")+INDIRECT($B14&"!M92")} -> #REF! | AQ14: {=INDIRECT($B14&"!M93")+INDIRECT($B14&"!M94")+INDIRECT($B14&"!M95")+INDIRECT($B14&"!M96")} -> #REF! | AR14: {=INDIRECT($B14&"!M98")+INDIRECT($B14&"!M99")} -> #REF! | AT14: {=INDIRECT($B14&"!M100")} -> #REF! | AU14: {=INDIRECT($B14&"!M103")+INDIRECT($B14&"!M104")} -> #REF! | AV14: {=INDIRECT($B14&"!M36")} -> #REF! | AW14: {=INDIRECT($B14&"!M105")-AV14} -> #REF! | AX14: =SUMIFS([1]能源!C:C,[1]能源!A:A,D14,[1]能源!B:B,"Electricity 电费") -> #VALUE! | AY14: =SUMIFS([1]能源!C:C,[1]能源!A:A,D14,[1]能源!B:B,"Steam 蒸汽费")+SUMIFS([1]能源!C:C,[1]能源!A:A,D14,[1]能源!B:B,"Geothermal water 地热水")+SUMIFS([1]能源!C:C,[1]能源!A:A,D14,[1]能源!B:B,"Water 水费") -> #VALUE! | AZ14: =SUMIFS([1]能源!C:C,[1]能源!A:A,D14,[1]能源!B:B,"Gas 煤气费")+SUMIFS([1]能源!C:C,[1]能源!A:A,D14,[1]能源!B:B,"Oil 燃油费") -> #VALUE! | BA14: =SUMIFS([1]能源!C:C,[1]能源!A:A,D14,[1]能源!B:B,"Heating 暖气") -> #VALUE! | BB14: =SUM(AX14:BA14) -> #VALUE! | BC14: =BB14/F14 -> #VALUE! | BD14: {=INDIRECT($B14&"!M101")-SUM(AX14:BA14)} -> #REF! | BG14: {=INDIRECT($B14&"!M119")} -> #REF! | BI14: {=INDIRECT($B14&"!M116")} -> #REF! | BK14: {=INDIRECT($B14&"!M123")} -> #REF! | BM14: {=INDIRECT($B14&"!M117")} -> #REF! | BN14: {=INDIRECT($B14&"!M118")+INDIRECT($B14&"!M120")} -> #REF! | BP14: {=-INDIRECT($B14&"!M114")+INDIRECT($B14&"!M115")-BG14-BI14-BM14-BN14} -> #REF!
A15: 云浮酒店 | B15: 云浮 | C15: 云浮酒店 | D15: 云浮市碧桂园凤凰酒店有限公司 | E15: =SUM(G15:M15)-F15 -> #REF! | F15: {=INDIRECT($B15&"!M16")} -> #REF! | G15: {=INDIRECT($B15&"!M43")} -> #REF! | H15: {=INDIRECT($B15&"!M52")+INDIRECT($B15&"!M53")} -> #REF! | I15: {=INDIRECT($B15&"!M55")} -> #REF! | J15: {=INDIRECT($B15&"!M54")} -> #REF! | K15: {=INDIRECT($B15&"!M75")} -> #REF! | L15: {=INDIRECT($B15&"!M69")+INDIRECT($B15&"!M70")} -> #REF! | M15: {=INDIRECT($B15&"!M77")-INDIRECT($B15&"!M75")-INDIRECT($B15&"!M69")-INDIRECT($B15&"!M70")} -> #REF! | N15: {=INDIRECT($B15&"!M115")} -> #REF! | O15: =SUM(G15:N15) -> #REF! | P15: {=INDIRECT($B15&"!M31")} -> #REF! | Q15: =P15/F15 -> #REF! | R15: {=INDIRECT($B15&"!M34")} -> #REF! | S15: =R15/F15 -> #REF! | T15: {=INDIRECT($B15&"!M38")} -> #REF! | V15: =T15/F15 -> #REF! | W15: {=INDIRECT($B15&"!M36")} -> #REF! | X15: =W15/F15 -> #REF! | Y15: =SUMIFS([1]客房!D:D,[1]客房!B:B,D15,[1]客房!C:C,"Reservation Fees 预订成本") -> #VALUE! | Z15: =SUMIFS([1]客房!D:D,[1]客房!B:B,D15,[1]客房!C:C," Total Cost of Sales 总销售成本") -> #VALUE! | AA15: {=INDIRECT($B15&"!M44")+INDIRECT($B15&"!M45")} -> #REF! | AB15: =SUMIFS([1]客房!D:D,[1]客房!B:B,D15,[1]客房!C:C,"Laundry 洗涤费") -> #VALUE! | AC15: {=INDIRECT($B15&"!M46")-Y15-Z15-AB15} -> #REF! | AD15: {=INDIRECT($B15&"!M47")-SUM(Y15:AC15)} -> #REF! | AF15: {=INDIRECT($B15&"!M60")} -> #REF! | AG15: {=INDIRECT($B15&"!M61")+INDIRECT($B15&"!M62")} -> #REF! | AH15: =SUMIFS([1]餐饮!D:D,[1]餐饮!B:B,D15,[1]餐饮!C:C,"Laundry 洗涤费") -> #VALUE! | AI15: {=INDIRECT($B15&"!M63")-AH15} -> #REF! | AJ15: {=INDIRECT($B15&"!M64")-SUM(AE15:AI15)} -> #REF! | AK15: =SUMIFS([1]新零售!D:D,[1]新零售!B:B,D15,[1]新零售!C:C,"Total Cost of Sales 总销售成本") -> #VALUE! | AL15: =SUMIFS([1]康乐温泉!C:C,[1]康乐温泉!A:A,D15,[1]康乐温泉!B:B,"Total Cost of Sales 总销售成本")+SUMIFS([1]康乐温泉!C:C,[1]康乐温泉!A:A,D15,[1]康乐温泉!B:B,"Total Other Expenses 其他费用合计") -> #VALUE! | AP15: {=INDIRECT($B15&"!M91")+INDIRECT($B15&"!M92")} -> #REF! | AQ15: {=INDIRECT($B15&"!M93")+INDIRECT($B15&"!M94")+INDIRECT($B15&"!M95")+INDIRECT($B15&"!M96")} -> #REF! | AR15: {=INDIRECT($B15&"!M98")+INDIRECT($B15&"!M99")} -> #REF! | AT15: {=INDIRECT($B15&"!M100")} -> #REF! | AU15: {=INDIRECT($B15&"!M103")+INDIRECT($B15&"!M104")} -> #REF! | AV15: {=INDIRECT($B15&"!M36")} -> #REF! | AW15: {=INDIRECT($B15&"!M105")-AV15} -> #REF! | AX15: =SUMIFS([1]能源!C:C,[1]能源!A:A,D15,[1]能源!B:B,"Electricity 电费") -> #VALUE! | AY15: =SUMIFS([1]能源!C:C,[1]能源!A:A,D15,[1]能源!B:B,"Steam 蒸汽费")+SUMIFS([1]能源!C:C,[1]能源!A:A,D15,[1]能源!B:B,"Geothermal water 地热水")+SUMIFS([1]能源!C:C,[1]能源!A:A,D15,[1]能源!B:B,"Water 水费") -> #VALUE! | AZ15: =SUMIFS([1]能源!C:C,[1]能源!A:A,D15,[1]能源!B:B,"Gas 煤气费")+SUMIFS([1]能源!C:C,[1]能源!A:A,D15,[1]能源!B:B,"Oil 燃油费") -> #VALUE! | BA15: =SUMIFS([1]能源!C:C,[1]能源!A:A,D15,[1]能源!B:B,"Heating 暖气") -> #VALUE! | BB15: =SUM(AX15:BA15) -> #VALUE! | BC15: =BB15/F15 -> #VALUE! | BD15: {=INDIRECT($B15&"!M101")-SUM(AX15:BA15)} -> #REF! | BG15: {=INDIRECT($B15&"!M119")} -> #REF! | BI15: {=INDIRECT($B15&"!M116")} -> #REF! | BK15: {=INDIRECT($B15&"!M123")} -> #REF! | BM15: {=INDIRECT($B15&"!M117")} -> #REF! | BN15: {=INDIRECT($B15&"!M118")+INDIRECT($B15&"!M120")} -> #REF! | BP15: {=-INDIRECT($B15&"!M114")+INDIRECT($B15&"!M115")-BG15-BI15-BM15-BN15} -> #REF!
A16: 金叶子酒店 | B16: 金叶子 | C16: 金叶子酒店 | D16: 广州金叶子酒店有限公司 | E16: =SUM(G16:M16)-F16 -> #REF! | F16: {=INDIRECT($B16&"!M16")} -> #REF! | G16: {=INDIRECT($B16&"!M43")} -> #REF! | H16: {=INDIRECT($B16&"!M52")+INDIRECT($B16&"!M53")} -> #REF! | I16: {=INDIRECT($B16&"!M55")} -> #REF! | J16: {=INDIRECT($B16&"!M54")} -> #REF! | K16: {=INDIRECT($B16&"!M75")} -> #REF! | L16: {=INDIRECT($B16&"!M69")+INDIRECT($B16&"!M70")} -> #REF! | M16: {=INDIRECT($B16&"!M77")-INDIRECT($B16&"!M75")-INDIRECT($B16&"!M69")-INDIRECT($B16&"!M70")} -> #REF! | N16: {=INDIRECT($B16&"!M115")} -> #REF! | O16: =SUM(G16:N16) -> #REF! | P16: {=INDIRECT($B16&"!M31")} -> #REF! | Q16: =P16/F16 -> #REF! | R16: {=INDIRECT($B16&"!M34")} -> #REF! | S16: =R16/F16 -> #REF! | T16: {=INDIRECT($B16&"!M38")} -> #REF! | V16: =T16/F16 -> #REF! | W16: {=INDIRECT($B16&"!M36")} -> #REF! | X16: =W16/F16 -> #REF! | Y16: =SUMIFS([1]客房!D:D,[1]客房!B:B,D16,[1]客房!C:C,"Reservation Fees 预订成本") -> #VALUE! | Z16: =SUMIFS([1]客房!D:D,[1]客房!B:B,D16,[1]客房!C:C," Total Cost of Sales 总销售成本") -> #VALUE! | AA16: {=INDIRECT($B16&"!M44")+INDIRECT($B16&"!M45")} -> #REF! | AB16: =SUMIFS([1]客房!D:D,[1]客房!B:B,D16,[1]客房!C:C,"Laundry 洗涤费") -> #VALUE! | AC16: {=INDIRECT($B16&"!M46")-Y16-Z16-AB16} -> #REF! | AD16: {=INDIRECT($B16&"!M47")-SUM(Y16:AC16)} -> #REF! | AF16: {=INDIRECT($B16&"!M60")} -> #REF! | AG16: {=INDIRECT($B16&"!M61")+INDIRECT($B16&"!M62")} -> #REF! | AH16: =SUMIFS([1]餐饮!D:D,[1]餐饮!B:B,D16,[1]餐饮!C:C,"Laundry 洗涤费") -> #VALUE! | AI16: {=INDIRECT($B16&"!M63")-AH16} -> #REF! | AJ16: {=INDIRECT($B16&"!M64")-SUM(AE16:AI16)} -> #REF! | AK16: =SUMIFS([1]新零售!D:D,[1]新零售!B:B,D16,[1]新零售!C:C,"Total Cost of Sales 总销售成本") -> #VALUE! | AL16: =SUMIFS([1]康乐温泉!C:C,[1]康乐温泉!A:A,D16,[1]康乐温泉!B:B,"Total Cost of Sales 总销售成本")+SUMIFS([1]康乐温泉!C:C,[1]康乐温泉!A:A,D16,[1]康乐温泉!B:B,"Total Other Expenses 其他费用合计") -> #VALUE! | AP16: {=INDIRECT($B16&"!M91")+INDIRECT($B16&"!M92")} -> #REF! | AQ16: {=INDIRECT($B16&"!M93")+INDIRECT($B16&"!M94")+INDIRECT($B16&"!M95")+INDIRECT($B16&"!M96")} -> #REF! | AR16: {=INDIRECT($B16&"!M98")+INDIRECT($B16&"!M99")} -> #REF! | AT16: {=INDIRECT($B16&"!M100")} -> #REF! | AU16: {=INDIRECT($B16&"!M103")+INDIRECT($B16&"!M104")} -> #REF! | AV16: {=INDIRECT($B16&"!M36")} -> #REF! | AW16: {=INDIRECT($B16&"!M105")-AV16} -> #REF! | AX16: =SUMIFS([1]能源!C:C,[1]能源!A:A,D16,[1]能源!B:B,"Electricity 电费") -> #VALUE! | AY16: =SUMIFS([1]能源!C:C,[1]能源!A:A,D16,[1]能源!B:B,"Steam 蒸汽费")+SUMIFS([1]能源!C:C,[1]能源!A:A,D16,[1]能源!B:B,"Geothermal water 地热水")+SUMIFS([1]能源!C:C,[1]能源!A:A,D16,[1]能源!B:B,"Water 水费") -> #VALUE! | AZ16: =SUMIFS([1]能源!C:C,[1]能源!A:A,D16,[1]能源!B:B,"Gas 煤气费")+SUMIFS([1]能源!C:C,[1]能源!A:A,D16,[1]能源!B:B,"Oil 燃油费") -> #VALUE! | BA16: =SUMIFS([1]能源!C:C,[1]能源!A:A,D16,[1]能源!B:B,"Heating 暖气") -> #VALUE! | BB16: =SUM(AX16:BA16) -> #VALUE! | BC16: =BB16/F16 -> #VALUE! | BD16: {=INDIRECT($B16&"!M101")-SUM(AX16:BA16)} -> #REF! | BG16: {=INDIRECT($B16&"!M119")} -> #REF! | BI16: {=INDIRECT($B16&"!M116")} -> #REF! | BK16: {=INDIRECT($B16&"!M123")} -> #REF! | BM16: {=INDIRECT($B16&"!M117")} -> #REF! | BN16: {=INDIRECT($B16&"!M118")+INDIRECT($B16&"!M120")} -> #REF! | BP16: {=-INDIRECT($B16&"!M114")+INDIRECT($B16&"!M115")-BG16-BI16-BM16-BN16} -> #REF!
A17: 苏家屯酒店 | B17: 苏家屯 | C17: 苏家屯酒店 | D17: 沈阳南营碧桂园酒店有限公司 | E17: =SUM(G17:M17)-F17 -> #REF! | F17: {=INDIRECT($B17&"!M16")} -> #REF! | G17: {=INDIRECT($B17&"!M43")} -> #REF! | H17: {=INDIRECT($B17&"!M52")+INDIRECT($B17&"!M53")} -> #REF! | I17: {=INDIRECT($B17&"!M55")} -> #REF! | J17: {=INDIRECT($B17&"!M54")} -> #REF! | K17: {=INDIRECT($B17&"!M75")} -> #REF! | L17: {=INDIRECT($B17&"!M69")+INDIRECT($B17&"!M70")} -> #REF! | M17: {=INDIRECT($B17&"!M77")-INDIRECT($B17&"!M75")-INDIRECT($B17&"!M69")-INDIRECT($B17&"!M70")} -> #REF! | N17: {=INDIRECT($B17&"!M115")} -> #REF! | O17: =SUM(G17:N17) -> #REF! | P17: {=INDIRECT($B17&"!M31")} -> #REF! | Q17: =P17/F17 -> #REF! | R17: {=INDIRECT($B17&"!M34")} -> #REF! | S17: =R17/F17 -> #REF! | T17: {=INDIRECT($B17&"!M38")} -> #REF! | V17: =T17/F17 -> #REF! | W17: {=INDIRECT($B17&"!M36")} -> #REF! | X17: =W17/F17 -> #REF! | Y17: =SUMIFS([1]客房!D:D,[1]客房!B:B,D17,[1]客房!C:C,"Reservation Fees 预订成本") -> #VALUE! | Z17: =SUMIFS([1]客房!D:D,[1]客房!B:B,D17,[1]客房!C:C," Total Cost of Sales 总销售成本") -> #VALUE! | AA17: {=INDIRECT($B17&"!M44")+INDIRECT($B17&"!M45")} -> #REF! | AB17: =SUMIFS([1]客房!D:D,[1]客房!B:B,D17,[1]客房!C:C,"Laundry 洗涤费") -> #VALUE! | AC17: {=INDIRECT($B17&"!M46")-Y17-Z17-AB17} -> #REF! | AD17: {=INDIRECT($B17&"!M47")-SUM(Y17:AC17)} -> #REF! | AF17: {=INDIRECT($B17&"!M60")} -> #REF! | AG17: {=INDIRECT($B17&"!M61")+INDIRECT($B17&"!M62")} -> #REF! | AH17: =SUMIFS([1]餐饮!D:D,[1]餐饮!B:B,D17,[1]餐饮!C:C,"Laundry 洗涤费") -> #VALUE! | AI17: {=INDIRECT($B17&"!M63")-AH17} -> #REF! | AJ17: {=INDIRECT($B17&"!M64")-SUM(AE17:AI17)} -> #REF! | AK17: =SUMIFS([1]新零售!D:D,[1]新零售!B:B,D17,[1]新零售!C:C,"Total Cost of Sales 总销售成本") -> #VALUE! | AL17: =SUMIFS([1]康乐温泉!C:C,[1]康乐温泉!A:A,D17,[1]康乐温泉!B:B,"Total Cost of Sales 总销售成本")+SUMIFS([1]康乐温泉!C:C,[1]康乐温泉!A:A,D17,[1]康乐温泉!B:B,"Total Other Expenses 其他费用合计") -> #VALUE! | AP17: {=INDIRECT($B17&"!M91")+INDIRECT($B17&"!M92")} -> #REF! | AQ17: {=INDIRECT($B17&"!M93")+INDIRECT($B17&"!M94")+INDIRECT($B17&"!M95")+INDIRECT($B17&"!M96")} -> #REF! | AR17: {=INDIRECT($B17&"!M98")+INDIRECT($B17&"!M99")} -> #REF! | AT17: {=INDIRECT($B17&"!M100")} -> #REF! | AU17: {=INDIRECT($B17&"!M103")+INDIRECT($B17&"!M104")} -> #REF! | AV17: {=INDIRECT($B17&"!M36")} -> #REF! | AW17: {=INDIRECT($B17&"!M105")-AV17} -> #REF! | AX17: =SUMIFS([1]能源!C:C,[1]能源!A:A,D17,[1]能源!B:B,"Electricity 电费") -> #VALUE! | AY17: =SUMIFS([1]能源!C:C,[1]能源!A:A,D17,[1]能源!B:B,"Steam 蒸汽费")+SUMIFS([1]能源!C:C,[1]能源!A:A,D17,[1]能源!B:B,"Geothermal water 地热水")+SUMIFS([1]能源!C:C,[1]能源!A:A,D17,[1]能源!B:B,"Water 水费") -> #VALUE! | AZ17: =SUMIFS([1]能源!C:C,[1]能源!A:A,D17,[1]能源!B:B,"Gas 煤气费")+SUMIFS([1]能源!C:C,[1]能源!A:A,D17,[1]能源!B:B,"Oil 燃油费") -> #VALUE! | BA17: =SUMIFS([1]能源!C:C,[1]能源!A:A,D17,[1]能源!B:B,"Heating 暖气") -> #VALUE! | BB17: =SUM(AX17:BA17) -> #VALUE! | BC17: =BB17/F17 -> #VALUE! | BD17: {=INDIRECT($B17&"!M101")-SUM(AX17:BA17)} -> #REF! | BG17: {=INDIRECT($B17&"!M119")} -> #REF! | BI17: {=INDIRECT($B17&"!M116")} -> #REF! | BK17: {=INDIRECT($B17&"!M123")} -> #REF! | BM17: {=INDIRECT($B17&"!M117")} -> #REF! | BN17: {=INDIRECT($B17&"!M118")+INDIRECT($B17&"!M120")} -> #REF! | BP17: {=-INDIRECT($B17&"!M114")+INDIRECT($B17&"!M115")-BG17-BI17-BM17-BN17} -> #REF!
A18: 兴安盟酒店 | B18: 兴安盟 | C18: 兴安盟酒店 | D18: 科右前旗碧桂园凤凰置业有限公司 | E18: =SUM(G18:M18)-F18 -> #REF! | F18: {=INDIRECT($B18&"!M16")} -> #REF! | G18: {=INDIRECT($B18&"!M43")} -> #REF! | H18: {=INDIRECT($B18&"!M52")+INDIRECT($B18&"!M53")} -> #REF! | I18: {=INDIRECT($B18&"!M55")} -> #REF! | J18: {=INDIRECT($B18&"!M54")} -> #REF! | K18: {=INDIRECT($B18&"!M75")} -> #REF! | L18: {=INDIRECT($B18&"!M69")+INDIRECT($B18&"!M70")} -> #REF! | M18: {=INDIRECT($B18&"!M77")-INDIRECT($B18&"!M75")-INDIRECT($B18&"!M69")-INDIRECT($B18&"!M70")} -> #REF! | N18: {=INDIRECT($B18&"!M115")} -> #REF! | O18: =SUM(G18:N18) -> #REF! | P18: {=INDIRECT($B18&"!M31")} -> #REF! | Q18: =P18/F18 -> #REF! | R18: {=INDIRECT($B18&"!M34")} -> #REF! | S18: =R18/F18 -> #REF! | T18: {=INDIRECT($B18&"!M38")} -> #REF! | V18: =T18/F18 -> #REF! | W18: {=INDIRECT($B18&"!M36")} -> #REF! | X18: =W18/F18 -> #REF! | Y18: =SUMIFS([1]客房!D:D,[1]客房!B:B,D18,[1]客房!C:C,"Reservation Fees 预订成本") -> #VALUE! | Z18: =SUMIFS([1]客房!D:D,[1]客房!B:B,D18,[1]客房!C:C," Total Cost of Sales 总销售成本") -> #VALUE! | AA18: {=INDIRECT($B18&"!M44")+INDIRECT($B18&"!M45")} -> #REF! | AB18: =SUMIFS([1]客房!D:D,[1]客房!B:B,D18,[1]客房!C:C,"Laundry 洗涤费") -> #VALUE! | AC18: {=INDIRECT($B18&"!M46")-Y18-Z18-AB18} -> #REF! | AD18: {=INDIRECT($B18&"!M47")-SUM(Y18:AC18)} -> #REF! | AF18: {=INDIRECT($B18&"!M60")} -> #REF! | AG18: {=INDIRECT($B18&"!M61")+INDIRECT($B18&"!M62")} -> #REF! | AH18: =SUMIFS([1]餐饮!D:D,[1]餐饮!B:B,D18,[1]餐饮!C:C,"Laundry 洗涤费") -> #VALUE! | AI18: {=INDIRECT($B18&"!M63")-AH18} -> #REF! | AJ18: {=INDIRECT($B18&"!M64")-SUM(AE18:AI18)} -> #REF! | AK18: =SUMIFS([1]新零售!D:D,[1]新零售!B:B,D18,[1]新零售!C:C,"Total Cost of Sales 总销售成本") -> #VALUE! | AL18: =SUMIFS([1]康乐温泉!C:C,[1]康乐温泉!A:A,D18,[1]康乐温泉!B:B,"Total Cost of Sales 总销售成本")+SUMIFS([1]康乐温泉!C:C,[1]康乐温泉!A:A,D18,[1]康乐温泉!B:B,"Total Other Expenses 其他费用合计") -> #VALUE! | AP18: {=INDIRECT($B18&"!M91")+INDIRECT($B18&"!M92")} -> #REF! | AQ18: {=INDIRECT($B18&"!M93")+INDIRECT($B18&"!M94")+INDIRECT($B18&"!M95")+INDIRECT($B18&"!M96")} -> #REF! | AR18: {=INDIRECT($B18&"!M98")+INDIRECT($B18&"!M99")} -> #REF! | AT18: {=INDIRECT($B18&"!M100")} -> #REF! | AU18: {=INDIRECT($B18&"!M103")+INDIRECT($B18&"!M104")} -> #REF! | AV18: {=INDIRECT($B18&"!M36")} -> #REF! | AW18: {=INDIRECT($B18&"!M105")-AV18} -> #REF! | AX18: =SUMIFS([1]能源!C:C,[1]能源!A:A,D18,[1]能源!B:B,"Electricity 电费") -> #VALUE! | AY18: =SUMIFS([1]能源!C:C,[1]能源!A:A,D18,[1]能源!B:B,"Steam 蒸汽费")+SUMIFS([1]能源!C:C,[1]能源!A:A,D18,[1]能源!B:B,"Geothermal water 地热水")+SUMIFS([1]能源!C:C,[1]能源!A:A,D18,[1]能源!B:B,"Water 水费") -> #VALUE! | AZ18: =SUMIFS([1]能源!C:C,[1]能源!A:A,D18,[1]能源!B:B,"Gas 煤气费")+SUMIFS([1]能源!C:C,[1]能源!A:A,D18,[1]能源!B:B,"Oil 燃油费") -> #VALUE! | BA18: =SUMIFS([1]能源!C:C,[1]能源!A:A,D18,[1]能源!B:B,"Heating 暖气") -> #VALUE! | BB18: =SUM(AX18:BA18) -> #VALUE! | BC18: =BB18/F18 -> #VALUE! | BD18: {=INDIRECT($B18&"!M101")-SUM(AX18:BA18)} -> #REF! | BG18: {=INDIRECT($B18&"!M119")} -> #REF! | BI18: {=INDIRECT($B18&"!M116")} -> #REF! | BK18: {=INDIRECT($B18&"!M123")} -> #REF! | BM18: {=INDIRECT($B18&"!M117")} -> #REF! | BN18: {=INDIRECT($B18&"!M118")+INDIRECT($B18&"!M120")} -> #REF! | BP18: {=-INDIRECT($B18&"!M114")+INDIRECT($B18&"!M115")-BG18-BI18-BM18-BN18} -> #REF!
A19: 顺碧度假村 | B19: 度假村 | C19: 顺碧度假村 | D19: 佛山市顺德区碧桂园物业发展有限公司渡假村 | E19: =SUM(G19:M19)-F19 -> #REF! | F19: {=INDIRECT($B19&"!M16")} -> #REF! | G19: {=INDIRECT($B19&"!M43")} -> #REF! | H19: {=INDIRECT($B19&"!M52")+INDIRECT($B19&"!M53")} -> #REF! | I19: {=INDIRECT($B19&"!M55")} -> #REF! | J19: {=INDIRECT($B19&"!M54")} -> #REF! | K19: {=INDIRECT($B19&"!M75")} -> #REF! | L19: {=INDIRECT($B19&"!M69")+INDIRECT($B19&"!M70")} -> #REF! | M19: {=INDIRECT($B19&"!M77")-INDIRECT($B19&"!M75")-INDIRECT($B19&"!M69")-INDIRECT($B19&"!M70")} -> #REF! | N19: {=INDIRECT($B19&"!M115")} -> #REF! | O19: =SUM(G19:N19) -> #REF! | P19: {=INDIRECT($B19&"!M31")} -> #REF! | Q19: =P19/F19 -> #REF! | R19: {=INDIRECT($B19&"!M34")} -> #REF! | S19: =R19/F19 -> #REF! | T19: {=INDIRECT($B19&"!M38")} -> #REF! | V19: =T19/F19 -> #REF! | W19: {=INDIRECT($B19&"!M36")} -> #REF! | X19: =W19/F19 -> #REF! | Y19: =SUMIFS([1]客房!D:D,[1]客房!B:B,D19,[1]客房!C:C,"Reservation Fees 预订成本") -> #VALUE! | Z19: =SUMIFS([1]客房!D:D,[1]客房!B:B,D19,[1]客房!C:C," Total Cost of Sales 总销售成本") -> #VALUE! | AA19: {=INDIRECT($B19&"!M44")+INDIRECT($B19&"!M45")} -> #REF! | AB19: =SUMIFS([1]客房!D:D,[1]客房!B:B,D19,[1]客房!C:C,"Laundry 洗涤费") -> #VALUE! | AC19: {=INDIRECT($B19&"!M46")-Y19-Z19-AB19} -> #REF! | AD19: {=INDIRECT($B19&"!M47")-SUM(Y19:AC19)} -> #REF! | AF19: {=INDIRECT($B19&"!M60")} -> #REF! | AG19: {=INDIRECT($B19&"!M61")+INDIRECT($B19&"!M62")} -> #REF! | AH19: =SUMIFS([1]餐饮!D:D,[1]餐饮!B:B,D19,[1]餐饮!C:C,"Laundry 洗涤费") -> #VALUE! | AI19: {=INDIRECT($B19&"!M63")-AH19} -> #REF! | AJ19: {=INDIRECT($B19&"!M64")-SUM(AE19:AI19)} -> #REF! | AK19: =SUMIFS([1]新零售!D:D,[1]新零售!B:B,D19,[1]新零售!C:C,"Total Cost of Sales 总销售成本") -> #VALUE! | AL19: =SUMIFS([1]康乐温泉!C:C,[1]康乐温泉!A:A,D19,[1]康乐温泉!B:B,"Total Cost of Sales 总销售成本")+SUMIFS([1]康乐温泉!C:C,[1]康乐温泉!A:A,D19,[1]康乐温泉!B:B,"Total Other Expenses 其他费用合计") -> #VALUE! | AP19: {=INDIRECT($B19&"!M91")+INDIRECT($B19&"!M92")} -> #REF! | AQ19: {=INDIRECT($B19&"!M93")+INDIRECT($B19&"!M94")+INDIRECT($B19&"!M95")+INDIRECT($B19&"!M96")} -> #REF! | AR19: {=INDIRECT($B19&"!M98")+INDIRECT($B19&"!M99")} -> #REF! | AT19: {=INDIRECT($B19&"!M100")} -> #REF! | AU19: {=INDIRECT($B19&"!M103")+INDIRECT($B19&"!M104")} -> #REF! | AV19: {=INDIRECT($B19&"!M36")} -> #REF! | AW19: {=INDIRECT($B19&"!M105")-AV19} -> #REF! | AX19: =SUMIFS([1]能源!C:C,[1]能源!A:A,D19,[1]能源!B:B,"Electricity 电费") -> #VALUE! | AY19: =SUMIFS([1]能源!C:C,[1]能源!A:A,D19,[1]能源!B:B,"Steam 蒸汽费")+SUMIFS([1]能源!C:C,[1]能源!A:A,D19,[1]能源!B:B,"Geothermal water 地热水")+SUMIFS([1]能源!C:C,[1]能源!A:A,D19,[1]能源!B:B,"Water 水费") -> #VALUE! | AZ19: =SUMIFS([1]能源!C:C,[1]能源!A:A,D19,[1]能源!B:B,"Gas 煤气费")+SUMIFS([1]能源!C:C,[1]能源!A:A,D19,[1]能源!B:B,"Oil 燃油费") -> #VALUE! | BA19: =SUMIFS([1]能源!C:C,[1]能源!A:A,D19,[1]能源!B:B,"Heating 暖气") -> #VALUE! | BB19: =SUM(AX19:BA19) -> #VALUE! | BC19: =BB19/F19 -> #VALUE! | BD19: {=INDIRECT($B19&"!M101")-SUM(AX19:BA19)} -> #REF! | BG19: {=INDIRECT($B19&"!M119")} -> #REF! | BI19: {=INDIRECT($B19&"!M116")} -> #REF! | BK19: {=INDIRECT($B19&"!M123")} -> #REF! | BM19: {=INDIRECT($B19&"!M117")} -> #REF! | BN19: {=INDIRECT($B19&"!M118")+INDIRECT($B19&"!M120")} -> #REF! | BP19: {=-INDIRECT($B19&"!M114")+INDIRECT($B19&"!M115")-BG19-BI19-BM19-BN19} -> #REF!
A20: 共和酒店 | B20: 共和 | C20: 共和酒店 | D20: 鹤山市共和碧桂园房地产开发有限公司酒店分公司 | E20: =SUM(G20:M20)-F20 -> #REF! | F20: {=INDIRECT($B20&"!M16")} -> #REF! | G20: {=INDIRECT($B20&"!M43")} -> #REF! | H20: {=INDIRECT($B20&"!M52")+INDIRECT($B20&"!M53")} -> #REF! | I20: {=INDIRECT($B20&"!M55")} -> #REF! | J20: {=INDIRECT($B20&"!M54")} -> #REF! | K20: {=INDIRECT($B20&"!M75")} -> #REF! | L20: {=INDIRECT($B20&"!M69")+INDIRECT($B20&"!M70")} -> #REF! | M20: {=INDIRECT($B20&"!M77")-INDIRECT($B20&"!M75")-INDIRECT($B20&"!M69")-INDIRECT($B20&"!M70")} -> #REF! | N20: {=INDIRECT($B20&"!M115")} -> #REF! | O20: =SUM(G20:N20) -> #REF! | P20: {=INDIRECT($B20&"!M31")} -> #REF! | Q20: =P20/F20 -> #REF! | R20: {=INDIRECT($B20&"!M34")} -> #REF! | S20: =R20/F20 -> #REF! | T20: {=INDIRECT($B20&"!M38")} -> #REF! | V20: =T20/F20 -> #REF! | W20: {=INDIRECT($B20&"!M36")} -> #REF! | X20: =W20/F20 -> #REF! | Y20: =SUMIFS([1]客房!D:D,[1]客房!B:B,D20,[1]客房!C:C,"Reservation Fees 预订成本") -> #VALUE! | Z20: =SUMIFS([1]客房!D:D,[1]客房!B:B,D20,[1]客房!C:C," Total Cost of Sales 总销售成本") -> #VALUE! | AA20: {=INDIRECT($B20&"!M44")+INDIRECT($B20&"!M45")} -> #REF! | AB20: =SUMIFS([1]客房!D:D,[1]客房!B:B,D20,[1]客房!C:C,"Laundry 洗涤费") -> #VALUE! | AC20: {=INDIRECT($B20&"!M46")-Y20-Z20-AB20} -> #REF! | AD20: {=INDIRECT($B20&"!M47")-SUM(Y20:AC20)} -> #REF! | AF20: {=INDIRECT($B20&"!M60")} -> #REF! | AG20: {=INDIRECT($B20&"!M61")+INDIRECT($B20&"!M62")} -> #REF! | AH20: =SUMIFS([1]餐饮!D:D,[1]餐饮!B:B,D20,[1]餐饮!C:C,"Laundry 洗涤费") -> #VALUE! | AI20: {=INDIRECT($B20&"!M63")-AH20} -> #REF! | AJ20: {=INDIRECT($B20&"!M64")-SUM(AE20:AI20)} -> #REF! | AK20: =SUMIFS([1]新零售!D:D,[1]新零售!B:B,D20,[1]新零售!C:C,"Total Cost of Sales 总销售成本") -> #VALUE! | AL20: =SUMIFS([1]康乐温泉!C:C,[1]康乐温泉!A:A,D20,[1]康乐温泉!B:B,"Total Cost of Sales 总销售成本")+SUMIFS([1]康乐温泉!C:C,[1]康乐温泉!A:A,D20,[1]康乐温泉!B:B,"Total Other Expenses 其他费用合计") -> #VALUE! | AP20: {=INDIRECT($B20&"!M91")+INDIRECT($B20&"!M92")} -> #REF! | AQ20: {=INDIRECT($B20&"!M93")+INDIRECT($B20&"!M94")+INDIRECT($B20&"!M95")+INDIRECT($B20&"!M96")} -> #REF! | AR20: {=INDIRECT($B20&"!M98")+INDIRECT($B20&"!M99")} -> #REF! | AT20: {=INDIRECT($B20&"!M100")} -> #REF! | AU20: {=INDIRECT($B20&"!M103")+INDIRECT($B20&"!M104")} -> #REF! | AV20: {=INDIRECT($B20&"!M36")} -> #REF! | AW20: {=INDIRECT($B20&"!M105")-AV20} -> #REF! | AX20: =SUMIFS([1]能源!C:C,[1]能源!A:A,D20,[1]能源!B:B,"Electricity 电费") -> #VALUE! | AY20: =SUMIFS([1]能源!C:C,[1]能源!A:A,D20,[1]能源!B:B,"Steam 蒸汽费")+SUMIFS([1]能源!C:C,[1]能源!A:A,D20,[1]能源!B:B,"Geothermal water 地热水")+SUMIFS([1]能源!C:C,[1]能源!A:A,D20,[1]能源!B:B,"Water 水费") -> #VALUE! | AZ20: =SUMIFS([1]能源!C:C,[1]能源!A:A,D20,[1]能源!B:B,"Gas 煤气费")+SUMIFS([1]能源!C:C,[1]能源!A:A,D20,[1]能源!B:B,"Oil 燃油费") -> #VALUE! | BA20: =SUMIFS([1]能源!C:C,[1]能源!A:A,D20,[1]能源!B:B,"Heating 暖气") -> #VALUE! | BB20: =SUM(AX20:BA20) -> #VALUE! | BC20: =BB20/F20 -> #VALUE! | BD20: {=INDIRECT($B20&"!M101")-SUM(AX20:BA20)} -> #REF! | BG20: {=INDIRECT($B20&"!M119")} -> #REF! | BI20: {=INDIRECT($B20&"!M116")} -> #REF! | BK20: {=INDIRECT($B20&"!M123")} -> #REF! | BM20: {=INDIRECT($B20&"!M117")} -> #REF! | BN20: {=INDIRECT($B20&"!M118")+INDIRECT($B20&"!M120")} -> #REF! | BP20: {=-INDIRECT($B20&"!M114")+INDIRECT($B20&"!M115")-BG20-BI20-BM20-BN20} -> #REF!
... A36: 惠东酒店 | B36: 惠东 | C36: 惠东酒店 | D36: 惠东县凤悦酒店有限公司 | E36: =SUM(G36:M36)-F36 -> #REF! | F36: {=INDIRECT($B36&"!M16")} -> #REF! | G36: {=INDIRECT($B36&"!M43")} -> #REF! | H36: {=INDIRECT($B36&"!M52")+INDIRECT($B36&"!M53")} -> #REF! | I36: {=INDIRECT($B36&"!M55")} -> #REF! | J36: {=INDIRECT($B36&"!M54")} -> #REF! | K36: {=INDIRECT($B36&"!M75")} -> #REF! | L36: {=INDIRECT($B36&"!M69")+INDIRECT($B36&"!M70")} -> #REF! | M36: {=INDIRECT($B36&"!M77")-INDIRECT($B36&"!M75")-INDIRECT($B36&"!M69")-INDIRECT($B36&"!M70")} -> #REF! | N36: {=INDIRECT($B36&"!M115")} -> #REF! | O36: =SUM(G36:N36) -> #REF! | P36: {=INDIRECT($B36&"!M31")} -> #REF! | Q36: =P36/F36 -> #REF! | R36: {=INDIRECT($B36&"!M34")} -> #REF! | S36: =R36/F36 -> #REF! | T36: {=INDIRECT($B36&"!M38")} -> #REF! | V36: =T36/F36 -> #REF! | W36: {=INDIRECT($B36&"!M36")} -> #REF! | X36: =W36/F36 -> #REF! | Y36: =SUMIFS([1]客房!D:D,[1]客房!B:B,D36,[1]客房!C:C,"Reservation Fees 预订成本") -> #VALUE! | Z36: =SUMIFS([1]客房!D:D,[1]客房!B:B,D36,[1]客房!C:C," Total Cost of Sales 总销售成本") -> #VALUE! | AA36: {=INDIRECT($B36&"!M44")+INDIRECT($B36&"!M45")} -> #REF! | AB36: =SUMIFS([1]客房!D:D,[1]客房!B:B,D36,[1]客房!C:C,"Laundry 洗涤费") -> #VALUE! | AC36: {=INDIRECT($B36&"!M46")-Y36-Z36-AB36} -> #REF! | AD36: {=INDIRECT($B36&"!M47")-SUM(Y36:AC36)} -> #REF! | AF36: {=INDIRECT($B36&"!M60")} -> #REF! | AG36: {=INDIRECT($B36&"!M61")+INDIRECT($B36&"!M62")} -> #REF! | AH36: =SUMIFS([1]餐饮!D:D,[1]餐饮!B:B,D36,[1]餐饮!C:C,"Laundry 洗涤费") -> #VALUE! | AI36: {=INDIRECT($B36&"!M63")-AH36} -> #REF! | AJ36: {=INDIRECT($B36&"!M64")-SUM(AE36:AI36)} -> #REF! | AK36: =SUMIFS([1]新零售!D:D,[1]新零售!B:B,D36,[1]新零售!C:C,"Total Cost of Sales 总销售成本") -> #VALUE! | AL36: =SUMIFS([1]康乐温泉!C:C,[1]康乐温泉!A:A,D36,[1]康乐温泉!B:B,"Total Cost of Sales 总销售成本")+SUMIFS([1]康乐温泉!C:C,[1]康乐温泉!A:A,D36,[1]康乐温泉!B:B,"Total Other Expenses 其他费用合计") -> #VALUE! | AP36: {=INDIRECT($B36&"!M91")+INDIRECT($B36&"!M92")} -> #REF! | AQ36: {=INDIRECT($B36&"!M93")+INDIRECT($B36&"!M94")+INDIRECT($B36&"!M95")+INDIRECT($B36&"!M96")} -> #REF! | AR36: {=INDIRECT($B36&"!M98")+INDIRECT($B36&"!M99")} -> #REF! | AT36: {=INDIRECT($B36&"!M100")} -> #REF! | AU36: {=INDIRECT($B36&"!M103")+INDIRECT($B36&"!M104")} -> #REF! | AV36: {=INDIRECT($B36&"!M36")} -> #REF! | AW36: {=INDIRECT($B36&"!M105")-AV36} -> #REF! | AX36: =SUMIFS([1]能源!C:C,[1]能源!A:A,D36,[1]能源!B:B,"Electricity 电费") -> #VALUE! | AY36: =SUMIFS([1]能源!C:C,[1]能源!A:A,D36,[1]能源!B:B,"Steam 蒸汽费")+SUMIFS([1]能源!C:C,[1]能源!A:A,D36,[1]能源!B:B,"Geothermal water 地热水")+SUMIFS([1]能源!C:C,[1]能源!A:A,D36,[1]能源!B:B,"Water 水费") -> #VALUE! | AZ36: =SUMIFS([1]能源!C:C,[1]能源!A:A,D36,[1]能源!B:B,"Gas 煤气费")+SUMIFS([1]能源!C:C,[1]能源!A:A,D36,[1]能源!B:B,"Oil 燃油费") -> #VALUE! | BA36: =SUMIFS([1]能源!C:C,[1]能源!A:A,D36,[1]能源!B:B,"Heating 暖气") -> #VALUE! | BB36: =SUM(AX36:BA36) -> #VALUE! | BC36: =BB36/F36 -> #VALUE! | BD36: {=INDIRECT($B36&"!M101")-SUM(AX36:BA36)} -> #REF! | BG36: {=INDIRECT($B36&"!M119")} -> #REF! | BI36: {=INDIRECT($B36&"!M116")} -> #REF! | BK36: {=INDIRECT($B36&"!M123")} -> #REF! | BM36: {=INDIRECT($B36&"!M117")} -> #REF! | BN36: {=INDIRECT($B36&"!M118")+INDIRECT($B36&"!M120")} -> #REF! | BP36: {=-INDIRECT($B36&"!M114")+INDIRECT($B36&"!M115")-BG36-BI36-BM36-BN36} -> #REF!
A37: 武汉希尔顿 | B37: 武汉希尔顿 | C37: 武汉希尔顿 | D37: 武汉生态城碧桂园投资有限公司希尔顿酒店管理分公司 | E37: =SUM(G37:M37)-F37 -> #REF! | F37: {=INDIRECT($B37&"!M16")} -> #REF! | G37: {=INDIRECT($B37&"!M43")} -> #REF! | J37: {=INDIRECT($B37&"!M54")} -> #REF! | K37: {=INDIRECT($B37&"!M75")} -> #REF! | L37: {=INDIRECT($B37&"!M69")+INDIRECT($B37&"!M70")} -> #REF! | M37: {=INDIRECT($B37&"!M77")-INDIRECT($B37&"!M75")-INDIRECT($B37&"!M69")-INDIRECT($B37&"!M70")} -> #REF! | N37: {=INDIRECT($B37&"!M115")} -> #REF! | O37: =SUM(G37:N37) -> #REF! | P37: {=INDIRECT($B37&"!M31")} -> #REF! | Q37: =P37/F37 -> #REF! | R37: {=INDIRECT($B37&"!M34")} -> #REF! | S37: =R37/F37 -> #REF! | T37: {=INDIRECT($B37&"!M38")} -> #REF! | V37: =T37/F37 -> #REF! | W37: {=INDIRECT($B37&"!M36")} -> #REF! | X37: =W37/F37 -> #REF! | Y37: =SUMIFS([1]客房!D:D,[1]客房!B:B,D37,[1]客房!C:C,"Reservation Fees 预订成本") -> #VALUE! | Z37: =SUMIFS([1]客房!D:D,[1]客房!B:B,D37,[1]客房!C:C," Total Cost of Sales 总销售成本") -> #VALUE! | AA37: {=INDIRECT($B37&"!M44")+INDIRECT($B37&"!M45")} -> #REF! | AB37: =SUMIFS([1]客房!D:D,[1]客房!B:B,D37,[1]客房!C:C,"Laundry 洗涤费") -> #VALUE! | AC37: {=INDIRECT($B37&"!M46")-Y37-Z37-AB37} -> #REF! | AD37: {=INDIRECT($B37&"!M47")-SUM(Y37:AC37)} -> #REF! | AF37: {=INDIRECT($B37&"!M60")} -> #REF! | AG37: {=INDIRECT($B37&"!M61")+INDIRECT($B37&"!M62")} -> #REF! | AH37: =SUMIFS([1]餐饮!D:D,[1]餐饮!B:B,D37,[1]餐饮!C:C,"Laundry 洗涤费") -> #VALUE! | AI37: {=INDIRECT($B37&"!M63")-AH37} -> #REF! | AJ37: {=INDIRECT($B37&"!M64")-SUM(AE37:AI37)} -> #REF! | AK37: =SUMIFS([1]新零售!D:D,[1]新零售!B:B,D37,[1]新零售!C:C,"Total Cost of Sales 总销售成本") -> #VALUE! | AL37: =SUMIFS([1]康乐温泉!C:C,[1]康乐温泉!A:A,D37,[1]康乐温泉!B:B,"Total Cost of Sales 总销售成本")+SUMIFS([1]康乐温泉!C:C,[1]康乐温泉!A:A,D37,[1]康乐温泉!B:B,"Total Other Expenses 其他费用合计") -> #VALUE! | AP37: {=INDIRECT($B37&"!M91")+INDIRECT($B37&"!M92")} -> #REF! | AQ37: {=INDIRECT($B37&"!M93")+INDIRECT($B37&"!M94")+INDIRECT($B37&"!M95")+INDIRECT($B37&"!M96")} -> #REF! | AR37: {=INDIRECT($B37&"!M98")+INDIRECT($B37&"!M99")} -> #REF! | AT37: {=INDIRECT($B37&"!M100")} -> #REF! | AU37: {=INDIRECT($B37&"!M103")+INDIRECT($B37&"!M104")} -> #REF! | AV37: {=INDIRECT($B37&"!M36")} -> #REF! | AW37: {=INDIRECT($B37&"!M105")-AV37} -> #REF! | AX37: =SUMIFS([1]能源!C:C,[1]能源!A:A,D37,[1]能源!B:B,"Electricity 电费") -> #VALUE! | AY37: =SUMIFS([1]能源!C:C,[1]能源!A:A,D37,[1]能源!B:B,"Steam 蒸汽费")+SUMIFS([1]能源!C:C,[1]能源!A:A,D37,[1]能源!B:B,"Geothermal water 地热水")+SUMIFS([1]能源!C:C,[1]能源!A:A,D37,[1]能源!B:B,"Water 水费") -> #VALUE! | AZ37: =SUMIFS([1]能源!C:C,[1]能源!A:A,D37,[1]能源!B:B,"Gas 煤气费")+SUMIFS([1]能源!C:C,[1]能源!A:A,D37,[1]能源!B:B,"Oil 燃油费") -> #VALUE! | BA37: =SUMIFS([1]能源!C:C,[1]能源!A:A,D37,[1]能源!B:B,"Heating 暖气") -> #VALUE! | BB37: =SUM(AX37:BA37) -> #VALUE! | BC37: =BB37/F37 -> #VALUE! | BD37: {=INDIRECT($B37&"!M101")-SUM(AX37:BA37)} -> #REF! | BG37: {=INDIRECT($B37&"!M119")} -> #REF! | BI37: {=INDIRECT($B37&"!M116")} -> #REF! | BK37: {=INDIRECT($B37&"!M123")} -> #REF! | BM37: {=INDIRECT($B37&"!M117")} -> #REF! | BN37: {=INDIRECT($B37&"!M118")+INDIRECT($B37&"!M120")} -> #REF! | BP37: {=-INDIRECT($B37&"!M114")+INDIRECT($B37&"!M115")-BG37-BI37-BM37-BN37} -> #REF!
A38: 佛山希尔顿 | B38: 佛山希尔顿 | C38: 佛山希尔顿 | D38: 佛山碧桂园酒店有限公司希尔顿酒店管理分公司 | E38: =SUM(G38:M38)-F38 -> #REF! | F38: {=INDIRECT($B38&"!M16")} -> #REF! | G38: {=INDIRECT($B38&"!M43")} -> #REF! | J38: {=INDIRECT($B38&"!M54")} -> #REF! | K38: {=INDIRECT($B38&"!M75")} -> #REF! | L38: {=INDIRECT($B38&"!M69")+INDIRECT($B38&"!M70")} -> #REF! | M38: {=INDIRECT($B38&"!M77")-INDIRECT($B38&"!M75")-INDIRECT($B38&"!M69")-INDIRECT($B38&"!M70")} -> #REF! | N38: {=INDIRECT($B38&"!M115")} -> #REF! | O38: =SUM(G38:N38) -> #REF! | P38: {=INDIRECT($B38&"!M31")} -> #REF! | Q38: =P38/F38 -> #REF! | R38: {=INDIRECT($B38&"!M34")} -> #REF! | S38: =R38/F38 -> #REF! | T38: {=INDIRECT($B38&"!M38")} -> #REF! | V38: =T38/F38 -> #REF! | W38: {=INDIRECT($B38&"!M36")} -> #REF! | X38: =W38/F38 -> #REF! | Y38: =SUMIFS([1]客房!D:D,[1]客房!B:B,D38,[1]客房!C:C,"Reservation Fees 预订成本") -> #VALUE! | Z38: =SUMIFS([1]客房!D:D,[1]客房!B:B,D38,[1]客房!C:C," Total Cost of Sales 总销售成本") -> #VALUE! | AA38: {=INDIRECT($B38&"!M44")+INDIRECT($B38&"!M45")} -> #REF! | AB38: =SUMIFS([1]客房!D:D,[1]客房!B:B,D38,[1]客房!C:C,"Laundry 洗涤费") -> #VALUE! | AC38: {=INDIRECT($B38&"!M46")-Y38-Z38-AB38} -> #REF! | AD38: {=INDIRECT($B38&"!M47")-SUM(Y38:AC38)} -> #REF! | AF38: {=INDIRECT($B38&"!M60")} -> #REF! | AG38: {=INDIRECT($B38&"!M61")+INDIRECT($B38&"!M62")} -> #REF! | AH38: =SUMIFS([1]餐饮!D:D,[1]餐饮!B:B,D38,[1]餐饮!C:C,"Laundry 洗涤费") -> #VALUE! | AI38: {=INDIRECT($B38&"!M63")-AH38} -> #REF! | AJ38: {=INDIRECT($B38&"!M64")-SUM(AE38:AI38)} -> #REF! | AK38: =SUMIFS([1]新零售!D:D,[1]新零售!B:B,D38,[1]新零售!C:C,"Total Cost of Sales 总销售成本") -> #VALUE! | AL38: =SUMIFS([1]康乐温泉!C:C,[1]康乐温泉!A:A,D38,[1]康乐温泉!B:B,"Total Cost of Sales 总销售成本")+SUMIFS([1]康乐温泉!C:C,[1]康乐温泉!A:A,D38,[1]康乐温泉!B:B,"Total Other Expenses 其他费用合计") -> #VALUE! | AP38: {=INDIRECT($B38&"!M91")+INDIRECT($B38&"!M92")} -> #REF! | AQ38: {=INDIRECT($B38&"!M93")+INDIRECT($B38&"!M94")+INDIRECT($B38&"!M95")+INDIRECT($B38&"!M96")} -> #REF! | AR38: {=INDIRECT($B38&"!M98")+INDIRECT($B38&"!M99")} -> #REF! | AT38: {=INDIRECT($B38&"!M100")} -> #REF! | AU38: {=INDIRECT($B38&"!M103")+INDIRECT($B38&"!M104")} -> #REF! | AV38: {=INDIRECT($B38&"!M36")} -> #REF! | AW38: {=INDIRECT($B38&"!M105")-AV38} -> #REF! | AX38: =SUMIFS([1]能源!C:C,[1]能源!A:A,D38,[1]能源!B:B,"Electricity 电费") -> #VALUE! | AY38: =SUMIFS([1]能源!C:C,[1]能源!A:A,D38,[1]能源!B:B,"Steam 蒸汽费")+SUMIFS([1]能源!C:C,[1]能源!A:A,D38,[1]能源!B:B,"Geothermal water 地热水")+SUMIFS([1]能源!C:C,[1]能源!A:A,D38,[1]能源!B:B,"Water 水费") -> #VALUE! | AZ38: =SUMIFS([1]能源!C:C,[1]能源!A:A,D38,[1]能源!B:B,"Gas 煤气费")+SUMIFS([1]能源!C:C,[1]能源!A:A,D38,[1]能源!B:B,"Oil 燃油费") -> #VALUE! | BA38: =SUMIFS([1]能源!C:C,[1]能源!A:A,D38,[1]能源!B:B,"Heating 暖气") -> #VALUE! | BB38: =SUM(AX38:BA38) -> #VALUE! | BC38: =BB38/F38 -> #VALUE! | BD38: {=INDIRECT($B38&"!M101")-SUM(AX38:BA38)} -> #REF! | BG38: {=INDIRECT($B38&"!M119")} -> #REF! | BI38: {=INDIRECT($B38&"!M116")} -> #REF! | BK38: {=INDIRECT($B38&"!M123")} -> #REF! | BM38: {=INDIRECT($B38&"!M117")} -> #REF! | BN38: {=INDIRECT($B38&"!M118")+INDIRECT($B38&"!M120")} -> #REF! | BP38: {=-INDIRECT($B38&"!M114")+INDIRECT($B38&"!M115")-BG38-BI38-BM38-BN38} -> #REF!

Sheet 汇总明细-1月
B1: 酒店简称 | C1: 收入 | H1: 经营毛利 | M1: 业主利润返还（上报口径） | R1: 整体 | T1: 客房 | Y1: 餐饮 | AB1: 未分配 | AG1: 总 | AH1: 客房 | AK1: 餐饮 | AO1: 未分配 | AU1: 30 | AZ1: 当月 | BA1: 当月 | BB1: 累计 | BC1: 累计 | BE1: 当月-完成 | BF1: 当月-预算 | BG1: 累计-完成 | BH1: 累计-预算 | BJ1: 当月-完成 | BK1: 累计-完成 | BL1: 完成-当月 | BM1: 完成-累计 | BN1: 预算-当月 | BO1: 预算-累计 | BP1: 去年-当月 | BQ1: 去年-累计 | BR1: 今年-折旧摊销 | BS1: 今年-折旧摊销 | BT1: 去年-折旧摊销 | BU1: 去年-折旧摊销 | BW1: 当月-完成 | BX1: 完成-累计 | BY1: 全年累计 | BZ1: 当月-完成 | CA1: 完成-累计 | CC1: 当月-完成 | CD1: 完成-累计
C2: 完成 | D2: 指标 | E2: 完成率 | F2: 同期 | G2: 同比率 | H2: 完成 | I2: 指标 | J2: 完成率 | K2: 同期 | L2: 同比率 | M2: 完成 | N2: 指标 | O2: 完成率 | P2: 同期 | Q2: 同比率 | R2: 元均创收 | S2: GOP率 | T2: OCC | U2: ADR | V2: RevPAR | W2: 元均创收 | X2: 客房利润率 | Y2: 毛利率 | Z2: 元均创收 | AA2: 餐饮利润率 | AB2: 能耗占比 | AC2: 元均创收 | AD2: 营销费用率 | AE2: 未分配费用占比 | AG2: 人工 | AH2: 收入 | AI2: 人工 | AJ2: 利润 | AK2: 收入 | AL2: 餐饮毛利 | AM2: 人工 | AN2: 利润 | AO2: 能耗 | AP2: 人工 | AQ2: 预订费 | AR2: 未分配合计 | AS2: 可出租房 | AT2: 实际出租房 | AU2: 房间数 | AW2: 非经营收入-当月 | AX2: 非经营收入-累计 | AZ2: 调整经营毛利 | BA2: 低值易耗品摊销 | BB2: 调整经营毛利 | BC2: 低值易耗品摊销 | BE2: 租赁收入 | BF2: 租赁收入 | BG2: 租赁收入 | BH2: 租赁收入 | BJ2: 业主利润返还 | BK2: 业主利润返还 | BL2: 净利润 | BM2: 净利润 | BN2: 净利润 | BO2: 净利润 | BP2: 净利润 | BQ2: 净利润 | BR2: 当月 | BS2: 累计 | BT2: 当月 | BU2: 累计 | BW2: FFE | BX2: FFE | BY2: FFE | BZ2: 业主费用 | CA2: 业主费用 | CC2: 政府补助 | CD2: 政府补助
A3: 凤悦军令状合计： | B3: 汇总 | C3: =SUM(C5:C7) -> 4097415.6 | D3: =SUM(D5:D7) -> 4483405.9 | E3: =C3/D3 -> 0.91390691 | F3: =SUM(F5:F7) -> 5001951.3 | G3: =C3/F3-1 -> -0.18083656 | H3: =SUM(H5:H7) -> -646980.91 | I3: =SUM(I5:I7) -> -468430.93 | J3: =H3/I3 -> 1.3811661 | K3: =SUM(K5:K7) -> -712127.33 | L3: =IF(K3>0,H3/K3-1,IF(K3<0,1-H3/K3,"")) -> 0.091481421 | M3: =SUM(M5:M7) -> -1023395.4 | N3: =SUM(N5:N7) -> -853700.55 | O3: =IF(N3<0,2-M3/N3,M3/N3) -> 0.80122434 | P3: =SUM(P5:P7) -> -1166285.5 | Q3: =IF(P3>0,M3/P3-1,IF(P3<0,1-M3/P3,"")) -> 0.1225172 | R3: =C3/AG3 -> 2.1563777 | S3: =H3/C3 -> -0.15789975 | T3: =AT3/AS3 -> 0.21552663 | W3: =AH3/AI3 -> 3.6946797 | X3: =AJ3/AH3 -> 0.54364998 | Y3: =AL3/AK3 -> 0.55209861 | Z3: =AK3/AM3 -> 3.9033234 | AA3: =AN3/AK3 -> 0.26807803 | AB3: =AO3/C3 -> 0.29535062 | AC3: =C3/AP3 -> 4.7004373 | AD3: =AQ3/C3 -> 0.027139483 | AE3: =AR3/C3 -> 0.56572205 | AG3: =SUM(AG5:AG7) -> 1900138.2 | AH3: =SUM(AH5:AH7) -> 1706402 | AI3: =SUM(AI5:AI7) -> 461853.84 | AJ3: =SUM(AJ5:AJ7) -> 927685.41 | AK3: =SUM(AK5:AK7) -> 2211525.1 | AL3: =SUM(AL5:AL7) -> 1220980 | AM3: =SUM(AM5:AM7) -> 566574.92 | AN3: =SUM(AN5:AN7) -> 592861.31 | ... AU3: =SUM(AU5:AU7) -> 1290.6333 | BL3: =SUM(BL5:BL7) -> -2331107.6 | BM3: =SUM(BM5:BM7) -> -2331107.6 | BN3: =SUM(BN5:BN7) -> -2149807 | BO3: =SUM(BO5:BO7) -> -2149807 | BP3: =SUM(BP5:BP7) -> -2767586.4 | BQ3: =SUM(BQ5:BQ7) -> -2767586.4 | BR3: =SUM(BR5:BR7) -> 589904.35 | BS3: =SUM(BS5:BS7) -> 589904.35 | ... BU3: =SUM(BU5:BU7) -> 594993.27
A4: 凤悦事业部合计： | B4: 凤悦事业部合计： | C4: =SUM(C5:C7) -> 4097415.6 | D4: =SUM(D5:D7) -> 4483405.9 | E4: =C4/D4 -> 0.91390691 | F4: =SUM(F5:F7) -> 5001951.3 | G4: =C4/F4-1 -> -0.18083656 | H4: =SUM(H5:H7) -> -646980.91 | I4: =SUM(I5:I7) -> -468430.93 | J4: =H4/I4 -> 1.3811661 | K4: =SUM(K5:K7) -> -712127.33 | L4: =IF(K4>0,H4/K4-1,IF(K4<0,1-H4/K4,"")) -> 0.091481421 | M4: =SUM(M5:M7) -> -1023395.4 | N4: =SUM(N5:N7) -> -853700.55 | O4: =IF(N4<0,2-M4/N4,M4/N4) -> 0.80122434 | P4: =SUM(P5:P7) -> -1166285.5 | Q4: =IF(P4>0,M4/P4-1,IF(P4<0,1-M4/P4,"")) -> 0.1225172 | R4: =C4/AG4 -> 2.1563777 | S4: =H4/C4 -> -0.15789975 | T4: =AT4/AS4 -> 0.21552663 | W4: =AH4/AI4 -> 3.6946797 | X4: =AJ4/AH4 -> 0.54364998 | Y4: =AL4/AK4 -> 0.55209861 | Z4: =AK4/AM4 -> 3.9033234 | AA4: =AN4/AK4 -> 0.26807803 | AB4: =AO4/C4 -> 0.29535062 | AC4: =C4/AP4 -> 4.7004373 | AD4: =AQ4/C4 -> 0.027139483 | AE4: =AR4/C4 -> 0.56572205 | AG4: =SUM(AG5:AG7) -> 1900138.2 | AH4: =SUM(AH5:AH7) -> 1706402 | AI4: =SUM(AI5:AI7) -> 461853.84 | AJ4: =SUM(AJ5:AJ7) -> 927685.41 | AK4: =SUM(AK5:AK7) -> 2211525.1 | AL4: =SUM(AL5:AL7) -> 1220980 | AM4: =SUM(AM5:AM7) -> 566574.92 | AN4: =SUM(AN5:AN7) -> 592861.31 | ... AU4: =SUM(AU5:AU7) -> 1290.6333 | BL4: =SUM(BL5:BL7) -> -2331107.6 | BM4: =SUM(BM5:BM7) -> -2331107.6 | BN4: =SUM(BN5:BN7) -> -2149807 | BO4: =SUM(BO5:BO7) -> -2149807 | BP4: =SUM(BP5:BP7) -> -2767586.4 | BQ4: =SUM(BQ5:BQ7) -> -2767586.4 | BW4: =SUM(BW5:BW7) -> 103771.04 | BX4: =SUM(BX5:BX7) -> 103771.04 | BY4: =SUM(BY5:BY7) -> 1361952.5 | BZ4: =SUM(BZ5:BZ7) -> 0 | CA4: =SUM(CA5:CA7) -> 0 | CB4: =SUM(CB5:CB7) -> 0 | CC4: =SUM(CC5:CC7) -> 0 | CD4: =SUM(CD5:CD7) -> 0
A5: 于洪酒店 | B5: 于洪 | C5: {=INDIRECT($B5&"!H158")} -> 2831815.9 | D5: {=INDIRECT($B5&"!I158")} -> 2691281.4 | E5: {=INDIRECT($B5&"!J158")} -> 1.0522184 | F5: {=INDIRECT($B5&"!K158")} -> 2941734.5 | G5: {=INDIRECT($B5&"!L158")} -> -0.037365231 | H5: {=INDIRECT($B5&"!M158")} -> -343047.74 | I5: {=INDIRECT($B5&"!N158")} -> -251910.2 | J5: {=INDIRECT($B5&"!O158")} -> 0.63821417 | K5: {=INDIRECT($B5&"!P158")} -> -556666.38 | L5: {=INDIRECT($B5&"!Q158")} -> 0.38374626 | M5: {=INDIRECT($B5&"!R158")} -> -587351.47 | N5: {=INDIRECT($B5&"!S158")} -> -512203.25 | O5: {=INDIRECT($B5&"!T158")} -> 0.85328437 | P5: {=INDIRECT($B5&"!U158")} -> -847994.68 | Q5: {=INDIRECT($B5&"!V158")} -> 0.3073642 | R5: {=INDIRECT($B5&"!W158")} -> 2.5475392 | S5: {=INDIRECT($B5&"!X158")} -> -0.12114055 | T5: {=INDIRECT($B5&"!Y158")} -> 0.31282051 | U5: {=INDIRECT($B5&"!Z158")} -> 199.24168 | V5: {=INDIRECT($B5&"!AA158")} -> 62.326886 | W5: {=INDIRECT($B5&"!AB158")} -> 3.9706353 | X5: {=INDIRECT($B5&"!AC158")} -> 0.56916345 | Y5: {=INDIRECT($B5&"!AD158")} -> 0.53898494 | Z5: {=INDIRECT($B5&"!AE158")} -> 5.0071107 | AA5: {=INDIRECT($B5&"!AF158")} -> 0.311165 | AB5: {=INDIRECT($B5&"!AG158")} -> 0.33181395 | AC5: {=INDIRECT($B5&"!AH158")} -> 5.5028084 | AD5: {=INDIRECT($B5&"!AI158")} -> 0.02304718 | AE5: {=INDIRECT($B5&"!AJ158")} -> 0.55986208 | AG5: =C5/R5 -> 1111588.8 | AH5: {=INDIRECT($B5&"!H43")} -> 1138840.1 | AI5: =AH5/W5 -> 286815.6 | AJ5: =AH5*X5 -> 648186.18 | AK5: {=INDIRECT($B5&"!H56")} -> 1553007 | AL5: =AK5*Y5 -> 837047.4 | AM5: =IF(Z5=0,,AK5/Z5) -> 310160.31 | AN5: =AK5*AA5 -> 483241.43 | AO5: =C5*AB5 -> 939636.01 | AP5: =C5/AC5 -> 514612.85 | AQ5: =AD5*C5 -> 65265.37 | AR5: =C5*AE5 -> 1585426.3 | AS5: {=INDIRECT($B5&"!H6")} -> 17982 | AT5: {=INDIRECT($B5&"!H7")} -> 5673 | AU5: {=INDIRECT($B5&"!H5")/$AU$1} -> 604.5 | AW5: {=INDIRECT($B5&"!H23")} -> -416992.64 | AX5: {=INDIRECT($B5&"!M23")} -> -416992.64 | AZ5: {=INDIRECT(B5&"!H111")} -> -413116.79 | BA5: {=INDIRECT(B5&"!H129")} -> 174234.68 | BB5: {=INDIRECT(B5&"!M111")} -> -413116.79 | BC5: {=INDIRECT(B5&"!M129")} -> 174234.68 | BE5: {=INDIRECT($B5&"!H75")} -> 69952.73 | BF5: {=INDIRECT($B5&"!I75")} -> 48543.69 | BG5: {=INDIRECT($B5&"!M75")} -> 69952.73 | BH5: {=INDIRECT($B5&"!N75")} -> 48543.69 | BJ5: {=INDIRECT($B5&"!H148")} -> -587351.47 | BK5: {=INDIRECT($B5&"!M148")} -> -587351.47 | BL5: {=INDIRECT($B5&"!H132")} -> -1021850.6 | BM5: {=INDIRECT($B5&"!M132")} -> -1021850.6 | BN5: {=INDIRECT($B5&"!I132")} -> -911715.03 | BO5: {=INDIRECT($B5&"!N132")} -> -911715.03 | BP5: {=INDIRECT($B5&"!K132")} -> -1559193.2 | BQ5: {=INDIRECT($B5&"!P132")} -> -1559193.2 | BR5: {=INDIRECT($B5&"!H128")} -> 17506.46 | BS5: {=INDIRECT($B5&"!M128")} -> 17506.46 | BT5: {=INDIRECT($B5&"!K128")} -> 16628.66 | BU5: {=INDIRECT($B5&"!P128")} -> 16628.66 | BW5: {=INDIRECT($B5&"!H123")} -> 103771.04 | BX5: {=INDIRECT($B5&"!M123")} -> 103771.04 | BY5: {=INDIRECT($B5&"!R123")} -> 1361952.5 | BZ5: {=INDIRECT($B5&"!H119")} -> 0 | CA5: {=INDIRECT($B5&"!M119")} -> 0 | CC5: {=INDIRECT($B5&"!AK158")} -> 0 | CD5: {=INDIRECT($B5&"!AK159")} -> 0
A6: 滁州酒店 | B6: 滁州 | C6: {=INDIRECT($B6&"!H158")} -> 129030.87 | D6: {=INDIRECT($B6&"!I158")} -> 631295.71 | E6: {=INDIRECT($B6&"!J158")} -> 0.20439054 | F6: {=INDIRECT($B6&"!K158")} -> 808427.54 | G6: {=INDIRECT($B6&"!L158")} -> -0.84039278 | H6: {=INDIRECT($B6&"!M158")} -> -361955.44 | I6: {=INDIRECT($B6&"!N158")} -> -126727.92 | J6: {=INDIRECT($B6&"!O158")} -> -0.85616177 | K6: {=INDIRECT($B6&"!P158")} -> 23988.07 | L6: {=INDIRECT($B6&"!Q158")} -> -16.088977 | M6: {=INDIRECT($B6&"!R158")} -> -406462.45 | N6: {=INDIRECT($B6&"!S158")} -> -176856.06 | O6: {=INDIRECT($B6&"!T158")} -> -0.29826702 | P6: {=INDIRECT($B6&"!U158")} -> -49250.41 | Q6: {=INDIRECT($B6&"!V158")} -> -7.252976 | R6: {=INDIRECT($B6&"!W158")} -> 0.51806265 | S6: {=INDIRECT($B6&"!X158")} -> -2.8051848 | T6: {=INDIRECT($B6&"!Y158")} -> 0.032112758 | U6: {=INDIRECT($B6&"!Z158")} -> 165.84338 | V6: {=INDIRECT($B6&"!AA158")} -> 5.3256883 | W6: {=INDIRECT($B6&"!AB158")} -> 0.81298809 | X6: {=INDIRECT($B6&"!AC158")} -> -0.59771863 | Y6: {=INDIRECT($B6&"!AD158")} -> 0.47804757 | Z6: {=INDIRECT($B6&"!AE158")} -> 0.98638897 | AA6: {=INDIRECT($B6&"!AF158")} -> -0.5975288 | AB6: {=INDIRECT($B6&"!AG158")} -> 1.0659493 | AC6: {=INDIRECT($B6&"!AH158")} -> 1.1984064 | AD6: {=INDIRECT($B6&"!AI158")} -> 0.0016072898 | AE6: {=INDIRECT($B6&"!AJ158")} -> 2.2241329 | AG6: =C6/R6 -> 249064.22 | AH6: {=INDIRECT($B6&"!H43")} -> 55218.59 | AI6: =AH6/W6 -> 67920.54 | AJ6: =AH6*X6 -> -33005.18 | AK6: {=INDIRECT($B6&"!H56")} -> 72474.9 | AL6: =AK6*Y6 -> 34646.45 | AM6: =IF(Z6=0,,AK6/Z6) -> 73474.97 | AN6: =AK6*AA6 -> -43305.84 | AO6: =C6*AB6 -> 137540.37 | AP6: =C6/AC6 -> 107668.71 | AQ6: =AD6*C6 -> 207.39 | AR6: =C6*AE6 -> 286981.8 | AS6: {=INDIRECT($B6&"!H6")} -> 10323 | AT6: {=INDIRECT($B6&"!H7")} -> 331.5 | AU6: {=INDIRECT($B6&"!H5")/$AU$1} -> 344.1 | AW6: {=INDIRECT($B6&"!H23")} -> -146465.9 | AX6: {=INDIRECT($B6&"!M23")} -> -146465.9 | AZ6: {=INDIRECT(B6&"!H111")} -> -365091.52 | BA6: {=INDIRECT(B6&"!H129")} -> 41370.93 | BB6: {=INDIRECT(B6&"!M111")} -> -365091.52 | BC6: {=INDIRECT(B6&"!M129")} -> 41370.93 | BE6: {=INDIRECT($B6&"!H75")} -> 1070.34 | BF6: {=INDIRECT($B6&"!I75")} -> 4587.16 | BG6: {=INDIRECT($B6&"!M75")} -> 1070.34 | BH6: {=INDIRECT($B6&"!N75")} -> 4587.16 | BJ6: {=INDIRECT($B6&"!H148")} -> -406462.45 | BK6: {=INDIRECT($B6&"!M148")} -> -406462.45 | BL6: {=INDIRECT($B6&"!H132")} -> -574847.52 | BM6: {=INDIRECT($B6&"!M132")} -> -574847.52 | BN6: {=INDIRECT($B6&"!I132")} -> -368794.93 | BO6: {=INDIRECT($B6&"!N132")} -> -368794.93 | BP6: {=INDIRECT($B6&"!K132")} -> -240283.7 | BQ6: {=INDIRECT($B6&"!P132")} -> -240283.7 | BR6: {=INDIRECT($B6&"!H128")} -> 21919.17 | BS6: {=INDIRECT($B6&"!M128")} -> 21919.17 | BT6: {=INDIRECT($B6&"!K128")} -> 23471.43 | BU6: {=INDIRECT($B6&"!P128")} -> 23471.43 | BW6: {=INDIRECT($B6&"!H123")} -> 0 | BX6: {=INDIRECT($B6&"!M123")} -> 0 | BY6: {=INDIRECT($B6&"!R123")} -> 0 | BZ6: {=INDIRECT($B6&"!H119")} -> 0 | CA6: {=INDIRECT($B6&"!M119")} -> 0 | CC6: {=INDIRECT($B6&"!AK158")} -> 0 | CD6: {=INDIRECT($B6&"!AK159")} -> 0
A7: 武汉酒店 | B7: 武汉 | C7: {=INDIRECT($B7&"!H158")} -> 1136568.8 | D7: {=INDIRECT($B7&"!I158")} -> 1160828.7 | E7: {=INDIRECT($B7&"!J158")} -> 0.97910122 | F7: {=INDIRECT($B7&"!K158")} -> 1251789.2 | G7: {=INDIRECT($B7&"!L158")} -> -0.092044583 | H7: {=INDIRECT($B7&"!M158")} -> 58022.27 | I7: {=INDIRECT($B7&"!N158")} -> -89792.81 | J7: {=INDIRECT($B7&"!O158")} -> 2.6461795 | K7: {=INDIRECT($B7&"!P158")} -> -179449.02 | L7: {=INDIRECT($B7&"!Q158")} -> 1.3233357 | M7: {=INDIRECT($B7&"!R158")} -> -29581.52 | N7: {=INDIRECT($B7&"!S158")} -> -164641.24 | O7: {=INDIRECT($B7&"!T158")} -> 1.8203274 | P7: {=INDIRECT($B7&"!U158")} -> -269040.38 | Q7: {=INDIRECT($B7&"!V158")} -> 0.89004803 | R7: {=INDIRECT($B7&"!W158")} -> 2.1067655 | S7: {=INDIRECT($B7&"!X158")} -> 0.051050379 | T7: {=INDIRECT($B7&"!Y158")} -> 0.22488062 | U7: {=INDIRECT($B7&"!Z158")} -> 221.8789 | V7: {=INDIRECT($B7&"!AA158")} -> 49.896264 | W7: {=INDIRECT($B7&"!AB158")} -> 4.7829935 | X7: {=INDIRECT($B7&"!AC158")} -> 0.60995125 | Y7: {=INDIRECT($B7&"!AD158")} -> 0.59600743 | Z7: {=INDIRECT($B7&"!AE158")} -> 3.2034786 | AA7: {=INDIRECT($B7&"!AF158")} -> 0.26094614 | AB7: {=INDIRECT($B7&"!AG158")} -> 0.117017 | AC7: {=INDIRECT($B7&"!AH158")} -> 4.5567032 | AD7: {=INDIRECT($B7&"!AI158")} -> 0.040234237 | AE7: {=INDIRECT($B7&"!AJ158")} -> 0.39204858 | AG7: =C7/R7 -> 539485.22 | AH7: {=INDIRECT($B7&"!H43")} -> 512343.26 | AI7: =AH7/W7 -> 107117.7 | AJ7: =AH7*X7 -> 312504.41 | AK7: {=INDIRECT($B7&"!H56")} -> 586043.23 | AL7: =AK7*Y7 -> 349286.12 | AM7: =IF(Z7=0,,AK7/Z7) -> 182939.64 | AN7: =AK7*AA7 -> 152925.72 | AO7: =C7*AB7 -> 132997.87 | AP7: =C7/AC7 -> 249427.88 | AQ7: =AD7*C7 -> 45728.98 | AR7: =C7*AE7 -> 445590.2 | AS7: {=INDIRECT($B7&"!H6")} -> 10261 | AT7: {=INDIRECT($B7&"!H7")} -> 2307.5 | AU7: {=INDIRECT($B7&"!H5")/$AU$1} -> 342.03333 | AW7: {=INDIRECT($B7&"!H23")} -> -138945.96 | AX7: {=INDIRECT($B7&"!M23")} -> -138945.96 | AZ7: {=INDIRECT(B7&"!H111")} -> 29490.46 | BA7: {=INDIRECT(B7&"!H129")} -> 59071.98 | BB7: {=INDIRECT(B7&"!M111")} -> 29490.46 | BC7: {=INDIRECT(B7&"!M129")} -> 59071.98 | BE7: {=INDIRECT($B7&"!H75")} -> 36757.13 | BF7: {=INDIRECT($B7&"!I75")} -> 19479.43 | BG7: {=INDIRECT($B7&"!M75")} -> 36757.13 | BH7: {=INDIRECT($B7&"!N75")} -> 19479.43 | BJ7: {=INDIRECT($B7&"!H148")} -> -29581.52 | BK7: {=INDIRECT($B7&"!M148")} -> -29581.52 | BL7: {=INDIRECT($B7&"!H132")} -> -734409.49 | BM7: {=INDIRECT($B7&"!M132")} -> -734409.49 | BN7: {=INDIRECT($B7&"!I132")} -> -869297 | BO7: {=INDIRECT($B7&"!N132")} -> -869297 | BP7: {=INDIRECT($B7&"!K132")} -> -968109.48 | BQ7: {=INDIRECT($B7&"!P132")} -> -968109.48 | BR7: {=INDIRECT($B7&"!H128")} -> 550478.72 | BS7: {=INDIRECT($B7&"!M128")} -> 550478.72 | BT7: {=INDIRECT($B7&"!K128")} -> 554893.18 | BU7: {=INDIRECT($B7&"!P128")} -> 554893.18 | BW7: {=INDIRECT($B7&"!H123")} -> 0 | BX7: {=INDIRECT($B7&"!M123")} -> 0 | BY7: {=INDIRECT($B7&"!R123")} -> 0 | BZ7: {=INDIRECT($B7&"!H119")} -> 0 | CA7: {=INDIRECT($B7&"!M119")} -> 0 | CC7: {=INDIRECT($B7&"!AK158")} -> 0 | CD7: {=INDIRECT($B7&"!AK159")} -> 0

Sheet 汇总明细-累计
B1: 酒店简称 | C1: 收入 | J1: 经营毛利 | Q1: 业主利润返还（上报口径） | X1: 整体 | Z1: 客房 | AE1: 餐饮 | AH1: 未分配 | AM1: 总 | AN1: 客房 | AQ1: 餐饮 | AU1: 未分配 | BB1: 全年预算 | BC1: 全年预算 | BD1: 全年预算
C2: 完成 | D2: 指标 | E2: 完成率 | F2: 同期 | G2: 同比率 | H2: 全年目标 | I2: 全年完成率 | J2: 完成 | K2: 指标 | L2: 完成率 | M2: 同期 | N2: 同比率 | O2: 全年目标 | P2: 全年完成率 | Q2: 完成 | R2: 指标 | S2: 完成率 | T2: 同期 | U2: 同比率 | V2: 全年目标 | W2: 全年完成率 | X2: 元均创收 | Y2: GOP率 | Z2: OCC | AA2: ADR | AB2: RevPAR | AC2: 元均创收 | AD2: 客房利润率 | AE2: 毛利率 | AF2: 元均创收 | AG2: 餐饮利润率 | AH2: 能耗占比 | AI2: 元均创收 | AJ2: 营销费用率 | AK2: 未分配费用占比 | AM2: 人工 | AN2: 收入 | AO2: 人工 | AP2: 利润 | AQ2: 收入 | AR2: 餐饮毛利 | AS2: 人工 | AT2: 利润 | AU2: 能耗 | AV2: 人工 | AW2: 预定费 | AX2: 未分配合计 | AY2: 可出租房 | AZ2: 实际出租房 | BA2: 房间数 | BB2: 总收入 | BC2: 经营毛利 | BD2: 业主返还利润（上报）
A3: 凤悦军令状合计： | B3: 汇总 | C3: =SUM(C5:C7) -> 4097415.6 | D3: =SUM(D5:D7) -> 4483405.9 | E3: =C3/D3 -> 0.91390691 | F3: =SUM(F5:F7) -> 5001951.3 | G3: =C3/F3-1 -> -0.18083656 | H3: =SUM(H5:H7) -> 65708706 | I3: =IF(BB3=0,"",IF(BB3<0,2-C3/BB3,C3/BB3)) -> 0.062357272 | J3: =SUM(J5:J7) -> -646980.91 | K3: =SUM(K5:K7) -> -468430.93 | L3: =J3/K3 -> 1.3811661 | M3: =SUM(M5:M7) -> -712127.33 | N3: =IF(M3>0,J3/M3-1,IF(M3<0,1-J3/M3,"")) -> 0.091481421 | O3: =SUM(O5:O7) -> 6027250.7 | P3: =IF(BC3=0,"",IF(BC3<0,2-J3/BC3,J3/BC3)) -> -0.10734263 | Q3: =SUM(Q5:Q7) -> -1023395.4 | R3: =SUM(R5:R7) -> -853700.55 | S3: =IF(R3<0,2-Q3/R3,Q3/R3) -> 0.80122434 | T3: =SUM(T5:T7) -> -1166285.5 | U3: =IF(T3>0,Q3/T3-1,IF(T3<0,1-Q3/T3,"")) -> 0.1225172 | V3: =SUM(V5:V7) -> 1332304 | W3: =IF(BD3=0,"",IF(BD3<0,2-Q3/BD3,Q3/BD3)) -> -0.76813958 | X3: =C3/AM3 -> 2.1563777 | Y3: =J3/C3 -> -0.15789975 | Z3: =AZ3/AY3 -> 0.21552663 | AC3: =AN3/AO3 -> 3.6946797 | AD3: =AP3/AN3 -> 0.54364998 | AE3: =AR3/AQ3 -> 0.55209861 | AF3: =AQ3/AS3 -> 3.9033234 | AG3: =AT3/AQ3 -> 0.26807803 | AH3: =AU3/C3 -> 0.29535062 | AI3: =C3/AV3 -> 4.7004373 | AJ3: =AW3/C3 -> 0.027139483 | AK3: =AX3/C3 -> 0.56572205 | AM3: =SUM(AM5:AM7) -> 1900138.2 | AN3: =SUM(AN5:AN7) -> 1706402 | AO3: =SUM(AO5:AO7) -> 461853.84 | AP3: =SUM(AP5:AP7) -> 927685.41 | AQ3: =SUM(AQ5:AQ7) -> 2211525.1 | AR3: =SUM(AR5:AR7) -> 1220980 | AS3: =SUM(AS5:AS7) -> 566574.92 | AT3: =SUM(AT5:AT7) -> 592861.31 | ... BD3: =SUM(BD5:BD7) -> 1332304
A4: 凤悦事业部合计： | B4: 凤悦事业部合计： | C4: =SUM(C5:C7) -> 4097415.6 | D4: =SUM(D5:D7) -> 4483405.9 | E4: =C4/D4 -> 0.91390691 | F4: =SUM(F5:F7) -> 5001951.3 | G4: =C4/F4-1 -> -0.18083656 | H4: =SUM(H5:H7) -> 65708706 | I4: =IF(BB4=0,"",IF(BB4<0,2-C4/BB4,C4/BB4)) -> 0.062357272 | J4: =SUM(J5:J7) -> -646980.91 | K4: =SUM(K5:K7) -> -468430.93 | L4: =J4/K4 -> 1.3811661 | M4: =SUM(M5:M7) -> -712127.33 | N4: =IF(M4>0,J4/M4-1,IF(M4<0,1-J4/M4,"")) -> 0.091481421 | O4: =SUM(O5:O7) -> 6027250.7 | P4: =IF(BC4=0,"",IF(BC4<0,2-J4/BC4,J4/BC4)) -> -0.10734263 | Q4: =SUM(Q5:Q7) -> -1023395.4 | R4: =SUM(R5:R7) -> -853700.55 | S4: =IF(R4<0,2-Q4/R4,Q4/R4) -> 0.80122434 | T4: =SUM(T5:T7) -> -1166285.5 | U4: =IF(T4>0,Q4/T4-1,IF(T4<0,1-Q4/T4,"")) -> 0.1225172 | V4: =SUM(V5:V7) -> 1332304 | W4: =IF(BD4=0,"",IF(BD4<0,2-Q4/BD4,Q4/BD4)) -> -0.76813958 | X4: =C4/AM4 -> 2.1563777 | Y4: =J4/C4 -> -0.15789975 | Z4: =AZ4/AY4 -> 0.21552663 | AC4: =AN4/AO4 -> 3.6946797 | AD4: =AP4/AN4 -> 0.54364998 | AE4: =AR4/AQ4 -> 0.55209861 | AF4: =AQ4/AS4 -> 3.9033234 | AG4: =AT4/AQ4 -> 0.26807803 | AH4: =AU4/C4 -> 0.29535062 | AI4: =C4/AV4 -> 4.7004373 | AJ4: =AW4/C4 -> 0.027139483 | AK4: =AX4/C4 -> 0.56572205 | AM4: =SUM(AM5:AM7) -> 1900138.2 | AN4: =SUM(AN5:AN7) -> 1706402 | AO4: =SUM(AO5:AO7) -> 461853.84 | AP4: =SUM(AP5:AP7) -> 927685.41 | AQ4: =SUM(AQ5:AQ7) -> 2211525.1 | AR4: =SUM(AR5:AR7) -> 1220980 | AS4: =SUM(AS5:AS7) -> 566574.92 | AT4: =SUM(AT5:AT7) -> 592861.31 | ... BD4: =SUM(BD5:BD7) -> 1332304
A5: 于洪酒店 | B5: 于洪 | C5: {=INDIRECT($B5&"!H159")} -> 2831815.9 | D5: {=INDIRECT($B5&"!I159")} -> 2691281.4 | E5: {=INDIRECT($B5&"!J159")} -> 1.0522184 | F5: {=INDIRECT($B5&"!K159")} -> 2941734.5 | G5: {=INDIRECT($B5&"!L159")} -> -0.037365231 | H5: {=INDIRECT($B5&"!R16")} -> 36674896 | I5: =IF(BB5=0,"",IF(BB5<0,2-C5/BB5,C5/BB5)) -> 0.077214013 | J5: {=INDIRECT($B5&"!M159")} -> -343047.74 | K5: {=INDIRECT($B5&"!N159")} -> -251910.2 | L5: {=INDIRECT($B5&"!O159")} -> 0.63821417 | M5: {=INDIRECT($B5&"!P159")} -> -556666.38 | N5: {=INDIRECT($B5&"!Q159")} -> 0.38374626 | O5: {=INDIRECT($B5&"!R20")} -> 3300000 | P5: =IF(BC5=0,"",IF(BC5<0,2-J5/BC5,J5/BC5)) -> -0.10395386 | Q5: {=INDIRECT($B5&"!R159")} -> -587351.47 | R5: {=INDIRECT($B5&"!S159")} -> -512203.25 | S5: {=INDIRECT($B5&"!T159")} -> 0.85328437 | T5: {=INDIRECT($B5&"!U159")} -> -847994.68 | U5: {=INDIRECT($B5&"!V159")} -> 0.3073642 | V5: {=INDIRECT($B5&"!R148")} -> 245325.72 | W5: =IF(BD5=0,"",IF(BD5<0,2-Q5/BD5,Q5/BD5)) -> -2.39417 | X5: {=INDIRECT($B5&"!W159")} -> 2.5475392 | Y5: {=INDIRECT($B5&"!X159")} -> -0.12114055 | Z5: {=INDIRECT($B5&"!Y159")} -> 0.31282051 | AA5: {=INDIRECT($B5&"!Z159")} -> 199.24168 | AB5: {=INDIRECT($B5&"!AA159")} -> 62.326886 | AC5: {=INDIRECT($B5&"!AB159")} -> 3.9706353 | AD5: {=INDIRECT($B5&"!AC159")} -> 0.56916345 | AE5: {=INDIRECT($B5&"!AD159")} -> 0.53898494 | AF5: {=INDIRECT($B5&"!AE159")} -> 5.0071107 | AG5: {=INDIRECT($B5&"!AF159")} -> 0.311165 | AH5: {=INDIRECT($B5&"!AG159")} -> 0.33181395 | AI5: {=INDIRECT($B5&"!AH159")} -> 5.5028084 | AJ5: {=INDIRECT($B5&"!AI159")} -> 0.02304718 | AK5: {=INDIRECT($B5&"!AJ159")} -> 0.55986208 | AM5: =C5/X5 -> 1111588.8 | AN5: {=INDIRECT($B5&"!M43")} -> 1138840.1 | AO5: =AN5/AC5 -> 286815.6 | AP5: =AN5*AD5 -> 648186.18 | AQ5: {=INDIRECT($B5&"!M56")} -> 1553007 | AR5: =AQ5*AE5 -> 837047.4 | AS5: =AQ5/AF5 -> 310160.31 | AT5: =AQ5*AG5 -> 483241.43 | AU5: =C5*AH5 -> 939636.01 | AV5: =C5/AI5 -> 514612.85 | AW5: =AJ5*C5 -> 65265.37 | AX5: =C5*AK5 -> 1585426.3 | AY5: =INDIRECT($B5&"!M6") -> 17982 | AZ5: {=INDIRECT($B5&"!M7")} -> 5673 | BA5: ='汇总明细-1月'!AU5 -> 604.5 | BB5: {=INDIRECT($B5&"!R16")} -> 36674896 | BC5: {=INDIRECT($B5&"!R20")} -> 3300000 | BD5: {=INDIRECT($B5&"!R148")} -> 245325.72
A6: 滁州酒店 | B6: 滁州 | C6: {=INDIRECT($B6&"!H159")} -> 129030.87 | D6: {=INDIRECT($B6&"!I159")} -> 631295.71 | E6: {=INDIRECT($B6&"!J159")} -> 0.20439054 | F6: {=INDIRECT($B6&"!K159")} -> 808427.54 | G6: {=INDIRECT($B6&"!L159")} -> -0.84039278 | H6: {=INDIRECT($B6&"!R16")} -> 11217170 | I6: =IF(BB6=0,"",IF(BB6<0,2-C6/BB6,C6/BB6)) -> 0.011502979 | J6: {=INDIRECT($B6&"!M159")} -> -361955.44 | K6: {=INDIRECT($B6&"!N159")} -> -126727.92 | L6: {=INDIRECT($B6&"!O159")} -> -0.85616177 | M6: {=INDIRECT($B6&"!P159")} -> 23988.07 | N6: {=INDIRECT($B6&"!Q159")} -> -16.088977 | O6: {=INDIRECT($B6&"!R20")} -> 760000.31 | P6: =IF(BC6=0,"",IF(BC6<0,2-J6/BC6,J6/BC6)) -> -0.47625696 | Q6: {=INDIRECT($B6&"!R159")} -> -406462.45 | R6: {=INDIRECT($B6&"!S159")} -> -176856.06 | S6: {=INDIRECT($B6&"!T159")} -> -0.29826702 | T6: {=INDIRECT($B6&"!U159")} -> -49250.41 | U6: {=INDIRECT($B6&"!V159")} -> -7.252976 | V6: {=INDIRECT($B6&"!R148")} -> 103838.07 | W6: =IF(BD6=0,"",IF(BD6<0,2-Q6/BD6,Q6/BD6)) -> -3.9143876 | X6: {=INDIRECT($B6&"!W159")} -> 0.51806265 | Y6: {=INDIRECT($B6&"!X159")} -> -2.8051848 | Z6: {=INDIRECT($B6&"!Y159")} -> 0.032112758 | AA6: {=INDIRECT($B6&"!Z159")} -> 165.84338 | AB6: {=INDIRECT($B6&"!AA159")} -> 5.3256883 | AC6: {=INDIRECT($B6&"!AB159")} -> 0.81298809 | AD6: {=INDIRECT($B6&"!AC159")} -> -0.59771863 | AE6: {=INDIRECT($B6&"!AD159")} -> 0.47804757 | AF6: {=INDIRECT($B6&"!AE159")} -> 0.98638897 | AG6: {=INDIRECT($B6&"!AF159")} -> -0.5975288 | AH6: {=INDIRECT($B6&"!AG159")} -> 1.0659493 | AI6: {=INDIRECT($B6&"!AH159")} -> 1.1984064 | AJ6: {=INDIRECT($B6&"!AI159")} -> 0.0016072898 | AK6: {=INDIRECT($B6&"!AJ159")} -> 2.2241329 | AM6: =C6/X6 -> 249064.22 | AN6: {=INDIRECT($B6&"!M43")} -> 55218.59 | AO6: =AN6/AC6 -> 67920.54 | AP6: =AN6*AD6 -> -33005.18 | AQ6: {=INDIRECT($B6&"!M56")} -> 72474.9 | AR6: =AQ6*AE6 -> 34646.45 | AS6: =AQ6/AF6 -> 73474.97 | AT6: =AQ6*AG6 -> -43305.84 | AU6: =C6*AH6 -> 137540.37 | AV6: =C6/AI6 -> 107668.71 | AW6: =AJ6*C6 -> 207.39 | AX6: =C6*AK6 -> 286981.8 | AY6: {=INDIRECT($B6&"!M6")} -> 10323 | AZ6: {=INDIRECT($B6&"!M7")} -> 331.5 | BA6: ='汇总明细-1月'!AU6 -> 344.1 | BB6: {=INDIRECT($B6&"!R16")} -> 11217170 | BC6: {=INDIRECT($B6&"!R20")} -> 760000.31 | BD6: {=INDIRECT($B6&"!R148")} -> 103838.07
A7: 武汉酒店 | B7: 武汉 | C7: {=INDIRECT($B7&"!H159")} -> 1136568.8 | D7: {=INDIRECT($B7&"!I159")} -> 1160828.7 | E7: {=INDIRECT($B7&"!J159")} -> 0.97910122 | F7: {=INDIRECT($B7&"!K159")} -> 1251789.2 | G7: {=INDIRECT($B7&"!L159")} -> -0.092044583 | H7: {=INDIRECT($B7&"!R16")} -> 17816639 | I7: =IF(BB7=0,"",IF(BB7<0,2-C7/BB7,C7/BB7)) -> 0.063792549 | J7: {=INDIRECT($B7&"!M159")} -> 58022.27 | K7: {=INDIRECT($B7&"!N159")} -> -89792.81 | L7: {=INDIRECT($B7&"!O159")} -> 2.6461795 | M7: {=INDIRECT($B7&"!P159")} -> -179449.02 | N7: {=INDIRECT($B7&"!Q159")} -> 1.3233357 | O7: {=INDIRECT($B7&"!R20")} -> 1967250.4 | P7: =IF(BC7=0,"",IF(BC7<0,2-J7/BC7,J7/BC7)) -> 0.029494095 | Q7: {=INDIRECT($B7&"!R159")} -> -29581.52 | R7: {=INDIRECT($B7&"!S159")} -> -164641.24 | S7: {=INDIRECT($B7&"!T159")} -> 1.8203274 | T7: {=INDIRECT($B7&"!U159")} -> -269040.38 | U7: {=INDIRECT($B7&"!V159")} -> 0.89004803 | V7: {=INDIRECT($B7&"!R148")} -> 983140.22 | W7: =IF(BD7=0,"",IF(BD7<0,2-Q7/BD7,Q7/BD7)) -> -0.030088811 | X7: {=INDIRECT($B7&"!W159")} -> 2.1067655 | Y7: {=INDIRECT($B7&"!X159")} -> 0.051050379 | Z7: {=INDIRECT($B7&"!Y159")} -> 0.22488062 | AA7: {=INDIRECT($B7&"!Z159")} -> 221.8789 | AB7: {=INDIRECT($B7&"!AA159")} -> 49.896264 | AC7: {=INDIRECT($B7&"!AB159")} -> 4.7829935 | AD7: {=INDIRECT($B7&"!AC159")} -> 0.60995125 | AE7: {=INDIRECT($B7&"!AD159")} -> 0.59600743 | AF7: {=INDIRECT($B7&"!AE159")} -> 3.2034786 | AG7: {=INDIRECT($B7&"!AF159")} -> 0.26094614 | AH7: {=INDIRECT($B7&"!AG159")} -> 0.117017 | AI7: {=INDIRECT($B7&"!AH159")} -> 4.5567032 | AJ7: {=INDIRECT($B7&"!AI159")} -> 0.040234237 | AK7: {=INDIRECT($B7&"!AJ159")} -> 0.39204858 | AM7: =C7/X7 -> 539485.22 | AN7: {=INDIRECT($B7&"!M43")} -> 512343.26 | AO7: =AN7/AC7 -> 107117.7 | AP7: =AN7*AD7 -> 312504.41 | AQ7: {=INDIRECT($B7&"!M56")} -> 586043.23 | AR7: =AQ7*AE7 -> 349286.12 | AS7: =AQ7/AF7 -> 182939.64 | AT7: =AQ7*AG7 -> 152925.72 | AU7: =C7*AH7 -> 132997.87 | AV7: =C7/AI7 -> 249427.88 | AW7: =AJ7*C7 -> 45728.98 | AX7: =C7*AK7 -> 445590.2 | AY7: {=INDIRECT($B7&"!M6")} -> 10261 | AZ7: {=INDIRECT($B7&"!M7")} -> 2307.5 | BA7: ='汇总明细-1月'!AU7 -> 342.03333 | BB7: {=INDIRECT($B7&"!R16")} -> 17816639 | BC7: {=INDIRECT($B7&"!R20")} -> 1967250.4 | BD7: {=INDIRECT($B7&"!R148")} -> 983140.22

Sheet 当月-能耗
B1: 完成 | I1: 预算 | P1: 上年同期
A2: 酒店 | B2: 可出租房 | C2: 开房数 | D2: 开房率 | E2: 总收入（不含税） | F2: 不动产租赁（不含税） | G2: 能源消耗汇总 | H2: 维修费用汇总 | I2: 可出租房 | J2: 开房数 | K2: 开房率 | L2: 总收入（不含税） | M2: 不动产租赁（不含税） | N2: 能源消耗汇总 | O2: 维修费用汇总 | P2: 可出租房 | Q2: 开房数 | R2: 开房率 | S2: 总收入（不含税） | T2: 不动产租赁（不含税） | U2: 能源消耗汇总 | V2: 维修费用汇总
A3: 于洪 | B3: {=INDIRECT($A3&"!H5")} -> 18135 | C3: {=INDIRECT($A3&"!H7")} -> 5673 | D3: {=INDIRECT($A3&"!H9")} -> 0.31282051 | E3: {=INDIRECT($A3&"!H16")} -> 2831815.9 | F3: {=INDIRECT($A3&"!H75")} -> 69952.73 | G3: {=INDIRECT($A3&"!H34")} -> 939636.01 | H3: {=INDIRECT($A3&"!H36")} -> 46717.47 | I3: {=INDIRECT($A3&"!I5")} -> 18104 | J3: {=INDIRECT($A3&"!I7")} -> 4468 | K3: {=INDIRECT($A3&"!I9")} -> 0.24679629 | L3: {=INDIRECT($A3&"!I16")} -> 2691281.4 | M3: {=INDIRECT($A3&"!I75")} -> 48543.69 | N3: {=INDIRECT($A3&"!I34")} -> 780583.94 | O3: {=INDIRECT($A3&"!I36")} -> 42167 | P3: {=INDIRECT($A3&"!K5")} -> 19561 | Q3: {=INDIRECT($A3&"!K7")} -> 4260 | R3: {=INDIRECT($A3&"!K9")} -> 0.21778028 | S3: {=INDIRECT($A3&"!K16")} -> 2941734.5 | T3: {=INDIRECT($A3&"!K75")} -> 47126.04 | U3: {=INDIRECT($A3&"!K34")} -> 962610.95 | V3: {=INDIRECT($A3&"!K36")} -> 35318.51
A4: 滁州 | B4: {=INDIRECT($A4&"!H5")} -> 10323 | C4: {=INDIRECT($A4&"!H7")} -> 331.5 | D4: {=INDIRECT($A4&"!H9")} -> 0.032112758 | E4: {=INDIRECT($A4&"!H16")} -> 129030.87 | F4: {=INDIRECT($A4&"!H75")} -> 1070.34 | G4: {=INDIRECT($A4&"!H34")} -> 137540.37 | H4: {=INDIRECT($A4&"!H36")} -> 16743.95 | I4: {=INDIRECT($A4&"!I5")} -> 10323 | J4: {=INDIRECT($A4&"!I7")} -> 1850 | K4: {=INDIRECT($A4&"!I9")} -> 0.17921147 | L4: {=INDIRECT($A4&"!I16")} -> 631295.71 | M4: {=INDIRECT($A4&"!I75")} -> 4587.16 | N4: {=INDIRECT($A4&"!I34")} -> 114000 | O4: {=INDIRECT($A4&"!I36")} -> 20000 | P4: {=INDIRECT($A4&"!K5")} -> 10323 | Q4: {=INDIRECT($A4&"!K7")} -> 2026.5 | R4: {=INDIRECT($A4&"!K9")} -> 0.19630921 | S4: {=INDIRECT($A4&"!K16")} -> 808427.54 | T4: {=INDIRECT($A4&"!K75")} -> 4344.65 | U4: {=INDIRECT($A4&"!K34")} -> 124352.42 | V4: {=INDIRECT($A4&"!K36")} -> 12546.82
A5: 武汉 | B5: {=INDIRECT($A5&"!H5")} -> 10261 | C5: {=INDIRECT($A5&"!H7")} -> 2307.5 | D5: {=INDIRECT($A5&"!H9")} -> 0.22488062 | E5: {=INDIRECT($A5&"!H16")} -> 1136568.8 | F5: {=INDIRECT($A5&"!H75")} -> 36757.13 | G5: {=INDIRECT($A5&"!H34")} -> 132997.87 | H5: {=INDIRECT($A5&"!H36")} -> 18239.38 | I5: {=INDIRECT($A5&"!I5")} -> 10261 | J5: {=INDIRECT($A5&"!I7")} -> 2427 | K5: {=INDIRECT($A5&"!I9")} -> 0.23652665 | L5: {=INDIRECT($A5&"!I16")} -> 1160828.7 | M5: {=INDIRECT($A5&"!I75")} -> 19479.43 | N5: {=INDIRECT($A5&"!I34")} -> 144300 | O5: {=INDIRECT($A5&"!I36")} -> 28000 | P5: {=INDIRECT($A5&"!K5")} -> 10261 | Q5: {=INDIRECT($A5&"!K7")} -> 1824 | R5: {=INDIRECT($A5&"!K9")} -> 0.17776045 | S5: {=INDIRECT($A5&"!K16")} -> 1251789.2 | T5: {=INDIRECT($A5&"!K75")} -> 21942.06 | U5: {=INDIRECT($A5&"!K34")} -> 120892.18 | V5: {=INDIRECT($A5&"!K36")} -> 32562.07

Sheet 累计-能耗
B1: 完成 | I1: 预算 | P1: 上年同期
A2: 酒店 | B2: 可出租房 | C2: 开房数 | D2: 开房率 | E2: 总收入（不含税） | F2: 不动产租赁（不含税） | G2: 能源消耗汇总 | H2: 维修费用汇总 | I2: 可出租房 | J2: 开房数 | K2: 开房率 | L2: 总收入（不含税） | M2: 不动产租赁（不含税） | N2: 能源消耗汇总 | O2: 维修费用汇总 | P2: 可出租房 | Q2: 开房数 | R2: 开房率 | S2: 总收入（不含税） | T2: 不动产租赁（不含税） | U2: 能源消耗汇总 | V2: 维修费用汇总
A3: 于洪 | B3: {=INDIRECT($A3&"!M5")} -> 18135 | C3: {=INDIRECT($A3&"!M7")} -> 5673 | D3: {=INDIRECT($A3&"!M9")} -> 0.31282051 | E3: {=INDIRECT($A3&"!M16")} -> 2831815.9 | F3: {=INDIRECT($A3&"!M75")} -> 69952.73 | G3: {=INDIRECT($A3&"!M34")} -> 939636.01 | H3: {=INDIRECT($A3&"!M36")} -> 46717.47 | I3: {=INDIRECT($A3&"!N5")} -> 18104 | J3: {=INDIRECT($A3&"!N7")} -> 4468 | K3: {=INDIRECT($A3&"!N9")} -> 0.24679629 | L3: {=INDIRECT($A3&"!N16")} -> 2691281.4 | M3: {=INDIRECT($A3&"!N75")} -> 48543.69 | N3: {=INDIRECT($A3&"!N34")} -> 780583.94 | O3: {=INDIRECT($A3&"!N36")} -> 42167 | P3: {=INDIRECT($A3&"!P5")} -> 19561 | Q3: {=INDIRECT($A3&"!P7")} -> 4260 | R3: {=INDIRECT($A3&"!P9")} -> 0.21778028 | S3: {=INDIRECT($A3&"!P16")} -> 2941734.5 | T3: {=INDIRECT($A3&"!P75")} -> 47126.04 | U3: {=INDIRECT($A3&"!P34")} -> 962610.95 | V3: {=INDIRECT($A3&"!P36")} -> 35318.51
A4: 滁州 | B4: {=INDIRECT($A4&"!M5")} -> 10323 | C4: {=INDIRECT($A4&"!M7")} -> 331.5 | D4: {=INDIRECT($A4&"!M9")} -> 0.032112758 | E4: {=INDIRECT($A4&"!M16")} -> 129030.87 | F4: {=INDIRECT($A4&"!M75")} -> 1070.34 | G4: {=INDIRECT($A4&"!M34")} -> 137540.37 | H4: {=INDIRECT($A4&"!M36")} -> 16743.95 | I4: {=INDIRECT($A4&"!N5")} -> 10323 | J4: {=INDIRECT($A4&"!N7")} -> 1850 | K4: {=INDIRECT($A4&"!N9")} -> 0.17921147 | L4: {=INDIRECT($A4&"!N16")} -> 631295.71 | M4: {=INDIRECT($A4&"!N75")} -> 4587.16 | N4: {=INDIRECT($A4&"!N34")} -> 114000 | O4: {=INDIRECT($A4&"!N36")} -> 20000 | P4: {=INDIRECT($A4&"!P5")} -> 10323 | Q4: {=INDIRECT($A4&"!P7")} -> 2026.5 | R4: {=INDIRECT($A4&"!P9")} -> 0.19630921 | S4: {=INDIRECT($A4&"!P16")} -> 808427.54 | T4: {=INDIRECT($A4&"!P75")} -> 4344.65 | U4: {=INDIRECT($A4&"!P34")} -> 124352.42 | V4: {=INDIRECT($A4&"!P36")} -> 12546.82
A5: 武汉 | B5: {=INDIRECT($A5&"!M5")} -> 10261 | C5: {=INDIRECT($A5&"!M7")} -> 2307.5 | D5: {=INDIRECT($A5&"!M9")} -> 0.22488062 | E5: {=INDIRECT($A5&"!M16")} -> 1136568.8 | F5: {=INDIRECT($A5&"!M75")} -> 36757.13 | G5: {=INDIRECT($A5&"!M34")} -> 132997.87 | H5: {=INDIRECT($A5&"!M36")} -> 18239.38 | I5: {=INDIRECT($A5&"!N5")} -> 10261 | J5: {=INDIRECT($A5&"!N7")} -> 2427 | K5: {=INDIRECT($A5&"!N9")} -> 0.23652665 | L5: {=INDIRECT($A5&"!N16")} -> 1160828.7 | M5: {=INDIRECT($A5&"!N75")} -> 19479.43 | N5: {=INDIRECT($A5&"!N34")} -> 144300 | O5: {=INDIRECT($A5&"!N36")} -> 28000 | P5: {=INDIRECT($A5&"!P5")} -> 10261 | Q5: {=INDIRECT($A5&"!P7")} -> 1824 | R5: {=INDIRECT($A5&"!P9")} -> 0.17776045 | S5: {=INDIRECT($A5&"!P16")} -> 1251789.2 | T5: {=INDIRECT($A5&"!P75")} -> 21942.06 | U5: {=INDIRECT($A5&"!P34")} -> 120892.18 | V5: {=INDIRECT($A5&"!P36")} -> 32562.07

Sheet 当月排名取数
B1: 整体 | C1: 整体 | D1: 整体 | E1: 整体 | F1: 整体 | G1: 整体 | H1: 整体 | I1: 整体 | J1: 整体 | K1: 整体 | L1: 客房 | M1: 客房 | N1: 客房 | O1: 客房 | P1: 客房 | Q1: 客房 | R1: 客房 | S1: 客房 | T1: 客房 | U1: 客房 | V1: 餐饮 | W1: 餐饮 | X1: 餐饮 | Y1: 餐饮 | Z1: 餐饮 | AA1: 餐饮 | AB1: 未分配 | AC1: 未分配 | AD1: 未分配 | AE1: 未分配 | AF1: 未分配 | AG1: 未分配 | AH1: 未分配 | AI1: 未分配
B2: 总收入 | C2: 总收入 | D2: 经营毛利 | E2: 经营毛利 | F2: 业主利润返还（上报） | G2: 业主利润返还（上报） | H2: 元均创收（元） | I2: 元均创收（元） | J2: GOP率 | K2: GOP率 | L2: OCC | M2: OCC | N2: ADR（元） | O2: ADR（元） | P2: RevPAR（元） | Q2: RevPAR（元） | R2: 元均创收（元） | S2: 元均创收（元） | T2: 客房利润率 | U2: 客房利润率 | V2: 毛利率 | W2: 毛利率 | X2: 元均创收（元） | Y2: 元均创收（元） | Z2: 餐饮利润率 | AA2: 餐饮利润率 | AB2: 能耗占比 | AC2: 能耗占比 | AD2: 元均创收（元） | AE2: 元均创收（元） | AF2: 营销费用率 | AG2: 营销费用率 | AH2: 未分配费用占比 | AI2: 未分配费用占比
A3: 酒店 | B3: 当月完成 | C3: 排名 | D3: 当月完成 | E3: 排名 | F3: 当月完成 | G3: 排名 | H3: 当月完成 | I3: 排名 | J3: 当月完成 | K3: 排名 | L3: 当月完成 | M3: 排名 | N3: 当月完成 | O3: 排名 | P3: 当月完成 | Q3: 排名 | R3: 当月完成 | S3: 排名 | T3: 当月完成 | U3: 排名 | V3: 当月完成 | W3: 排名 | X3: 当月完成 | Y3: 排名 | Z3: 当月完成 | AA3: 排名 | AB3: 当月完成 | AC3: 排名 | AD3: 当月完成 | AE3: 排名 | AF3: 当月完成 | AG3: 排名 | AH3: 当月完成 | AI3: 排名
A4: 于洪酒店 | B4: =VLOOKUP($A4,'汇总-1月'!$B$5:$AE$23,2,0) -> 283.18159 | C4: =RANK(B4,$B$4:$B$59) -> #N/A | D4: =VLOOKUP($A4,'汇总-1月'!$B$5:$AE$23,7,0) -> -34.304774 | E4: =RANK(D4,$D$4:$D$59) -> #N/A | F4: =VLOOKUP($A4,'汇总-1月'!$B$5:$AE$23,12,0) -> -58.735147 | G4: =RANK(F4,$F$4:$F$59) -> #N/A | H4: =VLOOKUP($A4,'汇总-1月'!$B$5:$AE$23,17,0) -> 2.5475392 | I4: =RANK(H4,$H$4:$H$59) -> #N/A | J4: =VLOOKUP($A4,'汇总-1月'!$B$5:$AE$23,18,0) -> -0.12114055 | K4: =RANK(J4,$J$4:$J$59) -> #N/A | L4: =VLOOKUP($A4,'汇总-1月'!$B$5:$AE$23,19,0) -> 0.31282051 | M4: =RANK(L4,$L$4:$L$59) -> #N/A | N4: =VLOOKUP($A4,'汇总-1月'!$B$5:$AE$23,20,0) -> 199.24168 | O4: =RANK(N4,$N$4:$N$59) -> #N/A | P4: =VLOOKUP($A4,'汇总-1月'!$B$5:$AE$23,21,0) -> 62.326886 | Q4: =RANK(P4,$P$4:$P$59) -> #N/A | R4: =VLOOKUP($A4,'汇总-1月'!$B$5:$AE$23,22,0) -> 3.9706353 | S4: =RANK(R4,$R$4:$R$59) -> #N/A | T4: =VLOOKUP($A4,'汇总-1月'!$B$5:$AE$23,23,0) -> 0.56916345 | U4: =RANK(T4,$T$4:$T$59) -> #N/A | V4: =VLOOKUP($A4,'汇总-1月'!$B$5:$AE$23,24,0) -> 0.53898494 | W4: =RANK(V4,$V$4:$V$59) -> #N/A | X4: =VLOOKUP($A4,'汇总-1月'!$B$5:$AE$23,25,0) -> 5.0071107 | Y4: =RANK(X4,$X$4:$X$59) -> #N/A | Z4: =VLOOKUP($A4,'汇总-1月'!$B$5:$AE$23,26,0) -> 0.311165 | AA4: =RANK(Z4,$Z$4:$Z$59) -> #N/A | AB4: =VLOOKUP($A4,'汇总-1月'!$B$5:$AE$23,27,0) -> 0.33181395 | AC4: =RANK(AB4,$AB$4:$AB$59) -> #N/A | AD4: =VLOOKUP($A4,'汇总-1月'!$B$5:$AE$23,28,0) -> 5.5028084 | AE4: =RANK(AD4,$AD$4:$AD$59) -> #N/A | AF4: =VLOOKUP($A4,'汇总-1月'!$B$5:$AE$23,29,0) -> 0.02304718 | AG4: =RANK(AF4,$AF$4:$AF$59) -> #N/A | AH4: =VLOOKUP($A4,'汇总-1月'!$B$5:$AE$23,30,0) -> 0.55986208 | AI4: =RANK(AH4,$AH$4:$AH$59) -> #N/A
A5: 滁州酒店 | B5: =VLOOKUP($A5,'汇总-1月'!$B$5:$AE$23,2,0) -> 12.903087 | C5: =RANK(B5,$B$4:$B$59) -> #N/A | D5: =VLOOKUP($A5,'汇总-1月'!$B$5:$AE$23,7,0) -> -36.195544 | E5: =RANK(D5,$D$4:$D$59) -> #N/A | F5: =VLOOKUP($A5,'汇总-1月'!$B$5:$AE$23,12,0) -> -40.646245 | G5: =RANK(F5,$F$4:$F$59) -> #N/A | H5: =VLOOKUP($A5,'汇总-1月'!$B$5:$AE$23,17,0) -> 0.51806265 | I5: =RANK(H5,$H$4:$H$59) -> #N/A | J5: =VLOOKUP($A5,'汇总-1月'!$B$5:$AE$23,18,0) -> -2.8051848 | K5: =RANK(J5,$J$4:$J$59) -> #N/A | L5: =VLOOKUP($A5,'汇总-1月'!$B$5:$AE$23,19,0) -> 0.032112758 | M5: =RANK(L5,$L$4:$L$59) -> #N/A | N5: =VLOOKUP($A5,'汇总-1月'!$B$5:$AE$23,20,0) -> 165.84338 | O5: =RANK(N5,$N$4:$N$59) -> #N/A | P5: =VLOOKUP($A5,'汇总-1月'!$B$5:$AE$23,21,0) -> 5.3256883 | Q5: =RANK(P5,$P$4:$P$59) -> #N/A | R5: =VLOOKUP($A5,'汇总-1月'!$B$5:$AE$23,22,0) -> 0.81298809 | S5: =RANK(R5,$R$4:$R$59) -> #N/A | T5: =VLOOKUP($A5,'汇总-1月'!$B$5:$AE$23,23,0) -> -0.59771863 | U5: =RANK(T5,$T$4:$T$59) -> #N/A | V5: =VLOOKUP($A5,'汇总-1月'!$B$5:$AE$23,24,0) -> 0.47804757 | W5: =RANK(V5,$V$4:$V$59) -> #N/A | X5: =VLOOKUP($A5,'汇总-1月'!$B$5:$AE$23,25,0) -> 0.98638897 | Y5: =RANK(X5,$X$4:$X$59) -> #N/A | Z5: =VLOOKUP($A5,'汇总-1月'!$B$5:$AE$23,26,0) -> -0.5975288 | AA5: =RANK(Z5,$Z$4:$Z$59) -> #N/A | AB5: =VLOOKUP($A5,'汇总-1月'!$B$5:$AE$23,27,0) -> 1.0659493 | AC5: =RANK(AB5,$AB$4:$AB$59) -> #N/A | AD5: =VLOOKUP($A5,'汇总-1月'!$B$5:$AE$23,28,0) -> 1.1984064 | AE5: =RANK(AD5,$AD$4:$AD$59) -> #N/A | AF5: =VLOOKUP($A5,'汇总-1月'!$B$5:$AE$23,29,0) -> 0.0016072898 | AG5: =RANK(AF5,$AF$4:$AF$59) -> #N/A | AH5: =VLOOKUP($A5,'汇总-1月'!$B$5:$AE$23,30,0) -> 2.2241329 | AI5: =RANK(AH5,$AH$4:$AH$59) -> #N/A
A6: 武汉酒店 | B6: =VLOOKUP($A6,'汇总-1月'!$B$5:$AE$23,2,0) -> 113.65688 | C6: =RANK(B6,$B$4:$B$59) -> #N/A | D6: =VLOOKUP($A6,'汇总-1月'!$B$5:$AE$23,7,0) -> 5.802227 | E6: =RANK(D6,$D$4:$D$59) -> #N/A | F6: =VLOOKUP($A6,'汇总-1月'!$B$5:$AE$23,12,0) -> -2.958152 | G6: =RANK(F6,$F$4:$F$59) -> #N/A | H6: =VLOOKUP($A6,'汇总-1月'!$B$5:$AE$23,17,0) -> 2.1067655 | I6: =RANK(H6,$H$4:$H$59) -> #N/A | J6: =VLOOKUP($A6,'汇总-1月'!$B$5:$AE$23,18,0) -> 0.051050379 | K6: =RANK(J6,$J$4:$J$59) -> #N/A | L6: =VLOOKUP($A6,'汇总-1月'!$B$5:$AE$23,19,0) -> 0.22488062 | M6: =RANK(L6,$L$4:$L$59) -> #N/A | N6: =VLOOKUP($A6,'汇总-1月'!$B$5:$AE$23,20,0) -> 221.8789 | O6: =RANK(N6,$N$4:$N$59) -> #N/A | P6: =VLOOKUP($A6,'汇总-1月'!$B$5:$AE$23,21,0) -> 49.896264 | Q6: =RANK(P6,$P$4:$P$59) -> #N/A | R6: =VLOOKUP($A6,'汇总-1月'!$B$5:$AE$23,22,0) -> 4.7829935 | S6: =RANK(R6,$R$4:$R$59) -> #N/A | T6: =VLOOKUP($A6,'汇总-1月'!$B$5:$AE$23,23,0) -> 0.60995125 | U6: =RANK(T6,$T$4:$T$59) -> #N/A | V6: =VLOOKUP($A6,'汇总-1月'!$B$5:$AE$23,24,0) -> 0.59600743 | W6: =RANK(V6,$V$4:$V$59) -> #N/A | X6: =VLOOKUP($A6,'汇总-1月'!$B$5:$AE$23,25,0) -> 3.2034786 | Y6: =RANK(X6,$X$4:$X$59) -> #N/A | Z6: =VLOOKUP($A6,'汇总-1月'!$B$5:$AE$23,26,0) -> 0.26094614 | AA6: =RANK(Z6,$Z$4:$Z$59) -> #N/A | AB6: =VLOOKUP($A6,'汇总-1月'!$B$5:$AE$23,27,0) -> 0.117017 | AC6: =RANK(AB6,$AB$4:$AB$59) -> #N/A | AD6: =VLOOKUP($A6,'汇总-1月'!$B$5:$AE$23,28,0) -> 4.5567032 | AE6: =RANK(AD6,$AD$4:$AD$59) -> #N/A | AF6: =VLOOKUP($A6,'汇总-1月'!$B$5:$AE$23,29,0) -> 0.040234237 | AG6: =RANK(AF6,$AF$4:$AF$59) -> #N/A | AH6: =VLOOKUP($A6,'汇总-1月'!$B$5:$AE$23,30,0) -> 0.39204858 | AI6: =RANK(AH6,$AH$4:$AH$59) -> #N/A
A7: 海南临高 | B7: =VLOOKUP($A7,'汇总-1月'!$B$5:$AE$23,2,0) -> #N/A | C7: =RANK(B7,$B$4:$B$59) -> #N/A | D7: =VLOOKUP($A7,'汇总-1月'!$B$5:$AE$23,7,0) -> #N/A | E7: =RANK(D7,$D$4:$D$59) -> #N/A | F7: =VLOOKUP($A7,'汇总-1月'!$B$5:$AE$23,12,0) -> #N/A | G7: =RANK(F7,$F$4:$F$59) -> #N/A | H7: =VLOOKUP($A7,'汇总-1月'!$B$5:$AE$23,17,0) -> #N/A | I7: =RANK(H7,$H$4:$H$59) -> #N/A | J7: =VLOOKUP($A7,'汇总-1月'!$B$5:$AE$23,18,0) -> #N/A | K7: =RANK(J7,$J$4:$J$59) -> #N/A | L7: =VLOOKUP($A7,'汇总-1月'!$B$5:$AE$23,19,0) -> #N/A | M7: =RANK(L7,$L$4:$L$59) -> #N/A | N7: =VLOOKUP($A7,'汇总-1月'!$B$5:$AE$23,20,0) -> #N/A | O7: =RANK(N7,$N$4:$N$59) -> #N/A | P7: =VLOOKUP($A7,'汇总-1月'!$B$5:$AE$23,21,0) -> #N/A | Q7: =RANK(P7,$P$4:$P$59) -> #N/A | R7: =VLOOKUP($A7,'汇总-1月'!$B$5:$AE$23,22,0) -> #N/A | S7: =RANK(R7,$R$4:$R$59) -> #N/A | T7: =VLOOKUP($A7,'汇总-1月'!$B$5:$AE$23,23,0) -> #N/A | U7: =RANK(T7,$T$4:$T$59) -> #N/A | V7: =VLOOKUP($A7,'汇总-1月'!$B$5:$AE$23,24,0) -> #N/A | W7: =RANK(V7,$V$4:$V$59) -> #N/A | X7: =VLOOKUP($A7,'汇总-1月'!$B$5:$AE$23,25,0) -> #N/A | Y7: =RANK(X7,$X$4:$X$59) -> #N/A | Z7: =VLOOKUP($A7,'汇总-1月'!$B$5:$AE$23,26,0) -> #N/A | AA7: =RANK(Z7,$Z$4:$Z$59) -> #N/A | AB7: =VLOOKUP($A7,'汇总-1月'!$B$5:$AE$23,27,0) -> #N/A | AC7: =RANK(AB7,$AB$4:$AB$59) -> #N/A | AD7: =VLOOKUP($A7,'汇总-1月'!$B$5:$AE$23,28,0) -> #N/A | AE7: =RANK(AD7,$AD$4:$AD$59) -> #N/A | AF7: =VLOOKUP($A7,'汇总-1月'!$B$5:$AE$23,29,0) -> #N/A | AG7: =RANK(AF7,$AF$4:$AF$59) -> #N/A | AH7: =VLOOKUP($A7,'汇总-1月'!$B$5:$AE$23,30,0) -> #N/A | AI7: =RANK(AH7,$AH$4:$AH$59) -> #N/A
A8: 三水酒店 | B8: =VLOOKUP($A8,'汇总-1月'!$B$5:$AE$23,2,0) -> #N/A | C8: =RANK(B8,$B$4:$B$59) -> #N/A | D8: =VLOOKUP($A8,'汇总-1月'!$B$5:$AE$23,7,0) -> #N/A | E8: =RANK(D8,$D$4:$D$59) -> #N/A | F8: =VLOOKUP($A8,'汇总-1月'!$B$5:$AE$23,12,0) -> #N/A | G8: =RANK(F8,$F$4:$F$59) -> #N/A | H8: =VLOOKUP($A8,'汇总-1月'!$B$5:$AE$23,17,0) -> #N/A | I8: =RANK(H8,$H$4:$H$59) -> #N/A | J8: =VLOOKUP($A8,'汇总-1月'!$B$5:$AE$23,18,0) -> #N/A | K8: =RANK(J8,$J$4:$J$59) -> #N/A | L8: =VLOOKUP($A8,'汇总-1月'!$B$5:$AE$23,19,0) -> #N/A | M8: =RANK(L8,$L$4:$L$59) -> #N/A | N8: =VLOOKUP($A8,'汇总-1月'!$B$5:$AE$23,20,0) -> #N/A | O8: =RANK(N8,$N$4:$N$59) -> #N/A | P8: =VLOOKUP($A8,'汇总-1月'!$B$5:$AE$23,21,0) -> #N/A | Q8: =RANK(P8,$P$4:$P$59) -> #N/A | R8: =VLOOKUP($A8,'汇总-1月'!$B$5:$AE$23,22,0) -> #N/A | S8: =RANK(R8,$R$4:$R$59) -> #N/A | T8: =VLOOKUP($A8,'汇总-1月'!$B$5:$AE$23,23,0) -> #N/A | U8: =RANK(T8,$T$4:$T$59) -> #N/A | V8: =VLOOKUP($A8,'汇总-1月'!$B$5:$AE$23,24,0) -> #N/A | W8: =RANK(V8,$V$4:$V$59) -> #N/A | X8: =VLOOKUP($A8,'汇总-1月'!$B$5:$AE$23,25,0) -> #N/A | Y8: =RANK(X8,$X$4:$X$59) -> #N/A | Z8: =VLOOKUP($A8,'汇总-1月'!$B$5:$AE$23,26,0) -> #N/A | AA8: =RANK(Z8,$Z$4:$Z$59) -> #N/A | AB8: =VLOOKUP($A8,'汇总-1月'!$B$5:$AE$23,27,0) -> #N/A | AC8: =RANK(AB8,$AB$4:$AB$59) -> #N/A | AD8: =VLOOKUP($A8,'汇总-1月'!$B$5:$AE$23,28,0) -> #N/A | AE8: =RANK(AD8,$AD$4:$AD$59) -> #N/A | AF8: =VLOOKUP($A8,'汇总-1月'!$B$5:$AE$23,29,0) -> #N/A | AG8: =RANK(AF8,$AF$4:$AF$59) -> #N/A | AH8: =VLOOKUP($A8,'汇总-1月'!$B$5:$AE$23,30,0) -> #N/A | AI8: =RANK(AH8,$AH$4:$AH$59) -> #N/A
A9: 泰州酒店 | B9: =VLOOKUP($A9,'汇总-1月'!$B$5:$AE$23,2,0) -> #N/A | C9: =RANK(B9,$B$4:$B$59) -> #N/A | D9: =VLOOKUP($A9,'汇总-1月'!$B$5:$AE$23,7,0) -> #N/A | E9: =RANK(D9,$D$4:$D$59) -> #N/A | F9: =VLOOKUP($A9,'汇总-1月'!$B$5:$AE$23,12,0) -> #N/A | G9: =RANK(F9,$F$4:$F$59) -> #N/A | H9: =VLOOKUP($A9,'汇总-1月'!$B$5:$AE$23,17,0) -> #N/A | I9: =RANK(H9,$H$4:$H$59) -> #N/A | J9: =VLOOKUP($A9,'汇总-1月'!$B$5:$AE$23,18,0) -> #N/A | K9: =RANK(J9,$J$4:$J$59) -> #N/A | L9: =VLOOKUP($A9,'汇总-1月'!$B$5:$AE$23,19,0) -> #N/A | M9: =RANK(L9,$L$4:$L$59) -> #N/A | N9: =VLOOKUP($A9,'汇总-1月'!$B$5:$AE$23,20,0) -> #N/A | O9: =RANK(N9,$N$4:$N$59) -> #N/A | P9: =VLOOKUP($A9,'汇总-1月'!$B$5:$AE$23,21,0) -> #N/A | Q9: =RANK(P9,$P$4:$P$59) -> #N/A | R9: =VLOOKUP($A9,'汇总-1月'!$B$5:$AE$23,22,0) -> #N/A | S9: =RANK(R9,$R$4:$R$59) -> #N/A | T9: =VLOOKUP($A9,'汇总-1月'!$B$5:$AE$23,23,0) -> #N/A | U9: =RANK(T9,$T$4:$T$59) -> #N/A | V9: =VLOOKUP($A9,'汇总-1月'!$B$5:$AE$23,24,0) -> #N/A | W9: =RANK(V9,$V$4:$V$59) -> #N/A | X9: =VLOOKUP($A9,'汇总-1月'!$B$5:$AE$23,25,0) -> #N/A | Y9: =RANK(X9,$X$4:$X$59) -> #N/A | Z9: =VLOOKUP($A9,'汇总-1月'!$B$5:$AE$23,26,0) -> #N/A | AA9: =RANK(Z9,$Z$4:$Z$59) -> #N/A | AB9: =VLOOKUP($A9,'汇总-1月'!$B$5:$AE$23,27,0) -> #N/A | AC9: =RANK(AB9,$AB$4:$AB$59) -> #N/A | AD9: =VLOOKUP($A9,'汇总-1月'!$B$5:$AE$23,28,0) -> #N/A | AE9: =RANK(AD9,$AD$4:$AD$59) -> #N/A | AF9: =VLOOKUP($A9,'汇总-1月'!$B$5:$AE$23,29,0) -> #N/A | AG9: =RANK(AF9,$AF$4:$AF$59) -> #N/A | AH9: =VLOOKUP($A9,'汇总-1月'!$B$5:$AE$23,30,0) -> #N/A | AI9: =RANK(AH9,$AH$4:$AH$59) -> #N/A
A10: 安庆酒店 | B10: =VLOOKUP($A10,'汇总-1月'!$B$5:$AE$23,2,0) -> #N/A | C10: =RANK(B10,$B$4:$B$59) -> #N/A | D10: =VLOOKUP($A10,'汇总-1月'!$B$5:$AE$23,7,0) -> #N/A | E10: =RANK(D10,$D$4:$D$59) -> #N/A | F10: =VLOOKUP($A10,'汇总-1月'!$B$5:$AE$23,12,0) -> #N/A | G10: =RANK(F10,$F$4:$F$59) -> #N/A | H10: =VLOOKUP($A10,'汇总-1月'!$B$5:$AE$23,17,0) -> #N/A | I10: =RANK(H10,$H$4:$H$59) -> #N/A | J10: =VLOOKUP($A10,'汇总-1月'!$B$5:$AE$23,18,0) -> #N/A | K10: =RANK(J10,$J$4:$J$59) -> #N/A | L10: =VLOOKUP($A10,'汇总-1月'!$B$5:$AE$23,19,0) -> #N/A | M10: =RANK(L10,$L$4:$L$59) -> #N/A | N10: =VLOOKUP($A10,'汇总-1月'!$B$5:$AE$23,20,0) -> #N/A | O10: =RANK(N10,$N$4:$N$59) -> #N/A | P10: =VLOOKUP($A10,'汇总-1月'!$B$5:$AE$23,21,0) -> #N/A | Q10: =RANK(P10,$P$4:$P$59) -> #N/A | R10: =VLOOKUP($A10,'汇总-1月'!$B$5:$AE$23,22,0) -> #N/A | S10: =RANK(R10,$R$4:$R$59) -> #N/A | T10: =VLOOKUP($A10,'汇总-1月'!$B$5:$AE$23,23,0) -> #N/A | U10: =RANK(T10,$T$4:$T$59) -> #N/A | V10: =VLOOKUP($A10,'汇总-1月'!$B$5:$AE$23,24,0) -> #N/A | W10: =RANK(V10,$V$4:$V$59) -> #N/A | X10: =VLOOKUP($A10,'汇总-1月'!$B$5:$AE$23,25,0) -> #N/A | Y10: =RANK(X10,$X$4:$X$59) -> #N/A | Z10: =VLOOKUP($A10,'汇总-1月'!$B$5:$AE$23,26,0) -> #N/A | AA10: =RANK(Z10,$Z$4:$Z$59) -> #N/A | AB10: =VLOOKUP($A10,'汇总-1月'!$B$5:$AE$23,27,0) -> #N/A | AC10: =RANK(AB10,$AB$4:$AB$59) -> #N/A | AD10: =VLOOKUP($A10,'汇总-1月'!$B$5:$AE$23,28,0) -> #N/A | AE10: =RANK(AD10,$AD$4:$AD$59) -> #N/A | AF10: =VLOOKUP($A10,'汇总-1月'!$B$5:$AE$23,29,0) -> #N/A | AG10: =RANK(AF10,$AF$4:$AF$59) -> #N/A | AH10: =VLOOKUP($A10,'汇总-1月'!$B$5:$AE$23,30,0) -> #N/A | AI10: =RANK(AH10,$AH$4:$AH$59) -> #N/A
A11: 张家界酒店 | B11: =VLOOKUP($A11,'汇总-1月'!$B$5:$AE$23,2,0) -> #N/A | C11: =RANK(B11,$B$4:$B$59) -> #N/A | D11: =VLOOKUP($A11,'汇总-1月'!$B$5:$AE$23,7,0) -> #N/A | E11: =RANK(D11,$D$4:$D$59) -> #N/A | F11: =VLOOKUP($A11,'汇总-1月'!$B$5:$AE$23,12,0) -> #N/A | G11: =RANK(F11,$F$4:$F$59) -> #N/A | H11: =VLOOKUP($A11,'汇总-1月'!$B$5:$AE$23,17,0) -> #N/A | I11: =RANK(H11,$H$4:$H$59) -> #N/A | J11: =VLOOKUP($A11,'汇总-1月'!$B$5:$AE$23,18,0) -> #N/A | K11: =RANK(J11,$J$4:$J$59) -> #N/A | L11: =VLOOKUP($A11,'汇总-1月'!$B$5:$AE$23,19,0) -> #N/A | M11: =RANK(L11,$L$4:$L$59) -> #N/A | N11: =VLOOKUP($A11,'汇总-1月'!$B$5:$AE$23,20,0) -> #N/A | O11: =RANK(N11,$N$4:$N$59) -> #N/A | P11: =VLOOKUP($A11,'汇总-1月'!$B$5:$AE$23,21,0) -> #N/A | Q11: =RANK(P11,$P$4:$P$59) -> #N/A | R11: =VLOOKUP($A11,'汇总-1月'!$B$5:$AE$23,22,0) -> #N/A | S11: =RANK(R11,$R$4:$R$59) -> #N/A | T11: =VLOOKUP($A11,'汇总-1月'!$B$5:$AE$23,23,0) -> #N/A | U11: =RANK(T11,$T$4:$T$59) -> #N/A | V11: =VLOOKUP($A11,'汇总-1月'!$B$5:$AE$23,24,0) -> #N/A | W11: =RANK(V11,$V$4:$V$59) -> #N/A | X11: =VLOOKUP($A11,'汇总-1月'!$B$5:$AE$23,25,0) -> #N/A | Y11: =RANK(X11,$X$4:$X$59) -> #N/A | Z11: =VLOOKUP($A11,'汇总-1月'!$B$5:$AE$23,26,0) -> #N/A | AA11: =RANK(Z11,$Z$4:$Z$59) -> #N/A | AB11: =VLOOKUP($A11,'汇总-1月'!$B$5:$AE$23,27,0) -> #N/A | AC11: =RANK(AB11,$AB$4:$AB$59) -> #N/A | AD11: =VLOOKUP($A11,'汇总-1月'!$B$5:$AE$23,28,0) -> #N/A | AE11: =RANK(AD11,$AD$4:$AD$59) -> #N/A | AF11: =VLOOKUP($A11,'汇总-1月'!$B$5:$AE$23,29,0) -> #N/A | AG11: =RANK(AF11,$AF$4:$AF$59) -> #N/A | AH11: =VLOOKUP($A11,'汇总-1月'!$B$5:$AE$23,30,0) -> #N/A | AI11: =RANK(AH11,$AH$4:$AH$59) -> #N/A
A12: 句容酒店 | B12: =VLOOKUP($A12,'汇总-1月'!$B$5:$AE$23,2,0) -> #N/A | C12: =RANK(B12,$B$4:$B$59) -> #N/A | D12: =VLOOKUP($A12,'汇总-1月'!$B$5:$AE$23,7,0) -> #N/A | E12: =RANK(D12,$D$4:$D$59) -> #N/A | F12: =VLOOKUP($A12,'汇总-1月'!$B$5:$AE$23,12,0) -> #N/A | G12: =RANK(F12,$F$4:$F$59) -> #N/A | H12: =VLOOKUP($A12,'汇总-1月'!$B$5:$AE$23,17,0) -> #N/A | I12: =RANK(H12,$H$4:$H$59) -> #N/A | J12: =VLOOKUP($A12,'汇总-1月'!$B$5:$AE$23,18,0) -> #N/A | K12: =RANK(J12,$J$4:$J$59) -> #N/A | L12: =VLOOKUP($A12,'汇总-1月'!$B$5:$AE$23,19,0) -> #N/A | M12: =RANK(L12,$L$4:$L$59) -> #N/A | N12: =VLOOKUP($A12,'汇总-1月'!$B$5:$AE$23,20,0) -> #N/A | O12: =RANK(N12,$N$4:$N$59) -> #N/A | P12: =VLOOKUP($A12,'汇总-1月'!$B$5:$AE$23,21,0) -> #N/A | Q12: =RANK(P12,$P$4:$P$59) -> #N/A | R12: =VLOOKUP($A12,'汇总-1月'!$B$5:$AE$23,22,0) -> #N/A | S12: =RANK(R12,$R$4:$R$59) -> #N/A | T12: =VLOOKUP($A12,'汇总-1月'!$B$5:$AE$23,23,0) -> #N/A | U12: =RANK(T12,$T$4:$T$59) -> #N/A | V12: =VLOOKUP($A12,'汇总-1月'!$B$5:$AE$23,24,0) -> #N/A | W12: =RANK(V12,$V$4:$V$59) -> #N/A | X12: =VLOOKUP($A12,'汇总-1月'!$B$5:$AE$23,25,0) -> #N/A | Y12: =RANK(X12,$X$4:$X$59) -> #N/A | Z12: =VLOOKUP($A12,'汇总-1月'!$B$5:$AE$23,26,0) -> #N/A | AA12: =RANK(Z12,$Z$4:$Z$59) -> #N/A | AB12: =VLOOKUP($A12,'汇总-1月'!$B$5:$AE$23,27,0) -> #N/A | AC12: =RANK(AB12,$AB$4:$AB$59) -> #N/A | AD12: =VLOOKUP($A12,'汇总-1月'!$B$5:$AE$23,28,0) -> #N/A | AE12: =RANK(AD12,$AD$4:$AD$59) -> #N/A | AF12: =VLOOKUP($A12,'汇总-1月'!$B$5:$AE$23,29,0) -> #N/A | AG12: =RANK(AF12,$AF$4:$AF$59) -> #N/A | AH12: =VLOOKUP($A12,'汇总-1月'!$B$5:$AE$23,30,0) -> #N/A | AI12: =RANK(AH12,$AH$4:$AH$59) -> #N/A
A13: 增城逸林酒店 | B13: =VLOOKUP($A13,'汇总-1月'!$B$5:$AE$23,2,0) -> #N/A | C13: =RANK(B13,$B$4:$B$59) -> #N/A | D13: =VLOOKUP($A13,'汇总-1月'!$B$5:$AE$23,7,0) -> #N/A | E13: =RANK(D13,$D$4:$D$59) -> #N/A | F13: =VLOOKUP($A13,'汇总-1月'!$B$5:$AE$23,12,0) -> #N/A | G13: =RANK(F13,$F$4:$F$59) -> #N/A | H13: =VLOOKUP($A13,'汇总-1月'!$B$5:$AE$23,17,0) -> #N/A | I13: =RANK(H13,$H$4:$H$59) -> #N/A | J13: =VLOOKUP($A13,'汇总-1月'!$B$5:$AE$23,18,0) -> #N/A | K13: =RANK(J13,$J$4:$J$59) -> #N/A | L13: =VLOOKUP($A13,'汇总-1月'!$B$5:$AE$23,19,0) -> #N/A | M13: =RANK(L13,$L$4:$L$59) -> #N/A | N13: =VLOOKUP($A13,'汇总-1月'!$B$5:$AE$23,20,0) -> #N/A | O13: =RANK(N13,$N$4:$N$59) -> #N/A | P13: =VLOOKUP($A13,'汇总-1月'!$B$5:$AE$23,21,0) -> #N/A | Q13: =RANK(P13,$P$4:$P$59) -> #N/A | R13: =VLOOKUP($A13,'汇总-1月'!$B$5:$AE$23,22,0) -> #N/A | S13: =RANK(R13,$R$4:$R$59) -> #N/A | T13: =VLOOKUP($A13,'汇总-1月'!$B$5:$AE$23,23,0) -> #N/A | U13: =RANK(T13,$T$4:$T$59) -> #N/A | V13: =VLOOKUP($A13,'汇总-1月'!$B$5:$AE$23,24,0) -> #N/A | W13: =RANK(V13,$V$4:$V$59) -> #N/A | X13: =VLOOKUP($A13,'汇总-1月'!$B$5:$AE$23,25,0) -> #N/A | Y13: =RANK(X13,$X$4:$X$59) -> #N/A | Z13: =VLOOKUP($A13,'汇总-1月'!$B$5:$AE$23,26,0) -> #N/A | AA13: =RANK(Z13,$Z$4:$Z$59) -> #N/A | AB13: =VLOOKUP($A13,'汇总-1月'!$B$5:$AE$23,27,0) -> #N/A | AC13: =RANK(AB13,$AB$4:$AB$59) -> #N/A | AD13: =VLOOKUP($A13,'汇总-1月'!$B$5:$AE$23,28,0) -> #N/A | AE13: =RANK(AD13,$AD$4:$AD$59) -> #N/A | AF13: =VLOOKUP($A13,'汇总-1月'!$B$5:$AE$23,29,0) -> #N/A | AG13: =RANK(AF13,$AF$4:$AF$59) -> #N/A | AH13: =VLOOKUP($A13,'汇总-1月'!$B$5:$AE$23,30,0) -> #N/A | AI13: =RANK(AH13,$AH$4:$AH$59) -> #N/A
A14: 云浮酒店 | B14: =VLOOKUP($A14,'汇总-1月'!$B$5:$AE$23,2,0) -> #N/A | C14: =RANK(B14,$B$4:$B$59) -> #N/A | D14: =VLOOKUP($A14,'汇总-1月'!$B$5:$AE$23,7,0) -> #N/A | E14: =RANK(D14,$D$4:$D$59) -> #N/A | F14: =VLOOKUP($A14,'汇总-1月'!$B$5:$AE$23,12,0) -> #N/A | G14: =RANK(F14,$F$4:$F$59) -> #N/A | H14: =VLOOKUP($A14,'汇总-1月'!$B$5:$AE$23,17,0) -> #N/A | I14: =RANK(H14,$H$4:$H$59) -> #N/A | J14: =VLOOKUP($A14,'汇总-1月'!$B$5:$AE$23,18,0) -> #N/A | K14: =RANK(J14,$J$4:$J$59) -> #N/A | L14: =VLOOKUP($A14,'汇总-1月'!$B$5:$AE$23,19,0) -> #N/A | M14: =RANK(L14,$L$4:$L$59) -> #N/A | N14: =VLOOKUP($A14,'汇总-1月'!$B$5:$AE$23,20,0) -> #N/A | O14: =RANK(N14,$N$4:$N$59) -> #N/A | P14: =VLOOKUP($A14,'汇总-1月'!$B$5:$AE$23,21,0) -> #N/A | Q14: =RANK(P14,$P$4:$P$59) -> #N/A | R14: =VLOOKUP($A14,'汇总-1月'!$B$5:$AE$23,22,0) -> #N/A | S14: =RANK(R14,$R$4:$R$59) -> #N/A | T14: =VLOOKUP($A14,'汇总-1月'!$B$5:$AE$23,23,0) -> #N/A | U14: =RANK(T14,$T$4:$T$59) -> #N/A | V14: =VLOOKUP($A14,'汇总-1月'!$B$5:$AE$23,24,0) -> #N/A | W14: =RANK(V14,$V$4:$V$59) -> #N/A | X14: =VLOOKUP($A14,'汇总-1月'!$B$5:$AE$23,25,0) -> #N/A | Y14: =RANK(X14,$X$4:$X$59) -> #N/A | Z14: =VLOOKUP($A14,'汇总-1月'!$B$5:$AE$23,26,0) -> #N/A | AA14: =RANK(Z14,$Z$4:$Z$59) -> #N/A | AB14: =VLOOKUP($A14,'汇总-1月'!$B$5:$AE$23,27,0) -> #N/A | AC14: =RANK(AB14,$AB$4:$AB$59) -> #N/A | AD14: =VLOOKUP($A14,'汇总-1月'!$B$5:$AE$23,28,0) -> #N/A | AE14: =RANK(AD14,$AD$4:$AD$59) -> #N/A | AF14: =VLOOKUP($A14,'汇总-1月'!$B$5:$AE$23,29,0) -> #N/A | AG14: =RANK(AF14,$AF$4:$AF$59) -> #N/A | AH14: =VLOOKUP($A14,'汇总-1月'!$B$5:$AE$23,30,0) -> #N/A | AI14: =RANK(AH14,$AH$4:$AH$59) -> #N/A
A15: 金叶子酒店 | B15: =VLOOKUP($A15,'汇总-1月'!$B$5:$AE$23,2,0) -> #N/A | C15: =RANK(B15,$B$4:$B$59) -> #N/A | D15: =VLOOKUP($A15,'汇总-1月'!$B$5:$AE$23,7,0) -> #N/A | E15: =RANK(D15,$D$4:$D$59) -> #N/A | F15: =VLOOKUP($A15,'汇总-1月'!$B$5:$AE$23,12,0) -> #N/A | G15: =RANK(F15,$F$4:$F$59) -> #N/A | H15: =VLOOKUP($A15,'汇总-1月'!$B$5:$AE$23,17,0) -> #N/A | I15: =RANK(H15,$H$4:$H$59) -> #N/A | J15: =VLOOKUP($A15,'汇总-1月'!$B$5:$AE$23,18,0) -> #N/A | K15: =RANK(J15,$J$4:$J$59) -> #N/A | L15: =VLOOKUP($A15,'汇总-1月'!$B$5:$AE$23,19,0) -> #N/A | M15: =RANK(L15,$L$4:$L$59) -> #N/A | N15: =VLOOKUP($A15,'汇总-1月'!$B$5:$AE$23,20,0) -> #N/A | O15: =RANK(N15,$N$4:$N$59) -> #N/A | P15: =VLOOKUP($A15,'汇总-1月'!$B$5:$AE$23,21,0) -> #N/A | Q15: =RANK(P15,$P$4:$P$59) -> #N/A | R15: =VLOOKUP($A15,'汇总-1月'!$B$5:$AE$23,22,0) -> #N/A | S15: =RANK(R15,$R$4:$R$59) -> #N/A | T15: =VLOOKUP($A15,'汇总-1月'!$B$5:$AE$23,23,0) -> #N/A | U15: =RANK(T15,$T$4:$T$59) -> #N/A | V15: =VLOOKUP($A15,'汇总-1月'!$B$5:$AE$23,24,0) -> #N/A | W15: =RANK(V15,$V$4:$V$59) -> #N/A | X15: =VLOOKUP($A15,'汇总-1月'!$B$5:$AE$23,25,0) -> #N/A | Y15: =RANK(X15,$X$4:$X$59) -> #N/A | Z15: =VLOOKUP($A15,'汇总-1月'!$B$5:$AE$23,26,0) -> #N/A | AA15: =RANK(Z15,$Z$4:$Z$59) -> #N/A | AB15: =VLOOKUP($A15,'汇总-1月'!$B$5:$AE$23,27,0) -> #N/A | AC15: =RANK(AB15,$AB$4:$AB$59) -> #N/A | AD15: =VLOOKUP($A15,'汇总-1月'!$B$5:$AE$23,28,0) -> #N/A | AE15: =RANK(AD15,$AD$4:$AD$59) -> #N/A | AF15: =VLOOKUP($A15,'汇总-1月'!$B$5:$AE$23,29,0) -> #N/A | AG15: =RANK(AF15,$AF$4:$AF$59) -> #N/A | AH15: =VLOOKUP($A15,'汇总-1月'!$B$5:$AE$23,30,0) -> #N/A | AI15: =RANK(AH15,$AH$4:$AH$59) -> #N/A
... A39: 佛山希尔顿 | B39: =VLOOKUP($A39,'汇总-1月'!$B$5:$AE$23,2,0) -> #N/A | C39: =RANK(B39,$B$4:$B$59) -> #N/A | D39: =VLOOKUP($A39,'汇总-1月'!$B$5:$AE$23,7,0) -> #N/A | E39: =RANK(D39,$D$4:$D$59) -> #N/A | F39: =VLOOKUP($A39,'汇总-1月'!$B$5:$AE$23,12,0) -> #N/A | G39: =RANK(F39,$F$4:$F$59) -> #N/A | H39: =VLOOKUP($A39,'汇总-1月'!$B$5:$AE$23,17,0) -> #N/A | I39: =RANK(H39,$H$4:$H$59) -> #N/A | J39: =VLOOKUP($A39,'汇总-1月'!$B$5:$AE$23,18,0) -> #N/A | K39: =RANK(J39,$J$4:$J$59) -> #N/A | L39: =VLOOKUP($A39,'汇总-1月'!$B$5:$AE$23,19,0) -> #N/A | M39: =RANK(L39,$L$4:$L$59) -> #N/A | N39: =VLOOKUP($A39,'汇总-1月'!$B$5:$AE$23,20,0) -> #N/A | O39: =RANK(N39,$N$4:$N$59) -> #N/A | P39: =VLOOKUP($A39,'汇总-1月'!$B$5:$AE$23,21,0) -> #N/A | Q39: =RANK(P39,$P$4:$P$59) -> #N/A | R39: =VLOOKUP($A39,'汇总-1月'!$B$5:$AE$23,22,0) -> #N/A | S39: =RANK(R39,$R$4:$R$59) -> #N/A | T39: =VLOOKUP($A39,'汇总-1月'!$B$5:$AE$23,23,0) -> #N/A | U39: =RANK(T39,$T$4:$T$59) -> #N/A | V39: =VLOOKUP($A39,'汇总-1月'!$B$5:$AE$23,24,0) -> #N/A | W39: =RANK(V39,$V$4:$V$59) -> #N/A | X39: =VLOOKUP($A39,'汇总-1月'!$B$5:$AE$23,25,0) -> #N/A | Y39: =RANK(X39,$X$4:$X$59) -> #N/A | Z39: =VLOOKUP($A39,'汇总-1月'!$B$5:$AE$23,26,0) -> #N/A | AA39: =RANK(Z39,$Z$4:$Z$59) -> #N/A | AB39: =VLOOKUP($A39,'汇总-1月'!$B$5:$AE$23,27,0) -> #N/A | AC39: =RANK(AB39,$AB$4:$AB$59) -> #N/A | AD39: =VLOOKUP($A39,'汇总-1月'!$B$5:$AE$23,28,0) -> #N/A | AE39: =RANK(AD39,$AD$4:$AD$59) -> #N/A | AF39: =VLOOKUP($A39,'汇总-1月'!$B$5:$AE$23,29,0) -> #N/A | AG39: =RANK(AF39,$AF$4:$AF$59) -> #N/A | AH39: =VLOOKUP($A39,'汇总-1月'!$B$5:$AE$23,30,0) -> #N/A | AI39: =RANK(AH39,$AH$4:$AH$59) -> #N/A

Sheet 累计排名取数
B1: 整体 | C1: 整体 | D1: 整体 | E1: 整体 | F1: 整体 | G1: 整体 | H1: 整体 | I1: 整体 | J1: 整体 | K1: 整体 | L1: 客房 | M1: 客房 | N1: 客房 | O1: 客房 | P1: 客房 | Q1: 客房 | R1: 客房 | S1: 客房 | T1: 客房 | U1: 客房 | V1: 餐饮 | W1: 餐饮 | X1: 餐饮 | Y1: 餐饮 | Z1: 餐饮 | AA1: 餐饮 | AB1: 未分配 | AC1: 未分配 | AD1: 未分配 | AE1: 未分配 | AF1: 未分配 | AG1: 未分配 | AH1: 未分配 | AI1: 未分配
B2: 总收入 | C2: 总收入 | D2: 经营毛利 | E2: 经营毛利 | F2: 业主利润返还（上报） | G2: 业主利润返还（上报） | H2: 元均创收（元） | I2: 元均创收（元） | J2: GOP率 | K2: GOP率 | L2: OCC | M2: OCC | N2: ADR（元） | O2: ADR（元） | P2: RevPAR（元） | Q2: RevPAR（元） | R2: 元均创收（元） | S2: 元均创收（元） | T2: 客房利润率 | U2: 客房利润率 | V2: 毛利率 | W2: 毛利率 | X2: 元均创收（元） | Y2: 元均创收（元） | Z2: 餐饮利润率 | AA2: 餐饮利润率 | AB2: 能耗占比 | AC2: 能耗占比 | AD2: 元均创收（元） | AE2: 元均创收（元） | AF2: 营销费用率 | AG2: 营销费用率 | AH2: 未分配费用占比 | AI2: 未分配费用占比
A3: 酒店 | B3: 累计完成 | C3: 排名 | D3: 累计完成 | E3: 排名 | F3: 累计完成 | G3: 排名 | H3: 累计完成 | I3: 排名 | J3: 累计完成 | K3: 排名 | L3: 累计完成 | M3: 排名 | N3: 累计完成 | O3: 排名 | P3: 累计完成 | Q3: 排名 | R3: 累计完成 | S3: 排名 | T3: 累计完成 | U3: 排名 | V3: 累计完成 | W3: 排名 | X3: 累计完成 | Y3: 排名 | Z3: 累计完成 | AA3: 排名 | AB3: 累计完成 | AC3: 排名 | AD3: 累计完成 | AE3: 排名 | AF3: 累计完成 | AG3: 排名 | AH3: 累计完成 | AI3: 排名
A4: 于洪酒店 | B4: =VLOOKUP($A4,'汇总-累计'!$B$5:$AH$23,2,0) -> 283.18159 | C4: =RANK(B4,$B$4:$B$59) -> #N/A | D4: =VLOOKUP($A4,'汇总-累计'!$B$5:$AH$23,8,0) -> -34.304774 | E4: =RANK(D4,$D$4:$D$59) -> #N/A | F4: =VLOOKUP($A4,'汇总-累计'!$B$5:$AH$23,14,0) -> -58.735147 | G4: =RANK(F4,$F$4:$F$59) -> #N/A | H4: =VLOOKUP($A4,'汇总-累计'!$B$5:$AH$23,20,0) -> 2.5475392 | I4: =RANK(H4,$H$4:$H$59) -> #N/A | J4: =VLOOKUP($A4,'汇总-累计'!$B$5:$AH$23,21,0) -> -0.12114055 | K4: =RANK(J4,$J$4:$J$59) -> #N/A | L4: =VLOOKUP($A4,'汇总-累计'!$B$5:$AH$23,22,0) -> 0.31282051 | M4: =RANK(L4,$L$4:$L$59) -> #N/A | N4: =VLOOKUP($A4,'汇总-累计'!$B$5:$AH$23,23,0) -> 199.24168 | O4: =RANK(N4,$N$4:$N$59) -> #N/A | P4: =VLOOKUP($A4,'汇总-累计'!$B$5:$AH$23,24,0) -> 62.326886 | Q4: =RANK(P4,$P$4:$P$59) -> #N/A | R4: =VLOOKUP($A4,'汇总-累计'!$B$5:$AH$23,25,0) -> 3.9706353 | S4: =RANK(R4,$R$4:$R$59) -> #N/A | T4: =VLOOKUP($A4,'汇总-累计'!$B$5:$AH$23,26,0) -> 0.56916345 | U4: =RANK(T4,$T$4:$T$59) -> #N/A | V4: =VLOOKUP($A4,'汇总-累计'!$B$5:$AH$23,27,0) -> 0.53898494 | W4: =RANK(V4,$V$4:$V$59) -> #N/A | X4: =VLOOKUP($A4,'汇总-累计'!$B$5:$AH$23,28,0) -> 5.0071107 | Y4: =RANK(X4,$X$4:$X$59) -> #N/A | Z4: =VLOOKUP($A4,'汇总-累计'!$B$5:$AH$23,29,0) -> 0.311165 | AA4: =RANK(Z4,$Z$4:$Z$59) -> #N/A | AB4: =VLOOKUP($A4,'汇总-累计'!$B$5:$AH$23,30,0) -> 0.33181395 | AC4: =RANK(AB4,$AB$4:$AB$59) -> #N/A | AD4: =VLOOKUP($A4,'汇总-累计'!$B$5:$AH$23,31,0) -> 5.5028084 | AE4: =RANK(AD4,$AD$4:$AD$59) -> #N/A | AF4: =VLOOKUP($A4,'汇总-累计'!$B$5:$AH$23,32,0) -> 0.02304718 | AG4: =RANK(AF4,$AF$4:$AF$59) -> #N/A | AH4: =VLOOKUP($A4,'汇总-累计'!$B$5:$AH$23,33,0) -> 0.55986208 | AI4: =RANK(AH4,$AH$4:$AH$59) -> #N/A
A5: 滁州酒店 | B5: =VLOOKUP($A5,'汇总-累计'!$B$5:$AH$23,2,0) -> 12.903087 | C5: =RANK(B5,$B$4:$B$59) -> #N/A | D5: =VLOOKUP($A5,'汇总-累计'!$B$5:$AH$23,8,0) -> -36.195544 | E5: =RANK(D5,$D$4:$D$59) -> #N/A | F5: =VLOOKUP($A5,'汇总-累计'!$B$5:$AH$23,14,0) -> -40.646245 | G5: =RANK(F5,$F$4:$F$59) -> #N/A | H5: =VLOOKUP($A5,'汇总-累计'!$B$5:$AH$23,20,0) -> 0.51806265 | I5: =RANK(H5,$H$4:$H$59) -> #N/A | J5: =VLOOKUP($A5,'汇总-累计'!$B$5:$AH$23,21,0) -> -2.8051848 | K5: =RANK(J5,$J$4:$J$59) -> #N/A | L5: =VLOOKUP($A5,'汇总-累计'!$B$5:$AH$23,22,0) -> 0.032112758 | M5: =RANK(L5,$L$4:$L$59) -> #N/A | N5: =VLOOKUP($A5,'汇总-累计'!$B$5:$AH$23,23,0) -> 165.84338 | O5: =RANK(N5,$N$4:$N$59) -> #N/A | P5: =VLOOKUP($A5,'汇总-累计'!$B$5:$AH$23,24,0) -> 5.3256883 | Q5: =RANK(P5,$P$4:$P$59) -> #N/A | R5: =VLOOKUP($A5,'汇总-累计'!$B$5:$AH$23,25,0) -> 0.81298809 | S5: =RANK(R5,$R$4:$R$59) -> #N/A | T5: =VLOOKUP($A5,'汇总-累计'!$B$5:$AH$23,26,0) -> -0.59771863 | U5: =RANK(T5,$T$4:$T$59) -> #N/A | V5: =VLOOKUP($A5,'汇总-累计'!$B$5:$AH$23,27,0) -> 0.47804757 | W5: =RANK(V5,$V$4:$V$59) -> #N/A | X5: =VLOOKUP($A5,'汇总-累计'!$B$5:$AH$23,28,0) -> 0.98638897 | Y5: =RANK(X5,$X$4:$X$59) -> #N/A | Z5: =VLOOKUP($A5,'汇总-累计'!$B$5:$AH$23,29,0) -> -0.5975288 | AA5: =RANK(Z5,$Z$4:$Z$59) -> #N/A | AB5: =VLOOKUP($A5,'汇总-累计'!$B$5:$AH$23,30,0) -> 1.0659493 | AC5: =RANK(AB5,$AB$4:$AB$59) -> #N/A | AD5: =VLOOKUP($A5,'汇总-累计'!$B$5:$AH$23,31,0) -> 1.1984064 | AE5: =RANK(AD5,$AD$4:$AD$59) -> #N/A | AF5: =VLOOKUP($A5,'汇总-累计'!$B$5:$AH$23,32,0) -> 0.0016072898 | AG5: =RANK(AF5,$AF$4:$AF$59) -> #N/A | AH5: =VLOOKUP($A5,'汇总-累计'!$B$5:$AH$23,33,0) -> 2.2241329 | AI5: =RANK(AH5,$AH$4:$AH$59) -> #N/A
A6: 武汉酒店 | B6: =VLOOKUP($A6,'汇总-累计'!$B$5:$AH$23,2,0) -> 113.65688 | C6: =RANK(B6,$B$4:$B$59) -> #N/A | D6: =VLOOKUP($A6,'汇总-累计'!$B$5:$AH$23,8,0) -> 5.802227 | E6: =RANK(D6,$D$4:$D$59) -> #N/A | F6: =VLOOKUP($A6,'汇总-累计'!$B$5:$AH$23,14,0) -> -2.958152 | G6: =RANK(F6,$F$4:$F$59) -> #N/A | H6: =VLOOKUP($A6,'汇总-累计'!$B$5:$AH$23,20,0) -> 2.1067655 | I6: =RANK(H6,$H$4:$H$59) -> #N/A | J6: =VLOOKUP($A6,'汇总-累计'!$B$5:$AH$23,21,0) -> 0.051050379 | K6: =RANK(J6,$J$4:$J$59) -> #N/A | L6: =VLOOKUP($A6,'汇总-累计'!$B$5:$AH$23,22,0) -> 0.22488062 | M6: =RANK(L6,$L$4:$L$59) -> #N/A | N6: =VLOOKUP($A6,'汇总-累计'!$B$5:$AH$23,23,0) -> 221.8789 | O6: =RANK(N6,$N$4:$N$59) -> #N/A | P6: =VLOOKUP($A6,'汇总-累计'!$B$5:$AH$23,24,0) -> 49.896264 | Q6: =RANK(P6,$P$4:$P$59) -> #N/A | R6: =VLOOKUP($A6,'汇总-累计'!$B$5:$AH$23,25,0) -> 4.7829935 | S6: =RANK(R6,$R$4:$R$59) -> #N/A | T6: =VLOOKUP($A6,'汇总-累计'!$B$5:$AH$23,26,0) -> 0.60995125 | U6: =RANK(T6,$T$4:$T$59) -> #N/A | V6: =VLOOKUP($A6,'汇总-累计'!$B$5:$AH$23,27,0) -> 0.59600743 | W6: =RANK(V6,$V$4:$V$59) -> #N/A | X6: =VLOOKUP($A6,'汇总-累计'!$B$5:$AH$23,28,0) -> 3.2034786 | Y6: =RANK(X6,$X$4:$X$59) -> #N/A | Z6: =VLOOKUP($A6,'汇总-累计'!$B$5:$AH$23,29,0) -> 0.26094614 | AA6: =RANK(Z6,$Z$4:$Z$59) -> #N/A | AB6: =VLOOKUP($A6,'汇总-累计'!$B$5:$AH$23,30,0) -> 0.117017 | AC6: =RANK(AB6,$AB$4:$AB$59) -> #N/A | AD6: =VLOOKUP($A6,'汇总-累计'!$B$5:$AH$23,31,0) -> 4.5567032 | AE6: =RANK(AD6,$AD$4:$AD$59) -> #N/A | AF6: =VLOOKUP($A6,'汇总-累计'!$B$5:$AH$23,32,0) -> 0.040234237 | AG6: =RANK(AF6,$AF$4:$AF$59) -> #N/A | AH6: =VLOOKUP($A6,'汇总-累计'!$B$5:$AH$23,33,0) -> 0.39204858 | AI6: =RANK(AH6,$AH$4:$AH$59) -> #N/A
A7: 海南临高 | B7: =VLOOKUP($A7,'汇总-累计'!$B$5:$AH$23,2,0) -> #N/A | C7: =RANK(B7,$B$4:$B$59) -> #N/A | D7: =VLOOKUP($A7,'汇总-累计'!$B$5:$AH$23,8,0) -> #N/A | E7: =RANK(D7,$D$4:$D$59) -> #N/A | F7: =VLOOKUP($A7,'汇总-累计'!$B$5:$AH$23,14,0) -> #N/A | G7: =RANK(F7,$F$4:$F$59) -> #N/A | H7: =VLOOKUP($A7,'汇总-累计'!$B$5:$AH$23,20,0) -> #N/A | I7: =RANK(H7,$H$4:$H$59) -> #N/A | J7: =VLOOKUP($A7,'汇总-累计'!$B$5:$AH$23,21,0) -> #N/A | K7: =RANK(J7,$J$4:$J$59) -> #N/A | L7: =VLOOKUP($A7,'汇总-累计'!$B$5:$AH$23,22,0) -> #N/A | M7: =RANK(L7,$L$4:$L$59) -> #N/A | N7: =VLOOKUP($A7,'汇总-累计'!$B$5:$AH$23,23,0) -> #N/A | O7: =RANK(N7,$N$4:$N$59) -> #N/A | P7: =VLOOKUP($A7,'汇总-累计'!$B$5:$AH$23,24,0) -> #N/A | Q7: =RANK(P7,$P$4:$P$59) -> #N/A | R7: =VLOOKUP($A7,'汇总-累计'!$B$5:$AH$23,25,0) -> #N/A | S7: =RANK(R7,$R$4:$R$59) -> #N/A | T7: =VLOOKUP($A7,'汇总-累计'!$B$5:$AH$23,26,0) -> #N/A | U7: =RANK(T7,$T$4:$T$59) -> #N/A | V7: =VLOOKUP($A7,'汇总-累计'!$B$5:$AH$23,27,0) -> #N/A | W7: =RANK(V7,$V$4:$V$59) -> #N/A | X7: =VLOOKUP($A7,'汇总-累计'!$B$5:$AH$23,28,0) -> #N/A | Y7: =RANK(X7,$X$4:$X$59) -> #N/A | Z7: =VLOOKUP($A7,'汇总-累计'!$B$5:$AH$23,29,0) -> #N/A | AA7: =RANK(Z7,$Z$4:$Z$59) -> #N/A | AB7: =VLOOKUP($A7,'汇总-累计'!$B$5:$AH$23,30,0) -> #N/A | AC7: =RANK(AB7,$AB$4:$AB$59) -> #N/A | AD7: =VLOOKUP($A7,'汇总-累计'!$B$5:$AH$23,31,0) -> #N/A | AE7: =RANK(AD7,$AD$4:$AD$59) -> #N/A | AF7: =VLOOKUP($A7,'汇总-累计'!$B$5:$AH$23,32,0) -> #N/A | AG7: =RANK(AF7,$AF$4:$AF$59) -> #N/A | AH7: =VLOOKUP($A7,'汇总-累计'!$B$5:$AH$23,33,0) -> #N/A | AI7: =RANK(AH7,$AH$4:$AH$59) -> #N/A
A8: 三水酒店 | B8: =VLOOKUP($A8,'汇总-累计'!$B$5:$AH$23,2,0) -> #N/A | C8: =RANK(B8,$B$4:$B$59) -> #N/A | D8: =VLOOKUP($A8,'汇总-累计'!$B$5:$AH$23,8,0) -> #N/A | E8: =RANK(D8,$D$4:$D$59) -> #N/A | F8: =VLOOKUP($A8,'汇总-累计'!$B$5:$AH$23,14,0) -> #N/A | G8: =RANK(F8,$F$4:$F$59) -> #N/A | H8: =VLOOKUP($A8,'汇总-累计'!$B$5:$AH$23,20,0) -> #N/A | I8: =RANK(H8,$H$4:$H$59) -> #N/A | J8: =VLOOKUP($A8,'汇总-累计'!$B$5:$AH$23,21,0) -> #N/A | K8: =RANK(J8,$J$4:$J$59) -> #N/A | L8: =VLOOKUP($A8,'汇总-累计'!$B$5:$AH$23,22,0) -> #N/A | M8: =RANK(L8,$L$4:$L$59) -> #N/A | N8: =VLOOKUP($A8,'汇总-累计'!$B$5:$AH$23,23,0) -> #N/A | O8: =RANK(N8,$N$4:$N$59) -> #N/A | P8: =VLOOKUP($A8,'汇总-累计'!$B$5:$AH$23,24,0) -> #N/A | Q8: =RANK(P8,$P$4:$P$59) -> #N/A | R8: =VLOOKUP($A8,'汇总-累计'!$B$5:$AH$23,25,0) -> #N/A | S8: =RANK(R8,$R$4:$R$59) -> #N/A | T8: =VLOOKUP($A8,'汇总-累计'!$B$5:$AH$23,26,0) -> #N/A | U8: =RANK(T8,$T$4:$T$59) -> #N/A | V8: =VLOOKUP($A8,'汇总-累计'!$B$5:$AH$23,27,0) -> #N/A | W8: =RANK(V8,$V$4:$V$59) -> #N/A | X8: =VLOOKUP($A8,'汇总-累计'!$B$5:$AH$23,28,0) -> #N/A | Y8: =RANK(X8,$X$4:$X$59) -> #N/A | Z8: =VLOOKUP($A8,'汇总-累计'!$B$5:$AH$23,29,0) -> #N/A | AA8: =RANK(Z8,$Z$4:$Z$59) -> #N/A | AB8: =VLOOKUP($A8,'汇总-累计'!$B$5:$AH$23,30,0) -> #N/A | AC8: =RANK(AB8,$AB$4:$AB$59) -> #N/A | AD8: =VLOOKUP($A8,'汇总-累计'!$B$5:$AH$23,31,0) -> #N/A | AE8: =RANK(AD8,$AD$4:$AD$59) -> #N/A | AF8: =VLOOKUP($A8,'汇总-累计'!$B$5:$AH$23,32,0) -> #N/A | AG8: =RANK(AF8,$AF$4:$AF$59) -> #N/A | AH8: =VLOOKUP($A8,'汇总-累计'!$B$5:$AH$23,33,0) -> #N/A | AI8: =RANK(AH8,$AH$4:$AH$59) -> #N/A
A9: 泰州酒店 | B9: =VLOOKUP($A9,'汇总-累计'!$B$5:$AH$23,2,0) -> #N/A | C9: =RANK(B9,$B$4:$B$59) -> #N/A | D9: =VLOOKUP($A9,'汇总-累计'!$B$5:$AH$23,8,0) -> #N/A | E9: =RANK(D9,$D$4:$D$59) -> #N/A | F9: =VLOOKUP($A9,'汇总-累计'!$B$5:$AH$23,14,0) -> #N/A | G9: =RANK(F9,$F$4:$F$59) -> #N/A | H9: =VLOOKUP($A9,'汇总-累计'!$B$5:$AH$23,20,0) -> #N/A | I9: =RANK(H9,$H$4:$H$59) -> #N/A | J9: =VLOOKUP($A9,'汇总-累计'!$B$5:$AH$23,21,0) -> #N/A | K9: =RANK(J9,$J$4:$J$59) -> #N/A | L9: =VLOOKUP($A9,'汇总-累计'!$B$5:$AH$23,22,0) -> #N/A | M9: =RANK(L9,$L$4:$L$59) -> #N/A | N9: =VLOOKUP($A9,'汇总-累计'!$B$5:$AH$23,23,0) -> #N/A | O9: =RANK(N9,$N$4:$N$59) -> #N/A | P9: =VLOOKUP($A9,'汇总-累计'!$B$5:$AH$23,24,0) -> #N/A | Q9: =RANK(P9,$P$4:$P$59) -> #N/A | R9: =VLOOKUP($A9,'汇总-累计'!$B$5:$AH$23,25,0) -> #N/A | S9: =RANK(R9,$R$4:$R$59) -> #N/A | T9: =VLOOKUP($A9,'汇总-累计'!$B$5:$AH$23,26,0) -> #N/A | U9: =RANK(T9,$T$4:$T$59) -> #N/A | V9: =VLOOKUP($A9,'汇总-累计'!$B$5:$AH$23,27,0) -> #N/A | W9: =RANK(V9,$V$4:$V$59) -> #N/A | X9: =VLOOKUP($A9,'汇总-累计'!$B$5:$AH$23,28,0) -> #N/A | Y9: =RANK(X9,$X$4:$X$59) -> #N/A | Z9: =VLOOKUP($A9,'汇总-累计'!$B$5:$AH$23,29,0) -> #N/A | AA9: =RANK(Z9,$Z$4:$Z$59) -> #N/A | AB9: =VLOOKUP($A9,'汇总-累计'!$B$5:$AH$23,30,0) -> #N/A | AC9: =RANK(AB9,$AB$4:$AB$59) -> #N/A | AD9: =VLOOKUP($A9,'汇总-累计'!$B$5:$AH$23,31,0) -> #N/A | AE9: =RANK(AD9,$AD$4:$AD$59) -> #N/A | AF9: =VLOOKUP($A9,'汇总-累计'!$B$5:$AH$23,32,0) -> #N/A | AG9: =RANK(AF9,$AF$4:$AF$59) -> #N/A | AH9: =VLOOKUP($A9,'汇总-累计'!$B$5:$AH$23,33,0) -> #N/A | AI9: =RANK(AH9,$AH$4:$AH$59) -> #N/A
A10: 安庆酒店 | B10: =VLOOKUP($A10,'汇总-累计'!$B$5:$AH$23,2,0) -> #N/A | C10: =RANK(B10,$B$4:$B$59) -> #N/A | D10: =VLOOKUP($A10,'汇总-累计'!$B$5:$AH$23,8,0) -> #N/A | E10: =RANK(D10,$D$4:$D$59) -> #N/A | F10: =VLOOKUP($A10,'汇总-累计'!$B$5:$AH$23,14,0) -> #N/A | G10: =RANK(F10,$F$4:$F$59) -> #N/A | H10: =VLOOKUP($A10,'汇总-累计'!$B$5:$AH$23,20,0) -> #N/A | I10: =RANK(H10,$H$4:$H$59) -> #N/A | J10: =VLOOKUP($A10,'汇总-累计'!$B$5:$AH$23,21,0) -> #N/A | K10: =RANK(J10,$J$4:$J$59) -> #N/A | L10: =VLOOKUP($A10,'汇总-累计'!$B$5:$AH$23,22,0) -> #N/A | M10: =RANK(L10,$L$4:$L$59) -> #N/A | N10: =VLOOKUP($A10,'汇总-累计'!$B$5:$AH$23,23,0) -> #N/A | O10: =RANK(N10,$N$4:$N$59) -> #N/A | P10: =VLOOKUP($A10,'汇总-累计'!$B$5:$AH$23,24,0) -> #N/A | Q10: =RANK(P10,$P$4:$P$59) -> #N/A | R10: =VLOOKUP($A10,'汇总-累计'!$B$5:$AH$23,25,0) -> #N/A | S10: =RANK(R10,$R$4:$R$59) -> #N/A | T10: =VLOOKUP($A10,'汇总-累计'!$B$5:$AH$23,26,0) -> #N/A | U10: =RANK(T10,$T$4:$T$59) -> #N/A | V10: =VLOOKUP($A10,'汇总-累计'!$B$5:$AH$23,27,0) -> #N/A | W10: =RANK(V10,$V$4:$V$59) -> #N/A | X10: =VLOOKUP($A10,'汇总-累计'!$B$5:$AH$23,28,0) -> #N/A | Y10: =RANK(X10,$X$4:$X$59) -> #N/A | Z10: =VLOOKUP($A10,'汇总-累计'!$B$5:$AH$23,29,0) -> #N/A | AA10: =RANK(Z10,$Z$4:$Z$59) -> #N/A | AB10: =VLOOKUP($A10,'汇总-累计'!$B$5:$AH$23,30,0) -> #N/A | AC10: =RANK(AB10,$AB$4:$AB$59) -> #N/A | AD10: =VLOOKUP($A10,'汇总-累计'!$B$5:$AH$23,31,0) -> #N/A | AE10: =RANK(AD10,$AD$4:$AD$59) -> #N/A | AF10: =VLOOKUP($A10,'汇总-累计'!$B$5:$AH$23,32,0) -> #N/A | AG10: =RANK(AF10,$AF$4:$AF$59) -> #N/A | AH10: =VLOOKUP($A10,'汇总-累计'!$B$5:$AH$23,33,0) -> #N/A | AI10: =RANK(AH10,$AH$4:$AH$59) -> #N/A
A11: 张家界酒店 | B11: =VLOOKUP($A11,'汇总-累计'!$B$5:$AH$23,2,0) -> #N/A | C11: =RANK(B11,$B$4:$B$59) -> #N/A | D11: =VLOOKUP($A11,'汇总-累计'!$B$5:$AH$23,8,0) -> #N/A | E11: =RANK(D11,$D$4:$D$59) -> #N/A | F11: =VLOOKUP($A11,'汇总-累计'!$B$5:$AH$23,14,0) -> #N/A | G11: =RANK(F11,$F$4:$F$59) -> #N/A | H11: =VLOOKUP($A11,'汇总-累计'!$B$5:$AH$23,20,0) -> #N/A | I11: =RANK(H11,$H$4:$H$59) -> #N/A | J11: =VLOOKUP($A11,'汇总-累计'!$B$5:$AH$23,21,0) -> #N/A | K11: =RANK(J11,$J$4:$J$59) -> #N/A | L11: =VLOOKUP($A11,'汇总-累计'!$B$5:$AH$23,22,0) -> #N/A | M11: =RANK(L11,$L$4:$L$59) -> #N/A | N11: =VLOOKUP($A11,'汇总-累计'!$B$5:$AH$23,23,0) -> #N/A | O11: =RANK(N11,$N$4:$N$59) -> #N/A | P11: =VLOOKUP($A11,'汇总-累计'!$B$5:$AH$23,24,0) -> #N/A | Q11: =RANK(P11,$P$4:$P$59) -> #N/A | R11: =VLOOKUP($A11,'汇总-累计'!$B$5:$AH$23,25,0) -> #N/A | S11: =RANK(R11,$R$4:$R$59) -> #N/A | T11: =VLOOKUP($A11,'汇总-累计'!$B$5:$AH$23,26,0) -> #N/A | U11: =RANK(T11,$T$4:$T$59) -> #N/A | V11: =VLOOKUP($A11,'汇总-累计'!$B$5:$AH$23,27,0) -> #N/A | W11: =RANK(V11,$V$4:$V$59) -> #N/A | X11: =VLOOKUP($A11,'汇总-累计'!$B$5:$AH$23,28,0) -> #N/A | Y11: =RANK(X11,$X$4:$X$59) -> #N/A | Z11: =VLOOKUP($A11,'汇总-累计'!$B$5:$AH$23,29,0) -> #N/A | AA11: =RANK(Z11,$Z$4:$Z$59) -> #N/A | AB11: =VLOOKUP($A11,'汇总-累计'!$B$5:$AH$23,30,0) -> #N/A | AC11: =RANK(AB11,$AB$4:$AB$59) -> #N/A | AD11: =VLOOKUP($A11,'汇总-累计'!$B$5:$AH$23,31,0) -> #N/A | AE11: =RANK(AD11,$AD$4:$AD$59) -> #N/A | AF11: =VLOOKUP($A11,'汇总-累计'!$B$5:$AH$23,32,0) -> #N/A | AG11: =RANK(AF11,$AF$4:$AF$59) -> #N/A | AH11: =VLOOKUP($A11,'汇总-累计'!$B$5:$AH$23,33,0) -> #N/A | AI11: =RANK(AH11,$AH$4:$AH$59) -> #N/A
A12: 句容酒店 | B12: =VLOOKUP($A12,'汇总-累计'!$B$5:$AH$23,2,0) -> #N/A | C12: =RANK(B12,$B$4:$B$59) -> #N/A | D12: =VLOOKUP($A12,'汇总-累计'!$B$5:$AH$23,8,0) -> #N/A | E12: =RANK(D12,$D$4:$D$59) -> #N/A | F12: =VLOOKUP($A12,'汇总-累计'!$B$5:$AH$23,14,0) -> #N/A | G12: =RANK(F12,$F$4:$F$59) -> #N/A | H12: =VLOOKUP($A12,'汇总-累计'!$B$5:$AH$23,20,0) -> #N/A | I12: =RANK(H12,$H$4:$H$59) -> #N/A | J12: =VLOOKUP($A12,'汇总-累计'!$B$5:$AH$23,21,0) -> #N/A | K12: =RANK(J12,$J$4:$J$59) -> #N/A | L12: =VLOOKUP($A12,'汇总-累计'!$B$5:$AH$23,22,0) -> #N/A | M12: =RANK(L12,$L$4:$L$59) -> #N/A | N12: =VLOOKUP($A12,'汇总-累计'!$B$5:$AH$23,23,0) -> #N/A | O12: =RANK(N12,$N$4:$N$59) -> #N/A | P12: =VLOOKUP($A12,'汇总-累计'!$B$5:$AH$23,24,0) -> #N/A | Q12: =RANK(P12,$P$4:$P$59) -> #N/A | R12: =VLOOKUP($A12,'汇总-累计'!$B$5:$AH$23,25,0) -> #N/A | S12: =RANK(R12,$R$4:$R$59) -> #N/A | T12: =VLOOKUP($A12,'汇总-累计'!$B$5:$AH$23,26,0) -> #N/A | U12: =RANK(T12,$T$4:$T$59) -> #N/A | V12: =VLOOKUP($A12,'汇总-累计'!$B$5:$AH$23,27,0) -> #N/A | W12: =RANK(V12,$V$4:$V$59) -> #N/A | X12: =VLOOKUP($A12,'汇总-累计'!$B$5:$AH$23,28,0) -> #N/A | Y12: =RANK(X12,$X$4:$X$59) -> #N/A | Z12: =VLOOKUP($A12,'汇总-累计'!$B$5:$AH$23,29,0) -> #N/A | AA12: =RANK(Z12,$Z$4:$Z$59) -> #N/A | AB12: =VLOOKUP($A12,'汇总-累计'!$B$5:$AH$23,30,0) -> #N/A | AC12: =RANK(AB12,$AB$4:$AB$59) -> #N/A | AD12: =VLOOKUP($A12,'汇总-累计'!$B$5:$AH$23,31,0) -> #N/A | AE12: =RANK(AD12,$AD$4:$AD$59) -> #N/A | AF12: =VLOOKUP($A12,'汇总-累计'!$B$5:$AH$23,32,0) -> #N/A | AG12: =RANK(AF12,$AF$4:$AF$59) -> #N/A | AH12: =VLOOKUP($A12,'汇总-累计'!$B$5:$AH$23,33,0) -> #N/A | AI12: =RANK(AH12,$AH$4:$AH$59) -> #N/A
A13: 增城逸林酒店 | B13: =VLOOKUP($A13,'汇总-累计'!$B$5:$AH$23,2,0) -> #N/A | C13: =RANK(B13,$B$4:$B$59) -> #N/A | D13: =VLOOKUP($A13,'汇总-累计'!$B$5:$AH$23,8,0) -> #N/A | E13: =RANK(D13,$D$4:$D$59) -> #N/A | F13: =VLOOKUP($A13,'汇总-累计'!$B$5:$AH$23,14,0) -> #N/A | G13: =RANK(F13,$F$4:$F$59) -> #N/A | H13: =VLOOKUP($A13,'汇总-累计'!$B$5:$AH$23,20,0) -> #N/A | I13: =RANK(H13,$H$4:$H$59) -> #N/A | J13: =VLOOKUP($A13,'汇总-累计'!$B$5:$AH$23,21,0) -> #N/A | K13: =RANK(J13,$J$4:$J$59) -> #N/A | L13: =VLOOKUP($A13,'汇总-累计'!$B$5:$AH$23,22,0) -> #N/A | M13: =RANK(L13,$L$4:$L$59) -> #N/A | N13: =VLOOKUP($A13,'汇总-累计'!$B$5:$AH$23,23,0) -> #N/A | O13: =RANK(N13,$N$4:$N$59) -> #N/A | P13: =VLOOKUP($A13,'汇总-累计'!$B$5:$AH$23,24,0) -> #N/A | Q13: =RANK(P13,$P$4:$P$59) -> #N/A | R13: =VLOOKUP($A13,'汇总-累计'!$B$5:$AH$23,25,0) -> #N/A | S13: =RANK(R13,$R$4:$R$59) -> #N/A | T13: =VLOOKUP($A13,'汇总-累计'!$B$5:$AH$23,26,0) -> #N/A | U13: =RANK(T13,$T$4:$T$59) -> #N/A | V13: =VLOOKUP($A13,'汇总-累计'!$B$5:$AH$23,27,0) -> #N/A | W13: =RANK(V13,$V$4:$V$59) -> #N/A | X13: =VLOOKUP($A13,'汇总-累计'!$B$5:$AH$23,28,0) -> #N/A | Y13: =RANK(X13,$X$4:$X$59) -> #N/A | Z13: =VLOOKUP($A13,'汇总-累计'!$B$5:$AH$23,29,0) -> #N/A | AA13: =RANK(Z13,$Z$4:$Z$59) -> #N/A | AB13: =VLOOKUP($A13,'汇总-累计'!$B$5:$AH$23,30,0) -> #N/A | AC13: =RANK(AB13,$AB$4:$AB$59) -> #N/A | AD13: =VLOOKUP($A13,'汇总-累计'!$B$5:$AH$23,31,0) -> #N/A | AE13: =RANK(AD13,$AD$4:$AD$59) -> #N/A | AF13: =VLOOKUP($A13,'汇总-累计'!$B$5:$AH$23,32,0) -> #N/A | AG13: =RANK(AF13,$AF$4:$AF$59) -> #N/A | AH13: =VLOOKUP($A13,'汇总-累计'!$B$5:$AH$23,33,0) -> #N/A | AI13: =RANK(AH13,$AH$4:$AH$59) -> #N/A
A14: 云浮酒店 | B14: =VLOOKUP($A14,'汇总-累计'!$B$5:$AH$23,2,0) -> #N/A | C14: =RANK(B14,$B$4:$B$59) -> #N/A | D14: =VLOOKUP($A14,'汇总-累计'!$B$5:$AH$23,8,0) -> #N/A | E14: =RANK(D14,$D$4:$D$59) -> #N/A | F14: =VLOOKUP($A14,'汇总-累计'!$B$5:$AH$23,14,0) -> #N/A | G14: =RANK(F14,$F$4:$F$59) -> #N/A | H14: =VLOOKUP($A14,'汇总-累计'!$B$5:$AH$23,20,0) -> #N/A | I14: =RANK(H14,$H$4:$H$59) -> #N/A | J14: =VLOOKUP($A14,'汇总-累计'!$B$5:$AH$23,21,0) -> #N/A | K14: =RANK(J14,$J$4:$J$59) -> #N/A | L14: =VLOOKUP($A14,'汇总-累计'!$B$5:$AH$23,22,0) -> #N/A | M14: =RANK(L14,$L$4:$L$59) -> #N/A | N14: =VLOOKUP($A14,'汇总-累计'!$B$5:$AH$23,23,0) -> #N/A | O14: =RANK(N14,$N$4:$N$59) -> #N/A | P14: =VLOOKUP($A14,'汇总-累计'!$B$5:$AH$23,24,0) -> #N/A | Q14: =RANK(P14,$P$4:$P$59) -> #N/A | R14: =VLOOKUP($A14,'汇总-累计'!$B$5:$AH$23,25,0) -> #N/A | S14: =RANK(R14,$R$4:$R$59) -> #N/A | T14: =VLOOKUP($A14,'汇总-累计'!$B$5:$AH$23,26,0) -> #N/A | U14: =RANK(T14,$T$4:$T$59) -> #N/A | V14: =VLOOKUP($A14,'汇总-累计'!$B$5:$AH$23,27,0) -> #N/A | W14: =RANK(V14,$V$4:$V$59) -> #N/A | X14: =VLOOKUP($A14,'汇总-累计'!$B$5:$AH$23,28,0) -> #N/A | Y14: =RANK(X14,$X$4:$X$59) -> #N/A | Z14: =VLOOKUP($A14,'汇总-累计'!$B$5:$AH$23,29,0) -> #N/A | AA14: =RANK(Z14,$Z$4:$Z$59) -> #N/A | AB14: =VLOOKUP($A14,'汇总-累计'!$B$5:$AH$23,30,0) -> #N/A | AC14: =RANK(AB14,$AB$4:$AB$59) -> #N/A | AD14: =VLOOKUP($A14,'汇总-累计'!$B$5:$AH$23,31,0) -> #N/A | AE14: =RANK(AD14,$AD$4:$AD$59) -> #N/A | AF14: =VLOOKUP($A14,'汇总-累计'!$B$5:$AH$23,32,0) -> #N/A | AG14: =RANK(AF14,$AF$4:$AF$59) -> #N/A | AH14: =VLOOKUP($A14,'汇总-累计'!$B$5:$AH$23,33,0) -> #N/A | AI14: =RANK(AH14,$AH$4:$AH$59) -> #N/A
A15: 金叶子酒店 | B15: =VLOOKUP($A15,'汇总-累计'!$B$5:$AH$23,2,0) -> #N/A | C15: =RANK(B15,$B$4:$B$59) -> #N/A | D15: =VLOOKUP($A15,'汇总-累计'!$B$5:$AH$23,8,0) -> #N/A | E15: =RANK(D15,$D$4:$D$59) -> #N/A | F15: =VLOOKUP($A15,'汇总-累计'!$B$5:$AH$23,14,0) -> #N/A | G15: =RANK(F15,$F$4:$F$59) -> #N/A | H15: =VLOOKUP($A15,'汇总-累计'!$B$5:$AH$23,20,0) -> #N/A | I15: =RANK(H15,$H$4:$H$59) -> #N/A | J15: =VLOOKUP($A15,'汇总-累计'!$B$5:$AH$23,21,0) -> #N/A | K15: =RANK(J15,$J$4:$J$59) -> #N/A | L15: =VLOOKUP($A15,'汇总-累计'!$B$5:$AH$23,22,0) -> #N/A | M15: =RANK(L15,$L$4:$L$59) -> #N/A | N15: =VLOOKUP($A15,'汇总-累计'!$B$5:$AH$23,23,0) -> #N/A | O15: =RANK(N15,$N$4:$N$59) -> #N/A | P15: =VLOOKUP($A15,'汇总-累计'!$B$5:$AH$23,24,0) -> #N/A | Q15: =RANK(P15,$P$4:$P$59) -> #N/A | R15: =VLOOKUP($A15,'汇总-累计'!$B$5:$AH$23,25,0) -> #N/A | S15: =RANK(R15,$R$4:$R$59) -> #N/A | T15: =VLOOKUP($A15,'汇总-累计'!$B$5:$AH$23,26,0) -> #N/A | U15: =RANK(T15,$T$4:$T$59) -> #N/A | V15: =VLOOKUP($A15,'汇总-累计'!$B$5:$AH$23,27,0) -> #N/A | W15: =RANK(V15,$V$4:$V$59) -> #N/A | X15: =VLOOKUP($A15,'汇总-累计'!$B$5:$AH$23,28,0) -> #N/A | Y15: =RANK(X15,$X$4:$X$59) -> #N/A | Z15: =VLOOKUP($A15,'汇总-累计'!$B$5:$AH$23,29,0) -> #N/A | AA15: =RANK(Z15,$Z$4:$Z$59) -> #N/A | AB15: =VLOOKUP($A15,'汇总-累计'!$B$5:$AH$23,30,0) -> #N/A | AC15: =RANK(AB15,$AB$4:$AB$59) -> #N/A | AD15: =VLOOKUP($A15,'汇总-累计'!$B$5:$AH$23,31,0) -> #N/A | AE15: =RANK(AD15,$AD$4:$AD$59) -> #N/A | AF15: =VLOOKUP($A15,'汇总-累计'!$B$5:$AH$23,32,0) -> #N/A | AG15: =RANK(AF15,$AF$4:$AF$59) -> #N/A | AH15: =VLOOKUP($A15,'汇总-累计'!$B$5:$AH$23,33,0) -> #N/A | AI15: =RANK(AH15,$AH$4:$AH$59) -> #N/A
... A39: 佛山希尔顿 | B39: =VLOOKUP($A39,'汇总-累计'!$B$5:$AH$23,2,0) -> #N/A | C39: =RANK(B39,$B$4:$B$59) -> #N/A | D39: =VLOOKUP($A39,'汇总-累计'!$B$5:$AH$23,8,0) -> #N/A | E39: =RANK(D39,$D$4:$D$59) -> #N/A | F39: =VLOOKUP($A39,'汇总-累计'!$B$5:$AH$23,14,0) -> #N/A | G39: =RANK(F39,$F$4:$F$59) -> #N/A | H39: =VLOOKUP($A39,'汇总-累计'!$B$5:$AH$23,20,0) -> #N/A | I39: =RANK(H39,$H$4:$H$59) -> #N/A | J39: =VLOOKUP($A39,'汇总-累计'!$B$5:$AH$23,21,0) -> #N/A | K39: =RANK(J39,$J$4:$J$59) -> #N/A | L39: =VLOOKUP($A39,'汇总-累计'!$B$5:$AH$23,22,0) -> #N/A | M39: =RANK(L39,$L$4:$L$59) -> #N/A | N39: =VLOOKUP($A39,'汇总-累计'!$B$5:$AH$23,23,0) -> #N/A | O39: =RANK(N39,$N$4:$N$59) -> #N/A | P39: =VLOOKUP($A39,'汇总-累计'!$B$5:$AH$23,24,0) -> #N/A | Q39: =RANK(P39,$P$4:$P$59) -> #N/A | R39: =VLOOKUP($A39,'汇总-累计'!$B$5:$AH$23,25,0) -> #N/A | S39: =RANK(R39,$R$4:$R$59) -> #N/A | T39: =VLOOKUP($A39,'汇总-累计'!$B$5:$AH$23,26,0) -> #N/A | U39: =RANK(T39,$T$4:$T$59) -> #N/A | V39: =VLOOKUP($A39,'汇总-累计'!$B$5:$AH$23,27,0) -> #N/A | W39: =RANK(V39,$V$4:$V$59) -> #N/A | X39: =VLOOKUP($A39,'汇总-累计'!$B$5:$AH$23,28,0) -> #N/A | Y39: =RANK(X39,$X$4:$X$59) -> #N/A | Z39: =VLOOKUP($A39,'汇总-累计'!$B$5:$AH$23,29,0) -> #N/A | AA39: =RANK(Z39,$Z$4:$Z$59) -> #N/A | AB39: =VLOOKUP($A39,'汇总-累计'!$B$5:$AH$23,30,0) -> #N/A | AC39: =RANK(AB39,$AB$4:$AB$59) -> #N/A | AD39: =VLOOKUP($A39,'汇总-累计'!$B$5:$AH$23,31,0) -> #N/A | AE39: =RANK(AD39,$AD$4:$AD$59) -> #N/A | AF39: =VLOOKUP($A39,'汇总-累计'!$B$5:$AH$23,32,0) -> #N/A | AG39: =RANK(AF39,$AF$4:$AF$59) -> #N/A | AH39: =VLOOKUP($A39,'汇总-累计'!$B$5:$AH$23,33,0) -> #N/A | AI39: =RANK(AH39,$AH$4:$AH$59) -> #N/A

Sheet 新事业部
AS1: 取净利润 | AT1: 取净利润
C2: 已上报 | D2: 已上报 | E2: 已上报 | F2: 已上报 | G2: 已上报 | H2: 已上报 | I2: 已上报 | J2: 已上报 | K2: 已上报 | L2: 已上报 | M2: 已上报 | N2: 已上报 | O2: 已上报 | P2: 已上报 | Q2: 已上报 | R2: 已上报 | S2: 已上报 | T2: 已上报 | U2: 已上报 | V2: 已上报 | W2: 已上报 | X2: 已上报 | Y2: 已上报 | Z2: 已上报 | AA2: 已上报 | AB2: 已上报 | AC2: 已上报 | AD2: 已上报 | AE2: 已上报 | AF2: 已上报 | AG2: 已上报 | AH2: 已上报 | AI2: 已上报 | AJ2: 已上报 | AK2: 已上报 | AL2: 已上报 | AM2: 已上报 | AN2: 已上报 | AO2: 取数 | AP2: 取数 | AQ2: 取数 | AR2: 广州凤凰 | AS2: 广州凤凰 | AT2: 广州凤凰 | AU2: 实际应上报 | AV2: 实际应上报 | AW2: 实际应上报 | AX2: 倒挤上报 | AY2: 倒挤上报 | AZ2: 倒挤上报
C3: 完成 | D3: 完成 | E3: 完成 | F3: 完成 | G3: 完成 | H3: 完成 | I3: 完成 | J3: 完成 | K3: 完成 | L3: 完成 | M3: 完成 | N3: 完成 | O3: 完成 | P3: 预算 | Q3: 预算 | R3: 预算 | S3: 预算 | T3: 预算 | U3: 预算 | V3: 预算 | W3: 预算 | X3: 预算 | Y3: 预算 | Z3: 预算 | AA3: 预算 | AB3: 去年 | AC3: 去年 | AD3: 去年 | AE3: 去年 | AF3: 去年 | AG3: 去年 | AH3: 去年 | AI3: 去年 | AJ3: 去年 | AK3: 去年 | AL3: 去年 | AM3: 去年 | AN3: 去年 | AO3: 去年 | AP3: 完成 | AQ3: 预算 | AR3: 去年 | AS3: 完成 | AT3: 预算 | AU3: 去年 | AV3: 完成 | AW3: 预算 | AX3: 去年 | AY3: 完成 | AZ3: 预算
C4: 累计 | D4: 1月 | E4: 2月 | F4: 3月 | G4: 4月 | H4: 5月 | I4: 6月 | J4: 7月 | K4: 8月 | L4: 9月 | M4: 10月 | N4: 11月 | O4: 12月 | P4: 1月 | Q4: 2月 | R4: 3月 | S4: 4月 | T4: 5月 | U4: 6月 | V4: 7月 | W4: 8月 | X4: 9月 | Y4: 10月 | Z4: 11月 | AA4: 12月 | AB4: 累计 | AC4: 1月 | AD4: 2月 | AE4: 3月 | AF4: 4月 | AG4: 5月 | AH4: 6月 | AI4: 7月 | AJ4: 8月 | AK4: 9月 | AL4: 10月 | AM4: 11月 | AN4: 12月 | AO4: 累计 | AP4: 累计 | AQ4: 累计 | AR4: 累计 | AS4: 累计 | AT4: 累计 | AU4: 累计 | AV4: 累计 | AW4: 累计 | AX4: 当月 | AY4: 当月 | AZ4: 当月
A5: 收入 | B5: 客房 | C5: =SUM(D5:O5) -> 48341.135 | D5: 3982.4379 | E5: 3214.8343 | F5: 3807.8547 | G5: 4418.577 | H5: 5256.773 | I5: 3116.3946 | J5: 4142.2344 | K5: 4188.1091 | L5: 3191.7785 | M5: 5323.1583 | N5: 4101.4004 | O5: 3597.583 | P5: 3863.6337 | Q5: 3521.4325 | R5: 4397.1392 | S5: 4819.5 | T5: 5079.1502 | U5: 4459.1148 | V5: 5179.6246 | W5: 5490.6081 | X5: 4267.3779 | Y5: 5594.7402 | Z5: 4757.9424 | AA5: 4700.5151 | AB5: =SUM(AC5:AN5) -> 54989.552 | AC5: 4572.3615 | AD5: 4120.0111 | AE5: 4351.2391 | AF5: 4840.594 | AG5: 5105.4388 | AH5: 3781.122 | AI5: 5033.4227 | AJ5: 5437.2654 | AK5: 3727.9746 | AL5: 5533.0602 | AM5: 4582.4317 | AN5: 3904.6313 | AO5: =汇总!P43/10000 -> 172.65391 | AP5: =汇总!M43/10000 -> 170.6402 | AQ5: =汇总!N43/10000 -> 187.33186 | AU5: =AO5+AR5 -> 172.65391 | AV5: =AP5+AS5 -> 170.6402 | AW5: =AQ5+AT5 -> 187.33186 | AX5: =AU5-AB5 -> -54816.898 | AY5: =AV5-C5 -> -48170.495
B6: 餐饮 | C6: =SUM(D6:O6) -> 43765.125 | D6: 4448.8134 | E6: 3259.1619 | F6: 3280.6592 | G6: 3111.6159 | H6: 4302.315 | I6: 2597.0236 | J6: 3279.6006 | K6: 3416.9368 | L6: 3155.5754 | M6: 5110.866 | N6: 4223.1068 | O6: 3579.4506 | P6: 4283.2716 | Q6: 3200.1051 | R6: 3759.3423 | S6: 3824.7666 | T6: 4464.8976 | U6: 3881.7396 | V6: 4212.9718 | W6: 4648.0062 | X6: 4343.2001 | Y6: 5024.7513 | Z6: 4518.2228 | AA6: 4631.5947 | AB6: =SUM(AC6:AN6) -> 48650.075 | AC6: 5915.1068 | AD6: 3669.527 | AE6: 3577.2901 | AF6: 3231.9726 | AG6: 4135.8818 | AH6: 3354.641 | AI6: 3964.7455 | AJ6: 4543.5179 | AK6: 3632.7158 | AL6: 4451.4438 | AM6: 4361.1626 | AN6: 3812.0704 | AO6: =(汇总!P56-汇总!P54)/10000 -> 304.20401 | AP6: =(汇总!M56-汇总!M54)/10000 -> 219.00033 | AQ6: =(汇总!N56-汇总!N54)/10000 -> 248.73443 | AU6: =AO6+AR6 -> 304.20401 | AV6: =AP6+AS6 -> 219.00033 | AW6: =AQ6+AT6 -> 248.73443 | AX6: =AU6-AB6 -> -48345.871 | AY6: =AV6-C6 -> -43546.125
B7: 康乐 | C7: =SUM(D7:O7) -> 249.53699 | D7: 16.633518 | E7: 14.620244 | F7: 17.202153 | G7: 26.808263 | H7: 17.056941 | I7: 21.516216 | J7: 40.987043 | K7: 37.107022 | L7: 14.528195 | M7: 17.28717 | N7: 14.502566 | O7: 11.287662 | P7: 13.399668 | Q7: 12.006563 | R7: 17.763456 | S7: 27.044648 | T7: 29.102071 | U7: 62.72106 | V7: 69.060858 | W7: 70.987435 | X7: 37.995734 | Y7: 22.182681 | Z7: 18.898296 | AA7: 17.920297 | AB7: =SUM(AC7:AN7) -> 354.94351 | AC7: 25.54026 | AD7: 21.46261 | AE7: 19.731318 | AF7: 21.983121 | AG7: 21.328409 | AH7: 44.9794 | AI7: 70.678331 | AJ7: 47.422684 | AK7: 20.9936 | AL7: 19.582115 | AM7: 22.675757 | AN7: 18.565904 | AO7: =汇总!P69/10000 -> 0 | AP7: =汇总!M69/10000 -> 0 | AQ7: =汇总!N69/10000 -> 0 | AU7: =AO7+AR7 -> 0 | AV7: =AP7+AS7 -> 0 | AW7: =AQ7+AT7 -> 0 | AX7: =AU7-AB7 -> -354.94351 | AY7: =AV7-C7 -> -249.53699
B8: 新零售及食品 | C8: =SUM(D8:O8) -> 2214.0165 | D8: 167.46911 | E8: 39.637074 | F8: 24.358106 | G8: 100.48193 | H8: 330.07524 | I8: 36.514341 | J8: 178.4426 | K8: 159.59726 | L8: 998.06605 | M8: 88.16112 | N8: 48.102749 | O8: 43.110923 | P8: 125.52762 | Q8: 36.869531 | R8: 28.408904 | S8: 51.686723 | T8: 200.14814 | U8: 59.084032 | V8: 38.178373 | W8: 166.26618 | X8: 844.70841 | Y8: 157.55321 | Z8: 49.922713 | AA8: 64.8146 | AB8: =SUM(AC8:AN8) -> 2491.4538 | AC8: 265.68786 | AD8: 110.47566 | AE8: 52.594074 | AF8: 50.708612 | AG8: 225.28706 | AH8: 116.65372 | AI8: 29.560772 | AJ8: 626.87602 | AK8: 842.56705 | AL8: 41.805291 | AM8: 34.688779 | AN8: 94.548858 | AO8: =汇总!P54/10000 -> 5.615138 | AP8: =汇总!M54/10000 -> 2.152184 | AQ8: =汇总!N54/10000 -> 2.654868 | AU8: =AO8+AR8 -> 5.615138 | AV8: =AP8+AS8 -> 2.152184 | AW8: =AQ8+AT8 -> 2.654868 | AX8: =AU8-AB8 -> -2485.8386 | AY8: =AV8-C8 -> -2211.8643
B9: 租金 | C9: =SUM(D9:O9) -> 8044.1075 | D9: 697.95909 | E9: 833.49095 | F9: 703.17925 | G9: 628.82332 | H9: 638.88235 | I9: 680.62711 | J9: 640.73024 | K9: 668.82064 | L9: 714.60445 | M9: 630.87034 | N9: 597.57024 | O9: 608.54951 | P9: 576.37929 | Q9: 764.96964 | R9: 629.83878 | S9: 569.57451 | T9: 575.23682 | U9: 661.73098 | V9: 592.22573 | W9: 593.97727 | X9: 642.65074 | Y9: 583.782 | Z9: 579.12181 | AA9: 663.696 | AB9: =SUM(AC9:AN9) -> 8111.9681 | AC9: 536.7083 | AD9: 927.63492 | AE9: 785.19096 | AF9: 583.00932 | AG9: 595.77877 | AH9: 675.5203 | AI9: 697.18606 | AJ9: 669.3686 | AK9: 700.54816 | AL9: 636.69438 | AM9: 616.32554 | AN9: 688.00284 | AO9: =汇总!P75/10000 -> 7.341275 | AP9: =汇总!M75/10000 -> 10.77802 | AQ9: =汇总!N75/10000 -> 7.261028 | AU9: =AO9+AR9 -> 7.341275 | AV9: =AP9+AS9 -> 10.77802 | AW9: =AQ9+AT9 -> 7.261028 | AX9: =AU9-AB9 -> -8104.6269 | AY9: =AV9-C9 -> -8033.3295
B10: 温泉 | C10: =SUM(D10:O10) -> 2565.6058 | D10: 728.96959 | E10: 420.01403 | F10: 140.24679 | G10: 112.50734 | H10: 99.056676 | I10: 39.809915 | J10: 63.337258 | K10: 87.31098 | L10: 42.070466 | M10: 169.19507 | N10: 244.90129 | O10: 418.18637 | P10: 636.58386 | Q10: 454.61313 | R10: 154.53304 | S10: 77.497165 | T10: 101.29987 | U10: 59.70972 | V10: 86.538501 | W10: 110.98701 | X10: 72.330688 | Y10: 181.01124 | Z10: 211.58571 | AA10: 450.40614 | AB10: =SUM(AC10:AN10) -> 2884.9156 | AC10: 474.83958 | AD10: 500.26839 | AE10: 241.00298 | AF10: 334.13648 | AG10: 98.564928 | AH10: 55.495887 | AI10: 82.826788 | AJ10: 110.10077 | AK10: 57.739644 | AL10: 173.97297 | AM10: 225.72762 | AN10: 530.23956 | AO10: =汇总!P70/10000 -> 0 | AP10: =汇总!M70/10000 -> 0 | AQ10: =汇总!N70/10000 -> 0 | AU10: =AO10+AR10 -> 0 | AV10: =AP10+AS10 -> 0 | AW10: =AQ10+AT10 -> 0 | AX10: =AU10-AB10 -> -2884.9156 | AY10: =AV10-C10 -> -2565.6058
B11: 其他收入 | C11: =SUM(D11:O11) -> 2587.8453 | D11: 240.9636 | E11: 183.79262 | F11: 198.75973 | G11: 204.78521 | H11: 223.15869 | I11: 208.34316 | J11: 233.07253 | K11: 206.73982 | L11: 182.02425 | M11: 251.04869 | N11: 220.13869 | O11: 235.01831 | P11: 83.849773 | Q11: 75.477006 | R11: 76.849954 | S11: 82.883095 | T11: 97.036404 | U11: 98.655586 | V11: 110.1993 | W11: 121.84214 | X11: 74.943306 | Y11: 86.163178 | Z11: 74.992083 | AA11: 84.927583 | AB11: =SUM(AC11:AN11) -> 2459.4394 | AC11: 223.7596 | AD11: 136.06995 | AE11: 139.69567 | AF11: 150.29278 | AG11: 197.86181 | AH11: 195.10241 | AI11: 250.48058 | AJ11: 216.63988 | AK11: 208.0077 | AL11: 282.79696 | AM11: 176.90835 | AN11: 281.8237 | AO11: =(汇总!P71+汇总!P72+汇总!P73+汇总!P74+汇总!P76)/10000 -> 10.380798 | AP11: =(汇总!M71+汇总!M72+汇总!M73+汇总!M74+汇总!M76)/10000 -> 7.170827 | AQ11: =(汇总!N71+汇总!N72+汇总!N73+汇总!N74+汇总!N76)/10000 -> 2.358396 | AU11: =AO11+AR11 -> 10.380798 | AV11: =AP11+AS11 -> 7.170827 | AW11: =AQ11+AT11 -> 2.358396 | AX11: =AU11-AB11 -> -2449.0586 | AY11: =AV11-C11 -> -2580.6745
A12: 利润 | B12: 净利润 | C12: =SUM(D12:O12) -> -22736.079 | D12: -1647.5633 | E12: -2740.0673 | F12: -2635.6477 | G12: -1723.6823 | H12: -647.32453 | I12: -2937.5154 | J12: -2661.3087 | K12: -2941.1728 | L12: -2754.6561 | M12: -354.34082 | N12: -1483.5231 | O12: -209.27686 | P12: -2155.7956 | Q12: -2675.2336 | R12: -1880.9637 | S12: -1682.6934 | T12: -1261.8575 | U12: -1914.2637 | V12: -1540.1101 | W12: -1184.0113 | X12: -2030.3556 | Y12: -796.19371 | Z12: -1444.8587 | AA12: -1384.4435 | AB12: =SUM(AC12:AN12) -> -23635.529 | AC12: -1332.0372 | AD12: -2447.1677 | AE12: -2213.5125 | AF12: -2127.2514 | AG12: -1837.7173 | AH12: -3017.1113 | AI12: -2521.1178 | AJ12: -1795.3665 | AK12: -3033.3805 | AL12: -488.70224 | AM12: -1240.177 | AN12: -1581.9878 | AO12: =汇总!P132/10000 -> -276.75864 | AP12: =汇总!M132/10000 -> -233.11076 | AQ12: =汇总!N132/10000 -> -214.9807 | AR12: =-AR17 -> #REF! | AS12: =-AS17 -> #REF! | AT12: =-AT17 -> #REF! | AU12: =AO12+AR12 -> #REF! | AV12: =AP12+AS12 -> #REF! | AW12: =AQ12+AT12 -> #REF! | AX12: =AU12-AB12 -> #REF! | AY12: =AV12-C12 -> #REF!
A13: 经营性现金流净额 | B13: 经营性现金流净额 | C13: =SUM(D13:O13) -> 0 | D13: -1038.0057 | E13: 3237.0229 | F13: 591.19846 | G13: 920.30742 | H13: 2616.7695 | I13: 513.14564 | J13: 1615.9678 | L13: -8456.4061 | M13: 0 | N13: 0 | O13: -7.2759576e-12 | P13: -1677.5914 | Q13: 2714.0154 | R13: 1146.0103 | S13: 732.81709 | T13: 1867.6861 | U13: 1620.833 | V13: 1484.4344 | W13: 2221.7974 | X13: 1893.6621 | Y13: 1657.6953 | Z13: 2358.7726 | AA13: 1238.8679 | AB13: =SUM(AC13:AN13) -> 0 | AH13: 0 | AJ13: 0 | AK13: 0 | AL13: 0 | AM13: 0 | AN13: 0 | AU13: =AO13+AR13 -> 0 | AV13: =AP13+AS13 -> 0 | AW13: =AQ13+AT13 -> 0 | AX13: =AU13-AB13 -> 0 | AY13: =AV13-C13 -> 0
A14: 折旧摊销 | C14: =SUM(D14:O14) -> 32891.401 | D14: 2748.0377 | E14: 2747.5546 | F14: 2749.4827 | G14: 2747.4841 | H14: 2298.7631 | I14: 2602.8073 | J14: 2629.5 | K14: 3416.8472 | L14: 2730.3372 | M14: 2732.8158 | N14: 2726.8365 | O14: 2760.9348 | P14: 2881.9021 | Q14: 2883.0617 | R14: 2884.1736 | S14: 2885.8989 | T14: 2886.7602 | U14: 2886.0176 | V14: 2886.084 | W14: 2886.2976 | X14: 2887.1521 | Y14: 2887.5341 | Z14: 2888.0364 | AA14: 2887.9039 | AB14: =SUM(AC14:AN14) -> 33502.958 | AC14: 2669.151 | AD14: 2803.6685 | AE14: 2931.4476 | AF14: 2866.5737 | AG14: 2809.1223 | AH14: 2900.3935 | AI14: 2906.8746 | AJ14: 2889.7596 | AK14: 2889.0658 | AL14: 2349.402 | AM14: 2759.4744 | AN14: 2728.0252 | AO14: =汇总!P128/10000 -> 59.499327 | AP14: =汇总!M128/10000 -> 58.990435 | AQ14: =汇总!N128/10000 -> 58.562947 | AU14: =AO14+AR14 -> 59.499327 | AV14: =AP14+AS14 -> 58.990435 | AW14: =AQ14+AT14 -> 58.562947 | AX14: =AU14-AB14 -> -33443.459 | AY14: =AV14-C14 -> -32832.411
A15: 成本 | B15: 材料成本 | C15: =SUM(D15:O15) -> 18852.376 | D15: 2015.7655 | E15: 1207.6812 | F15: 1245.6224 | G15: 1256.3928 | H15: 1926.3135 | I15: 1000.0955 | J15: 1437.9381 | K15: 1545.0524 | L15: 2048.8366 | M15: 2138.6454 | N15: 1604.0822 | O15: 1425.9506 | P15: 1785.6944 | Q15: 1327.5163 | R15: 1465.2489 | S15: 1521.346 | T15: 1907.3773 | U15: 1535.3096 | V15: 1646.383 | W15: 2012.603 | X15: 2459.8747 | Y15: 2096.9054 | Z15: 1753.7919 | AA15: 1819.677 | AB15: =SUM(AC15:AN15) -> 21132.781 | AC15: 2431.337 | AD15: 1710.1411 | AE15: 1290.9376 | AF15: 1350.2641 | AG15: 1770.5907 | AH15: 1374.9944 | AI15: 1572.9789 | AJ15: 2375.7891 | AK15: 2232.5945 | AL15: 1889.8729 | AM15: 1609.1626 | AN15: 1524.1183 | AO15: =汇总!P17/10000 -> 149.39084 | AP15: =汇总!M17/10000 -> 107.10259 | AQ15: =汇总!N17/10000 -> 113.17931 | AU15: =AO15+AR15 -> 149.39084 | AV15: =AP15+AS15 -> 107.10259 | AW15: =AQ15+AT15 -> 113.17931 | AX15: =AU15-AB15 -> -20983.39 | AY15: =AV15-C15 -> -18745.274
B16: 分包成本 | C16: =SUM(D16:O16) -> 0 | E16: 0 | F16: 0 | G16: 0 | H16: 0 | I16: 0 | J16: 0 | K16: 0 | L16: 0 | M16: 0 | N16: 0 | O16: 0 | AB16: =SUM(AC16:AN16) -> 0 | AH16: 0 | AJ16: 0 | AK16: 0 | AL16: 0 | AM16: 0 | AN16: 0 | AU16: =AO16+AR16 -> 0 | AV16: =AP16+AS16 -> 0 | AW16: =AQ16+AT16 -> 0 | AX16: =AU16-AB16 -> 0 | AY16: =AV16-C16 -> 0
B17: 人工成本-固定部分 | C17: =SUM(D17:O17) -> 24088.969 | D17: 2203.5165 | E17: 1914.455 | F17: 2016.3429 | G17: 1953.2796 | H17: 2203.4084 | I17: 1793.1299 | J17: 2039.1063 | K17: 1914.7947 | L17: 2006.3399 | M17: 2244.8807 | N17: 1971.2775 | O17: 1828.4374 | P17: 2034.4872 | Q17: 1905.9524 | R17: 1905.3845 | S17: 1980.7135 | T17: 2045.867 | U17: 1963.7884 | V17: 2059.4626 | W17: 2096.973 | X17: 2004.1712 | Y17: 2189.0382 | Z17: 2021.3518 | AA17: 2014.4366 | AB17: =SUM(AC17:AN17) -> 27142.13 | AC17: 2442.1639 | AD17: 2349.8484 | AE17: 2183.8367 | AF17: 2215.3161 | AG17: 2288.8954 | AH17: 2146.3389 | AI17: 2633.476 | AJ17: 2328.2863 | AK17: 2122.933 | AL17: 2293.098 | AM17: 2066.2368 | AN17: 2071.7008 | AO17: =(汇总!P44+汇总!P45+汇总!P61+汇总!P62+汇总!P79+汇总!P80)/10000 -> 129.20812 | AP17: =(汇总!M44+汇总!M45+汇总!M61+汇总!M62+汇总!M79+汇总!M80)/10000 -> 102.84288 | AQ17: =(汇总!N44+汇总!N45+汇总!N61+汇总!N62+汇总!N79+汇总!N80)/10000 -> 120.64576 | AR17: =-#REF!/10000 -> #REF! | AS17: =-#REF!/10000 -> #REF! | AT17: =-#REF!/10000 -> #REF! | AU17: =AO17+AR17 -> #REF! | AV17: =AP17+AS17 -> #REF! | AW17: =AQ17+AT17 -> #REF! | AX17: =AU17-AB17 -> #REF! | AY17: =AV17-C17 -> #REF!
B18: 人工成本-变动部分（随收入变动或绩效奖金） | C18: =SUM(D18:O18) -> 0 | G18: 0 | H18: 0 | I18: 0 | J18: 0 | K18: 0 | L18: 0 | M18: 0 | N18: 0 | O18: 0 | AB18: =SUM(AC18:AN18) -> 0 | AH18: 0 | AJ18: 0 | AK18: 0 | AL18: 0 | AM18: 0 | AN18: 0 | AU18: =AO18+AR18 -> 0 | AV18: =AP18+AS18 -> 0 | AW18: =AQ18+AT18 -> 0 | AX18: =AU18-AB18 -> 0 | AY18: =AV18-C18 -> 0
B19: 制造费用 | C19: =SUM(D19:O19) -> 0 | E19: 0 | F19: 0 | G19: 0 | H19: 0 | I19: 0 | J19: 0 | K19: 0 | L19: 0 | M19: 0 | N19: 0 | O19: 0 | AB19: =SUM(AC19:AN19) -> 0 | AH19: 0 | AJ19: 0 | AK19: 0 | AL19: 0 | AM19: 0 | AN19: 0 | AU19: =AO19+AR19 -> 0 | AV19: =AP19+AS19 -> 0 | AW19: =AQ19+AT19 -> 0 | AX19: =AU19-AB19 -> 0 | AY19: =AV19-C19 -> 0
B20: …… | C20: =SUM(D20:O20) -> 0 | E20: 0 | F20: 0 | G20: 0 | H20: 0 | I20: 0 | J20: 0 | K20: 0 | L20: 0 | M20: 0 | N20: 0 | O20: 0 | AB20: =SUM(AC20:AN20) -> 0 | AH20: 0 | AJ20: 0 | AK20: 0 | AL20: 0 | AM20: 0 | AN20: 0 | AU20: =AO20+AR20 -> 0 | AV20: =AP20+AS20 -> 0 | AW20: =AQ20+AT20 -> 0 | AX20: =AU20-AB20 -> 0 | AY20: =AV20-C20 -> 0
A21: 费用 | B21: 人工成本-固定部分 | C21: =SUM(D21:O21) -> 14968.935 | D21: 1289.9799 | E21: 1261.4259 | F21: 1342.0753 | G21: 1243.0877 | H21: 1343.6968 | I21: 1180.5056 | J21: 1223.7953 | K21: 1203.2791 | L21: 1196.6606 | M21: 1277.0101 | N21: 1224.1118 | O21: 1183.3071 | P21: 1335.6949 | Q21: 1293.3464 | R21: 1328.7494 | S21: 1333.7159 | T21: 1343.7475 | U21: 1325.2106 | V21: 1365.6313 | W21: 1377.3001 | X21: 1344.2993 | Y21: 1391.3615 | Z21: 1326.2394 | AA21: 1359.4268 | AB21: =SUM(AC21:AN21) -> 16618.101 | AC21: 1515.198 | AD21: 1444.7439 | AE21: 1368.8589 | AF21: 1365.0714 | AG21: 1556.8244 | AH21: 1311.6815 | AI21: 1413.301 | AJ21: 1354.6427 | AK21: 1287.1562 | AL21: 1372.1195 | AM21: 1241.0059 | AN21: 1387.4979 | AO21: =(汇总!P91+汇总!P92+汇总!P98+汇总!P99+汇总!P103+汇总!P104)/10000 -> 100.84754 | AP21: =(汇总!M91+汇总!M92+汇总!M98+汇总!M99+汇总!M103+汇总!M104)/10000 -> 87.170944 | AQ21: =(汇总!N91+汇总!N92+汇总!N98+汇总!N99+汇总!N103+汇总!N104)/10000 -> 90.617543 | AU21: =AO21+AR21 -> 100.84754 | AV21: =AP21+AS21 -> 87.170944 | AW21: =AQ21+AT21 -> 90.617543 | AX21: =AU21-AB21 -> -16517.254 | AY21: =AV21-C21 -> -14881.764
B22: 人工成本-变动部分 | C22: =SUM(D22:O22) -> 0 | G22: 0 | H22: 0 | I22: 0 | J22: 0 | K22: 0 | L22: 0 | M22: 0 | N22: 0 | O22: 0 | AB22: =SUM(AC22:AN22) -> 0 | AH22: 0 | AJ22: 0 | AK22: 0 | AL22: 0 | AM22: 0 | AN22: 0 | AU22: =AO22+AR22 -> 0 | AV22: =AP22+AS22 -> 0 | AW22: =AQ22+AT22 -> 0 | AX22: =AU22-AB22 -> 0 | AY22: =AV22-C22 -> 0
B23: 折旧摊销 | C23: =SUM(D23:O23) -> 32891.401 | D23: 2748.0377 | E23: 2747.5546 | F23: 2749.4827 | G23: 2747.4841 | H23: 2298.7631 | I23: 2601.7073 | J23: 2630.6 | K23: 3416.8472 | L23: 2730.3372 | M23: 2732.8158 | N23: 2726.8365 | O23: 2760.9348 | P23: 2881.9021 | Q23: 2883.0617 | R23: 2884.1736 | S23: 2885.8989 | T23: 2886.7602 | U23: 2886.0176 | V23: 2886.084 | W23: 2886.2976 | X23: 2887.1521 | Y23: 2887.5341 | Z23: 2888.0364 | AA23: 2887.9039 | AB23: =SUM(AC23:AN23) -> 33502.958 | AC23: 2811.098 | AD23: 2661.7215 | AE23: 2931.4476 | AF23: 2866.5737 | AG23: 2809.1223 | AH23: 2900.3935 | AI23: 2906.8746 | AJ23: 2889.7596 | AK23: 2889.0658 | AL23: 2349.402 | AM23: 2759.4744 | AN23: 2728.0252 | AO23: =汇总!P128/10000 -> 59.499327 | AP23: =汇总!M128/10000 -> 58.990435 | AQ23: =汇总!N128/10000 -> 58.562947 | AU23: =AO23+AR23 -> 59.499327 | AV23: =AP23+AS23 -> 58.990435 | AW23: =AQ23+AT23 -> 58.562947 | AX23: =AU23-AB23 -> -33443.459 | AY23: =AV23-C23 -> -32832.411
B24: 能耗费 | C24: =SUM(D24:O24) -> 9021.3736 | D24: 920.42334 | E24: 830.16601 | F24: 696.57532 | G24: 576.24386 | H24: 673.11429 | I24: 664.11875 | J24: 890.06255 | K24: 896.98785 | L24: 679.53559 | M24: 666.1372 | N24: 710.11844 | O24: 817.89042 | P24: 997.46189 | Q24: 885.05608 | R24: 753.10384 | S24: 662.00569 | T24: 706.37725 | U24: 740.06523 | V24: 954.64956 | W24: 981.21669 | X24: 787.35814 | Y24: 780.53354 | Z24: 842.19002 | AA24: 937.46687 | AB24: =SUM(AC24:AN24) -> 10210.131 | AC24: 1049.6541 | AD24: 966.64473 | AE24: 790.56416 | AF24: 738.23683 | AG24: 663.73513 | AH24: 750.75754 | AI24: 1048.4838 | AJ24: 1112.9793 | AK24: 833.70553 | AL24: 642.69943 | AM24: 696.82237 | AN24: 915.84815 | AO24: =汇总!P101/10000 -> 120.78555 | AP24: =汇总!M101/10000 -> 121.01743 | AQ24: =汇总!N101/10000 -> 103.88839 | AU24: =AO24+AR24 -> 120.78555 | AV24: =AP24+AS24 -> 121.01743 | AW24: =AQ24+AT24 -> 103.88839 | AX24: =AU24-AB24 -> -10089.346 | AY24: =AV24-C24 -> -8900.3562
B25: 税金 | C25: =SUM(D25:O25) -> 6714.9641 | D25: 538.47147 | E25: 590.26001 | F25: 554.29376 | G25: 553.52669 | H25: 479.28811 | I25: 547.00726 | J25: 522.9198 | K25: 599.43113 | L25: 540.4357 | M25: 546.3895 | N25: 535.12121 | O25: 707.81943 | P25: 450.89132 | Q25: 467.02099 | R25: 446.47643 | S25: 437.40125 | T25: 439.98845 | U25: 448.90945 | V25: 441.70346 | W25: 442.7756 | X25: 450.18804 | Y25: 446.2205 | Z25: 442.01154 | AA25: 460.6651 | AB25: =SUM(AC25:AN25) -> 6717.6439 | AC25: 543.69943 | AD25: 592.03414 | AE25: 582.68257 | AF25: 555.36028 | AG25: 569.96202 | AH25: 547.29895 | AI25: 553.42253 | AJ25: 571.92126 | AK25: 562.30136 | AL25: 560.78007 | AM25: 547.18114 | AN25: 531.0002 | AO25: =(汇总!P96+汇总!P117)/10000 -> 14.877452 | AP25: =(汇总!M96+汇总!M117)/10000 -> 14.3546 | AQ25: =(汇总!N96+汇总!N117)/10000 -> 15.490759 | AU25: =AO25+AR25 -> 14.877452 | AV25: =AP25+AS25 -> 14.3546 | AW25: =AQ25+AT25 -> 15.490759 | AX25: =AU25-AB25 -> -6702.7665 | AY25: =AV25-C25 -> -6700.6095
B26: 酒店管理费 | C26: =SUM(D26:O26) -> 3199.8226 | D26: 294.63894 | E26: 226.78463 | F26: 247.1669 | G26: 249.49874 | H26: 298.32133 | I26: 221.38531 | J26: 236.51511 | K26: 234.83015 | L26: 230.05473 | M26: 317.00203 | N26: 313.03183 | O26: 330.59288 | P26: 297.89919 | Q26: 232.7844 | R26: 286.54962 | S26: 296.74221 | T26: 336.18579 | U26: 294.41072 | V26: 321.40586 | W26: 357.47121 | X26: 301.82414 | Y26: 387.73861 | Z26: 327.57241 | AA26: 342.48895 | AB26: =SUM(AC26:AN26) -> 3513.7857 | AC26: 302.62704 | AD26: 273.39283 | AE26: 316.4952 | AF26: 256.21442 | AG26: 322.64556 | AH26: 252.73771 | AI26: 275.62113 | AJ26: 347.63465 | AK26: 215.85544 | AL26: 291.28681 | AM26: 320.27585 | AN26: 338.99904 | AO26: =(汇总!P110+汇总!P112)/10000 -> 11.942634 | AP26: =(汇总!M110+汇总!M112)/10000 -> 10.173694 | AQ26: =(汇总!N110+汇总!N112)/10000 -> 9.93296 | AU26: =AO26+AR26 -> 11.942634 | AV26: =AP26+AS26 -> 10.173694 | AW26: =AQ26+AT26 -> 9.93296 | AX26: =AU26-AB26 -> -3501.843 | AY26: =AV26-C26 -> -3189.6489
B27: 其他费用 | C27: =SUM(D27:O27) -> 20765.61 | D27: 1919.9762 | E27: 1927.2909 | F27: 1956.3485 | G27: 1747.7679 | H27: 2291.737 | I27: 1629.7948 | J27: 2258.7761 | K27: 1894.5719 | L27: 1621.1031 | M27: 2022.0467 | N27: 1848.6664 | O27: -352.46943 | P27: 1954.4101 | Q27: 1745.9688 | R27: 1875.1531 | S27: 2017.8227 | T27: 2142.4249 | U27: 2003.3078 | V27: 2153.5701 | W27: 2232.0484 | X27: 2078.6319 | Y27: 2267.0647 | Z27: 2054.351 | AA27: 2176.3156 | AB27: =SUM(AC27:AN27) -> 24740.345 | AC27: 2250.2635 | AD27: 1934.0908 | AE27: 1915.434 | AF27: 1992.9116 | AG27: 2236.0833 | AH27: 1956.4235 | AI27: 2245.8606 | AJ27: 2465.5448 | AK27: 2080.3151 | AL27: 2228.7992 | AM27: 2019.9383 | AN27: 1414.6806 | AO27: =SUM(AO5:AO11)-SUM(AO15:AO26)-AO12 -> 190.4023 | AP27: =SUM(AP5:AP11)-SUM(AP15:AP26)-AP12 -> 141.19975 | AQ27: =SUM(AQ5:AQ11)-SUM(AQ15:AQ26)-AQ12 -> 151.00361 | AU27: =AO27+AR27 -> 190.4023 | AV27: =AP27+AS27 -> 141.19975 | AW27: =AQ27+AT27 -> 151.00361 | AX27: =AU27-AB27 -> -24549.943 | AY27: =AV27-C27 -> -20624.41
B28: 租金 | I28: 0 | K28: 0 | L28: 0 | M28: 0 | N28: 0 | O28: 0 | AH28: 0 | AJ28: 0 | AK28: 0 | AL28: 0 | AM28: 0 | AN28: 0 | AX28: =AU28-AB28 -> 0 | AY28: =AV28-C28 -> 0
B29: 宣传推广费（含渠道费） | I29: 0 | K29: 0 | L29: 0 | M29: 0 | N29: 0 | O29: 0 | AH29: 0 | AJ29: 0 | AK29: 0 | AL29: 0 | AM29: 0 | AN29: 0 | AX29: =AU29-AB29 -> 0 | AY29: =AV29-C29 -> 0
B30: 维修费 | I30: 0 | K30: 0 | L30: 0 | M30: 0 | N30: 0 | O30: 0 | AH30: 0 | AJ30: 0 | AK30: 0 | AL30: 0 | AM30: 0 | AN30: 0 | AX30: =AU30-AB30 -> 0 | AY30: =AV30-C30 -> 0
B31: 洗涤费 | I31: 0 | K31: 0 | L31: 0 | M31: 0 | N31: 0 | O31: 0 | AH31: 0 | AJ31: 0 | AK31: 0 | AL31: 0 | AM31: 0 | AN31: 0 | AX31: =AU31-AB31 -> 0 | AY31: =AV31-C31 -> 0
B32: 其他费用（控制在总成本费用的10%以内，并提供大致的费用性质） | I32: 0 | K32: 0 | L32: 0 | M32: 0 | N32: 0 | O32: 0 | AY32: =AV32-C32 -> 0
C33: =SUM(D33:O33) -> 0 | AB33: =SUM(AC33:AN33) -> 0
B34: 业主返还利润 | C34: =SUM(D34:O34) -> 17950.259 | D34: 1714.2431 | E34: 615.67064 | F34: 1001.871 | G34: 1368.7338 | H34: 2509.2823 | I34: 259.35907 | J34: 880.36441 | K34: 1155.3042 | L34: 351.99604 | M34: 3108.5293 | N34: 1811.5064 | O34: 3173.3984 | AB34: =SUM(AC34:AN34) -> 18596.322 | AC34: 2075.2821 | AD34: 997.38595 | AE34: 1451.485 | AF34: 1390.966 | AG34: 1816.1439 | AH34: 558.56564 | AI34: 1501.1157 | AJ34: 1995.8638 | AK34: 702.02423 | AL34: 2169.4745 | AM34: 2657.8064 | AN34: 1280.2084 | AO34: =汇总!P148/10000 -> -116.62855 | AP34: =汇总!M148/10000 -> -102.33954 | AQ34: =汇总!N148/10000 -> -85.370055 | AR34: =#REF!/10000 -> #REF! | AS34: =AS12 -> #REF! | AT34: =AT12 -> #REF! | AU34: =AO34+AR34 -> #REF! | AV34: =AP34+AS34 -> #REF! | AW34: =AQ34+AT34 -> #REF! | AX34: =AU34-AB34 -> #REF! | AY34: =AV34-C34 -> #REF!
B36: 收入 | C36: =SUM(C5:C11) -> 107767.37 | D36: =SUM(D5:D11) -> 10283.246 | E36: =SUM(E5:E11) -> 7965.5511 | F36: =SUM(F5:F11) -> 8172.26 | G36: =SUM(G5:G11) -> 8603.599 | H36: =SUM(H5:H11) -> 10867.318 | I36: =SUM(I5:I11) -> 6700.229 | J36: =SUM(J5:J11) -> 8578.4046 | ... AW36: =SUM(AW5:AW11) -> 448.34059 | AX36: =AU36-AB36 -> -119442.15 | AY36: =SUM(AY5:AY11) -> -107357.63
B37: 费用 | C37: =SUM(C15:C27) -> 130503.45 | D37: =SUM(D15:D27) -> 11930.809 | E37: =SUM(E15:E27) -> 10705.618 | F37: =SUM(F15:F27) -> 10807.908 | G37: =SUM(G15:G27) -> 10327.281 | H37: =SUM(H15:H27) -> 11514.642 | I37: =SUM(I15:I27) -> 9637.7444 | J37: =SUM(J15:J27) -> 11239.713 | ... AW37: =SUM(AW15:AW27) -> #REF! | AX37: =AU37-AB37 -> #REF! | AY37: =SUM(AY15:AY27) -> #REF!
B38: 净利润 | C38: =C36-C37 -> -22736.079 | D38: =D36-D37 -> -1647.5633 | E38: =E36-E37 -> -2740.0673 | F38: =F36-F37 -> -2635.6477 | G38: =G36-G37 -> -1723.6823 | H38: =H36-H37 -> -647.32453 | I38: =I36-I37 -> -2937.5154 | J38: =J36-J37 -> -2661.3087 | ... AW38: =AW36-AW37 -> #REF! | AX38: =AU38-AB38 -> #REF! | AY38: =AY36-AY37 -> #REF!
B39: check | C39: =C12-C38 -> 0 | D39: =D12-D38 -> 3.8653525e-12 | E39: =E12-E38 -> -5.9117156e-12 | F39: =F12-F38 -> 3.6379788e-12 | G39: =G12-G38 -> -6.3664629e-12 | H39: =H12-H38 -> 0 | I39: =I12-I38 -> 0 | J39: =J12-J38 -> 8.1854523e-12 | ... AW39: =AW12-AW38 -> #REF! | AX39: =AU39-AB39 -> #REF! | AY39: =AY12-AY38 -> #REF!
C41: 当期 | D41: 当期 | E41: 当期 | F41: 累计 | G41: 累计 | H41: 累计 | I41: 当期 | J41: 当期 | K41: 当期 | L41: 累计 | M41: 累计 | N41: 累计
C42: 完成 | D42: 完成 | E42: 完成 | F42: 完成 | G42: 完成 | H42: 完成 | I42: 上年同期 | J42: 上年同期 | K42: 上年同期 | L42: 上年同期 | M42: 上年同期 | N42: 上年同期
C43: 新事业部表 | D43: 汇总-X月 | E43: 差异 | F43: 新事业部表 | G43: 汇总-累计 | H43: 差异 | I43: 新事业部表 | J43: 汇总-X月 | K43: 差异 | L43: 新事业部表 | M43: 汇总-累计 | N43: 差异
B44: 总收入 | C44: =SUM(O5:O11) -> 8493.1864 | D44: ='汇总-1月'!C3 -> 409.74156 | E44: =C44-D44 -> 8083.4448 | F44: =SUM(C5:C11) -> 107767.37 | G44: ='汇总-累计'!C3 -> 409.74156 | H44: =F44-G44 -> 107357.63 | I44: =SUM(AN5:AN11) -> 9329.8825 | J44: ='汇总-1月'!F3 -> 500.19513 | K44: =I44-J44 -> 8829.6874 | L44: =SUM(AB5:AB11) -> 119942.35 | M44: ='汇总-累计'!F3 -> 500.19513 | N44: =L44-M44 -> 119442.15
B45: 业主利润返还（上报口径） | C45: =O34 -> 3173.3984 | D45: ='汇总-1月'!M3 -> -102.33954 | E45: =C45-D45 -> 3275.7379 | F45: =C34 -> 17950.259 | G45: ='汇总-累计'!O3 -> -102.33954 | H45: =F45-G45 -> 18052.598 | I45: =AN34 -> 1280.2084 | J45: ='汇总-1月'!P3 -> -116.62855 | K45: =I45-J45 -> 1396.837 | L45: =AB34 -> 18596.322 | M45: ='汇总-累计'!R3 -> -116.62855 | N45: =L45-M45 -> 18712.95
B46: 业主利润返还-广州凤凰
B47: 净利润 | C47: =O12 -> -209.27686 | D47: ='汇总明细-1月'!BL3/10000 -> -233.11076 | E47: =C47-D47 -> 23.833896 | F47: =C12 -> -22736.079 | G47: ='汇总明细-1月'!BM3/10000 -> -233.11076 | H47: =F47-G47 -> -22502.968 | I47: =AN12 -> -1581.9878 | J47: ='汇总明细-1月'!BP3/10000 -> -276.75864 | K47: =I47-J47 -> -1305.2292 | L47: =AB12 -> -23635.529 | M47: ='汇总明细-1月'!BQ3/10000 -> -276.75864 | N47: =L47-M47 -> -23358.771

Sheet 汇总
H1: net; | I1: MtdAdj; | J1: MtdAct; | K1: Budget; | N1: LastYearMtd; | Q1: YtdNet; | R1: YtdAdj; | S1: YtdAct; | T1: YtdBudget; | W1: LastYearYtd; | Z1: Total;
G2: 军令状 | H2: =于洪!H2 -> 2026年1月 | I2: 预算行业损益总表 | R2: 单位： | S2: 元
G3: DESCRIPTION | H3: 本月 | M3: 本年累计 | R3: 全年预算指标完成进度
H4: 实际 | I4: 预算 | J4: 差异率 | K4: 去年 | L4: 差异率 | M4: 实际 | N4: 预算 | O4: 差异率 | P4: 去年 | Q4: 差异率 | R4: 全年预算 | S4: 完成率
G5: Total Rooms 总房量 | H5: =SUM(于洪:武汉!H5) -> 38719 | I5: =SUM(于洪:武汉!I5) -> 38688 | J5: =IF(I5=0,"",H5/I5-1) -> 0.00080128205 | K5: =SUM(于洪:武汉!K5) -> 40145 | L5: =IF(K5=0,"",H5/K5-1) -> -0.035521236 | M5: =SUM(于洪:武汉!M5) -> 38719 | N5: =SUM(于洪:武汉!N5) -> 38688 | O5: =IF(N5=0,"",M5/N5-1) -> 0.00080128205 | P5: =SUM(于洪:武汉!P5) -> 40145 | Q5: =IF(P5=0,"",M5/P5-1) -> -0.035521236 | R5: =SUM(于洪:武汉!R5) -> 455520 | S5: =IF(R5=0,"",M5/R5-1) -> -0.91500044
G6: Available Room 可出租房 | H6: =SUM(于洪:武汉!H6) -> 38566 | I6: =SUM(于洪:武汉!I6) -> 38688 | J6: =IF(I6=0,"",H6/I6-1) -> -0.0031534326 | K6: =SUM(于洪:武汉!K6) -> 37956 | L6: =IF(K6=0,"",H6/K6-1) -> 0.01607124 | M6: =SUM(于洪:武汉!M6) -> 38566 | N6: =SUM(于洪:武汉!N6) -> 38688 | O6: =IF(N6=0,"",M6/N6-1) -> -0.0031534326 | P6: =SUM(于洪:武汉!P6) -> 37956 | Q6: =IF(P6=0,"",M6/P6-1) -> 0.01607124 | R6: =SUM(于洪:武汉!R6) -> 455520 | S6: =IF(R6=0,"",M6/R6-1) -> -0.91533632
G7: Occupied Room Nights 已售间夜 | H7: =SUM(于洪:武汉!H7) -> 8312 | I7: =SUM(于洪:武汉!I7) -> 8745 | J7: =IF(I7=0,"",H7/I7-1) -> -0.049514008 | K7: =SUM(于洪:武汉!K7) -> 8110.5 | L7: =IF(K7=0,"",H7/K7-1) -> 0.024844338 | M7: =SUM(于洪:武汉!M7) -> 8312 | N7: =SUM(于洪:武汉!N7) -> 8745 | O7: =IF(N7=0,"",M7/N7-1) -> -0.049514008 | P7: =SUM(于洪:武汉!P7) -> 8110.5 | Q7: =IF(P7=0,"",M7/P7-1) -> 0.024844338 | R7: =SUM(于洪:武汉!R7) -> 148467.5 | S7: =IF(R7=0,"",M7/R7-1) -> -0.94401468
G8: Occupied Room Nights 已售间夜-有价 | H8: =SUM(于洪:武汉!H8) -> 8089.5 | I8: =SUM(于洪:武汉!I8) -> 8745 | J8: =IF(I8=0,"",H8/I8-1) -> -0.074957118 | K8: =SUM(于洪:武汉!K8) -> 7841.5 | L8: =IF(K8=0,"",H8/K8-1) -> 0.031626602 | M8: =SUM(于洪:武汉!M8) -> 8089.5 | N8: =SUM(于洪:武汉!N8) -> 8745 | O8: =IF(N8=0,"",M8/N8-1) -> -0.074957118 | P8: =SUM(于洪:武汉!P8) -> 7841.5 | Q8: =IF(P8=0,"",M8/P8-1) -> 0.031626602 | R8: =SUM(于洪:武汉!R8) -> 148467.5 | S8: =IF(R8=0,"",M8/R8-1) -> -0.94551333
A9: NoCalc | G9: Occupancy % 已售间夜OCC | H9: =H7/H5 -> 0.21467497 | I9: =I7/I5 -> 0.22603908 | J9: =IF(I9=0,"",H9/I9-1) -> -0.050275006 | K9: =K7/K5 -> 0.20203014 | L9: =IF(K9=0,"",H9/K9-1) -> 0.062588805 | M9: =M7/M5 -> 0.21467497 | N9: =N7/N5 -> 0.22603908 | O9: =IF(N9=0,"",M9/N9-1) -> -0.050275006 | P9: =P7/P5 -> 0.20203014 | Q9: =IF(P9=0,"",M9/P9-1) -> 0.062588805 | R9: =R7/R5 -> 0.32592971 | S9: =IF(R9=0,"",M9/R9-1) -> -0.34134581
A10: NoCalc | G10: Occupancy % 已售间夜OCC-有价 | H10: =H8/H5 -> 0.20892843 | I10: =I8/I5 -> 0.22603908 | J10: =IF(I10=0,"",H10/I10-1) -> -0.075697745 | K10: =K8/K5 -> 0.19532943 | L10: =IF(K10=0,"",H10/K10-1) -> 0.069620856 | M10: =M8/M5 -> 0.20892843 | N10: =N8/N5 -> 0.22603908 | O10: =IF(N10=0,"",M10/N10-1) -> -0.075697745 | P10: =P8/P5 -> 0.19532943 | Q10: =IF(P10=0,"",M10/P10-1) -> 0.069620856 | R10: =R8/R5 -> 0.32592971 | S10: =IF(R10=0,"",M10/R10-1) -> -0.35897702
G11: Average Daily Rate 已售间夜ADR | J11: =IF(H11=0,"",G11/H11-1)
G12: Average Daily Rate 已售间夜ADR-有价 | J12: =IF(H12=0,"",G12/H12-1)
G13: RevPAR 平均可出租房收入（总房量）
G15: 预算科目 | H15: 实际 | I15: 预算 | J15: 差异率 | K15: 去年 | L15: 差异率 | M15: 实际 | N15: 预算 | O15: 差异率 | P15: 去年 | Q15: 差异率 | R15: 全年预算 | S15: 完成率
G16: Total Revenue 总收入 | H16: =SUM(于洪:武汉!H16) -> 4097415.6 | I16: =SUM(于洪:武汉!I16) -> 4483405.9 | J16: =IF(I16=0,"",H16/I16-1) -> -0.086093089 | K16: =SUM(于洪:武汉!K16) -> 5001951.3 | L16: =IF(K16=0,"",H16/K16-1) -> -0.18083656 | M16: =SUM(于洪:武汉!M16) -> 4097415.6 | N16: =SUM(于洪:武汉!N16) -> 4483405.9 | O16: =IF(N16=0,"",M16/N16-1) -> -0.086093089 | P16: =SUM(于洪:武汉!P16) -> 5001951.3 | Q16: =IF(P16=0,"",M16/P16-1) -> -0.18083656 | R16: =SUM(于洪:武汉!R16) -> 65708706 | S16: =IF(R16=0,"",M16/R16-1) -> -0.93764273
E17: 注意不含客房销售成本 | G17: Total Cost of Sales 总销售成本 | H17: =SUM(于洪:武汉!H17) -> 1071025.9 | I17: =SUM(于洪:武汉!I17) -> 1131793.1 | J17: =IF(I17=0,"",H17/I17-1) -> -0.053691043 | K17: =SUM(于洪:武汉!K17) -> 1493908.4 | L17: =IF(K17=0,"",H17/K17-1) -> -0.28307121 | M17: =SUM(于洪:武汉!M17) -> 1071025.9 | N17: =SUM(于洪:武汉!N17) -> 1131793.1 | O17: =IF(N17=0,"",M17/N17-1) -> -0.053691043 | P17: =SUM(于洪:武汉!P17) -> 1493908.4 | Q17: =IF(P17=0,"",M17/P17-1) -> -0.28307121 | R17: =SUM(于洪:武汉!R17) -> 13555234 | S17: =IF(R17=0,"",M17/R17-1) -> -0.92098802
G18: Total Operating Depts Expenses 总运营费用 | H18: =SUM(于洪:武汉!H18) -> 1355372.2 | I18: =SUM(于洪:武汉!I18) -> 1518115.9 | J18: =IF(I18=0,"",H18/I18-1) -> -0.10720109 | K18: =SUM(于洪:武汉!K18) -> 1682706.4 | L18: =IF(K18=0,"",H18/K18-1) -> -0.19452838 | M18: =SUM(于洪:武汉!M18) -> 1355372.2 | N18: =SUM(于洪:武汉!N18) -> 1518115.9 | O18: =IF(N18=0,"",M18/N18-1) -> -0.10720109 | P18: =SUM(于洪:武汉!P18) -> 1682706.4 | Q18: =IF(P18=0,"",M18/P18-1) -> -0.19452838 | R18: =SUM(于洪:武汉!R18) -> 21031831 | S18: =IF(R18=0,"",M18/R18-1) -> -0.93555615
G19: Total Undistributed Expenses 总未分配费用 | H19: =SUM(于洪:武汉!H19) -> 2317998.4 | I19: =SUM(于洪:武汉!I19) -> 2301927.8 | J19: =IF(I19=0,"",H19/I19-1) -> 0.0069813441 | K19: =SUM(于洪:武汉!K19) -> 2537463.9 | L19: =IF(K19=0,"",H19/K19-1) -> -0.086490103 | M19: =SUM(于洪:武汉!M19) -> 2317998.4 | N19: =SUM(于洪:武汉!N19) -> 2301927.8 | O19: =IF(N19=0,"",M19/N19-1) -> 0.0069813441 | P19: =SUM(于洪:武汉!P19) -> 2537463.9 | Q19: =IF(P19=0,"",M19/P19-1) -> -0.086490103 | R19: =SUM(于洪:武汉!R19) -> 25094390 | S19: =IF(R19=0,"",M19/R19-1) -> -0.90762882
G20: Gross Operating Profit 经营毛利 | H20: =H16-SUM(H17:H19) -> -646980.91 | I20: =I16-SUM(I17:I19) -> -468430.93 | J20: =IF(I20=0,"",H20/I20-1) -> 0.38116608 | K20: =K16-SUM(K17:K19) -> -712127.33 | L20: =IF(K20=0,"",H20/K20-1) -> -0.091481421 | M20: =M16-SUM(M17:M19) -> -646980.91 | N20: =N16-SUM(N17:N19) -> -468430.93 | O20: =IF(N20=0,"",M20/N20-1) -> 0.38116608 | P20: =P16-SUM(P17:P19) -> -712127.33 | Q20: =IF(P20=0,"",M20/P20-1) -> -0.091481421 | R20: =R16-SUM(R17:R19) -> 6027250.7 | S20: =IF(R20=0,"",M20/R20-1) -> -1.1073426
G21: Gop % 经营毛利率 | H21: =IFERROR(H20/H16,0) -> -0.15789975 | I21: =IFERROR(I20/I16,0) -> -0.10448104 | J21: =IF(I21=0,"",H21/I21-1) -> 0.51127654 | K21: =IFERROR(K20/K16,0) -> -0.14236991 | L21: =IF(K21=0,"",H21/K21-1) -> 0.10908097 | M21: =IFERROR(M20/M16,0) -> -0.15789975 | N21: =IFERROR(N20/N16,0) -> -0.10448104 | O21: =IF(N21=0,"",M21/N21-1) -> 0.51127654 | P21: =IFERROR(P20/P16,0) -> -0.14236991 | Q21: =IF(P21=0,"",M21/P21-1) -> 0.10908097 | R21: =IFERROR(R20/R16,0) -> 0.091726821 | S21: =IF(R21=0,"",M21/R21-1) -> -2.7214131
G22: Total Management Fee 酒店管理费合计 | H22: =SUM(于洪:武汉!H22) -> 101736.94 | I22: =SUM(于洪:武汉!I22) -> 99329.6 | J22: =IF(I22=0,"",H22/I22-1) -> 0.024235877 | K22: =SUM(于洪:武汉!K22) -> 119426.34 | L22: =IF(K22=0,"",H22/K22-1) -> -0.14811975 | M22: =SUM(于洪:武汉!M22) -> 101736.94 | N22: =SUM(于洪:武汉!N22) -> 99329.6 | O22: =IF(N22=0,"",M22/N22-1) -> 0.024235877 | P22: =SUM(于洪:武汉!P22) -> 119426.34 | Q22: =IF(P22=0,"",M22/P22-1) -> -0.14811975 | R22: =SUM(于洪:武汉!R22) -> 1423895.5 | S22: =IF(R22=0,"",M22/R22-1) -> -0.92855028
G23: Non-operating Income and Expenses 非经营相关收入及支出 | H23: =SUM(于洪:武汉!H23) -> -702404.5 | I23: =SUM(于洪:武汉!I23) -> -695073.65 | J23: =IF(I23=0,"",H23/I23-1) -> 0.010546868 | K23: =SUM(于洪:武汉!K23) -> -1032045.6 | L23: =IF(K23=0,"",H23/K23-1) -> -0.31940556 | M23: =SUM(于洪:武汉!M23) -> -702404.5 | N23: =SUM(于洪:武汉!N23) -> -695073.65 | O23: =IF(N23=0,"",M23/N23-1) -> 0.010546868 | P23: =SUM(于洪:武汉!P23) -> -1032045.6 | Q23: =IF(P23=0,"",M23/P23-1) -> -0.31940556 | R23: =SUM(于洪:武汉!R23) -> -9075786 | S23: =IF(R23=0,"",M23/R23-1) -> -0.92260676
G24: EBITDA 息税前利润 | H24: =H20-H22+H23 -> -1451122.3 | I24: =I20-I22+I23 -> -1262834.2 | J24: =IF(I24=0,"",H24/I24-1) -> 0.14909968 | K24: =K20-K22+K23 -> -1863599.3 | L24: =IF(K24=0,"",H24/K24-1) -> -0.22133349 | M24: =M20-M22+M23 -> -1451122.3 | N24: =N20-N22+N23 -> -1262834.2 | O24: =IF(N24=0,"",M24/N24-1) -> 0.14909968 | P24: =P20-P22+P23 -> -1863599.3 | Q24: =IF(P24=0,"",M24/P24-1) -> -0.22133349 | R24: =R20-R22+R23 -> -4472430.8 | S24: =IF(R24=0,"",M24/R24-1) -> -0.67554057
G25: FFE 资产重置基金 | H25: =SUM(于洪:武汉!H25) -> 103771.04 | I25: =SUM(于洪:武汉!I25) -> 99829.55 | J25: =IF(I25=0,"",H25/I25-1) -> 0.039482162 | K25: =SUM(于洪:武汉!K25) -> 183468.17 | L25: =IF(K25=0,"",H25/K25-1) -> -0.43439216 | M25: =SUM(于洪:武汉!M25) -> 103771.04 | N25: =SUM(于洪:武汉!N25) -> 99829.55 | O25: =IF(N25=0,"",M25/N25-1) -> 0.039482162 | P25: =SUM(于洪:武汉!P25) -> 183468.17 | Q25: =IF(P25=0,"",M25/P25-1) -> -0.43439216 | R25: =SUM(于洪:武汉!R25) -> 1361952.5 | S25: =IF(R25=0,"",M25/R25-1) -> -0.92380715
G26: Owner's Return 业主返还利润 | H26: =H24-H25 -> -1554893.4 | I26: =I24-I25 -> -1362663.7 | J26: =IF(I26=0,"",H26/I26-1) -> 0.14106903 | K26: =K24-K25 -> -2047067.5 | L26: =IF(K26=0,"",H26/K26-1) -> -0.24042885 | M26: =M24-M25 -> -1554893.4 | N26: =N24-N25 -> -1362663.7 | O26: =IF(N26=0,"",M26/N26-1) -> 0.14106903 | P26: =P24-P25 -> -2047067.5 | Q26: =IF(P26=0,"",M26/P26-1) -> -0.24042885 | R26: =R24-R25 -> -5834383.3 | S26: =IF(R26=0,"",M26/R26-1) -> -0.73349482
G27: Interest, Depreciation, and Amorization 利息、折旧、摊销 | H27: =SUM(于洪:武汉!H27) -> 879985.23 | I27: =SUM(于洪:武汉!I27) -> 886972.78 | J27: =IF(I27=0,"",H27/I27-1) -> -0.0078779757 | K27: =SUM(于洪:武汉!K27) -> 903987.09 | L27: =IF(K27=0,"",H27/K27-1) -> -0.026551109 | M27: =SUM(于洪:武汉!M27) -> 879985.23 | N27: =SUM(于洪:武汉!N27) -> 886972.78 | O27: =IF(N27=0,"",M27/N27-1) -> -0.0078779757 | P27: =SUM(于洪:武汉!P27) -> 903987.09 | Q27: =IF(P27=0,"",M27/P27-1) -> -0.026551109 | R27: =SUM(于洪:武汉!R27) -> 10429632 | S27: =IF(R27=0,"",M27/R27-1) -> -0.91562643
G28: Corporate Income Tax 企业所得税 | H28: =SUM(于洪:武汉!H28) -> 0 | I28: =SUM(于洪:武汉!I28) -> 0 | J28: =IF(I28=0,"",H28/I28-1) | K28: =SUM(于洪:武汉!K28) -> 0 | L28: =IF(K28=0,"",H28/K28-1) | M28: =SUM(于洪:武汉!M28) -> 0 | N28: =SUM(于洪:武汉!N28) -> 0 | O28: =IF(N28=0,"",M28/N28-1) | P28: =SUM(于洪:武汉!P28) -> 0 | Q28: =IF(P28=0,"",M28/P28-1) | R28: =SUM(于洪:武汉!R28) -> 0 | S28: =IF(R28=0,"",M28/R28-1)
G29: Net Profit 净利润 | H29: =H26-H27-H28 -> -2434878.6 | I29: =I26-I27-I28 -> -2249636.5 | J29: =IF(I29=0,"",H29/I29-1) -> 0.082343128 | K29: =K26-K27-K28 -> -2951054.5 | L29: =IF(K29=0,"",H29/K29-1) -> -0.17491236 | M29: =M26-M27-M28 -> -2434878.6 | N29: =N26-N27-N28 -> -2249636.5 | O29: =IF(N29=0,"",M29/N29-1) -> 0.082343128 | P29: =P26-P27-P28 -> -2951054.5 | Q29: =IF(P29=0,"",M29/P29-1) -> -0.17491236 | R29: =R26-R27-R28 -> -16264015 | S29: =IF(R29=0,"",M29/R29-1) -> -0.85029043
G30: KPI's重要指标
G31: Payroll&Rel Expenses 工资及相关费用 | H31: =SUM(于洪:武汉!H31) -> 1900138.2 | I31: =SUM(于洪:武汉!I31) -> 2112633.1 | J31: =IF(I31=0,"",H31/I31-1) -> -0.10058295 | K31: =SUM(于洪:武汉!K31) -> 2300556.6 | L31: =IF(K31=0,"",H31/K31-1) -> -0.17405284 | M31: =SUM(于洪:武汉!M31) -> 1900138.2 | N31: =SUM(于洪:武汉!N31) -> 2112633.1 | O31: =IF(N31=0,"",M31/N31-1) -> -0.10058295 | P31: =SUM(于洪:武汉!P31) -> 2300556.6 | Q31: =IF(P31=0,"",M31/P31-1) -> -0.17405284 | R31: =SUM(于洪:武汉!R31) -> 26252813 | S31: =IF(R31=0,"",M31/R31-1) -> -0.92762154
G32: 其中：Year-end bonus 年终奖 | H32: =SUM(于洪:武汉!H32) -> 118993.67 | I32: =SUM(于洪:武汉!I32) -> 118993.66 | J32: =IF(I32=0,"",H32/I32-1) -> 8.4038091e-08 | K32: =SUM(于洪:武汉!K32) -> 173137.42 | L32: =IF(K32=0,"",H32/K32-1) -> -0.31272125 | M32: =SUM(于洪:武汉!M32) -> 118993.67 | N32: =SUM(于洪:武汉!N32) -> 118993.66 | O32: =IF(N32=0,"",M32/N32-1) -> 8.4038091e-08 | P32: =SUM(于洪:武汉!P32) -> 173137.42 | Q32: =IF(P32=0,"",M32/P32-1) -> -0.31272125 | R32: =SUM(于洪:武汉!R32) -> 1427924 | S32: =IF(R32=0,"",M32/R32-1) -> -0.91666666
G33: Payroll&Rel Expenses % 工资及相关费用占比 | H33: =IFERROR(H31/H16,0) -> 0.46374066 | I33: =IFERROR(I31/I16,0) -> 0.47121165 | J33: =IF(I33=0,"",H33/I33-1) -> -0.015854852 | K33: =IFERROR(K31/K16,0) -> 0.45993183 | L33: =IF(K33=0,"",H33/K33-1) -> 0.0082812824 | M33: =IFERROR(M31/M16,0) -> 0.46374066 | N33: =IFERROR(N31/N16,0) -> 0.47121165 | O33: =IF(N33=0,"",M33/N33-1) -> -0.015854852 | P33: =IFERROR(P31/P16,0) -> 0.45993183 | Q33: =IF(P33=0,"",M33/P33-1) -> 0.0082812824 | R33: =IFERROR(R31/R16,0) -> 0.39953325 | S33: =IF(R33=0,"",M33/R33-1) -> 0.16070604
G34: Energy 能源费用 | H34: =SUM(于洪:武汉!H34) -> 1210174.2 | I34: =SUM(于洪:武汉!I34) -> 1038883.9 | J34: =IF(I34=0,"",H34/I34-1) -> 0.16487916 | K34: =SUM(于洪:武汉!K34) -> 1207855.5 | L34: =IF(K34=0,"",H34/K34-1) -> 0.0019196832 | M34: =SUM(于洪:武汉!M34) -> 1210174.2 | N34: =SUM(于洪:武汉!N34) -> 1038883.9 | O34: =IF(N34=0,"",M34/N34-1) -> 0.16487916 | P34: =SUM(于洪:武汉!P34) -> 1207855.5 | Q34: =IF(P34=0,"",M34/P34-1) -> 0.0019196832 | R34: =SUM(于洪:武汉!R34) -> 8857093.7 | S34: =IF(R34=0,"",M34/R34-1) -> -0.86336667
G35: Energy % 能源费用占比 | H35: =IFERROR(H34/H16,0) -> 0.29535062 | I35: =IFERROR(I34/I16,0) -> 0.23171758 | J35: =IF(I35=0,"",H35/I35-1) -> 0.27461467 | K35: =IFERROR(K34/K16,0) -> 0.24147687 | L35: =IF(K35=0,"",H35/K35-1) -> 0.22310108 | M35: =IFERROR(M34/M16,0) -> 0.29535062 | N35: =IFERROR(N34/N16,0) -> 0.23171758 | O35: =IF(N35=0,"",M35/N35-1) -> 0.27461467 | P35: =IFERROR(P34/P16,0) -> 0.24147687 | Q35: =IF(P35=0,"",M35/P35-1) -> 0.22310108 | R35: =IFERROR(R34/R16,0) -> 0.13479331 | S35: =IF(R35=0,"",M35/R35-1) -> 1.1911371
G36: Maintenance Expense 维修费用 | H36: =SUM(于洪:武汉!H36) -> 81700.8 | I36: =SUM(于洪:武汉!I36) -> 90167 | J36: =IF(I36=0,"",H36/I36-1) -> -0.093894662 | K36: =SUM(于洪:武汉!K36) -> 80427.4 | L36: =IF(K36=0,"",H36/K36-1) -> 0.015832913 | M36: =SUM(于洪:武汉!M36) -> 81700.8 | N36: =SUM(于洪:武汉!N36) -> 90167 | O36: =IF(N36=0,"",M36/N36-1) -> -0.093894662 | P36: =SUM(于洪:武汉!P36) -> 80427.4 | Q36: =IF(P36=0,"",M36/P36-1) -> 0.015832913 | R36: =SUM(于洪:武汉!R36) -> 1551338 | S36: =IF(R36=0,"",M36/R36-1) -> -0.94733527
G37: Maintenance Expense % 维修费用占比 | H37: =IFERROR(H36/H16,0) -> 0.019939593 | I37: =IFERROR(I36/I16,0) -> 0.020111273 | J37: =IF(I37=0,"",H37/I37-1) -> -0.0085365076 | K37: =IFERROR(K36/K16,0) -> 0.016079205 | L37: =IF(K37=0,"",H37/K37-1) -> 0.24008576 | M37: =IFERROR(M36/M16,0) -> 0.019939593 | N37: =IFERROR(N36/N16,0) -> 0.020111273 | O37: =IF(N37=0,"",M37/N37-1) -> -0.0085365076 | P37: =IFERROR(P36/P16,0) -> 0.016079205 | Q37: =IF(P37=0,"",M37/P37-1) -> 0.24008576 | R37: =IFERROR(R36/R16,0) -> 0.023609322 | S37: =IF(R37=0,"",M37/R37-1) -> -0.15543559
G38: Laundry 洗涤费 | H38: =SUM(于洪:武汉!H38) -> 82978.89 | I38: =SUM(于洪:武汉!I38) -> 82944.82 | J38: =IF(I38=0,"",H38/I38-1) -> 0.00041075501 | K38: =SUM(于洪:武汉!K38) -> 119251.93 | L38: =IF(K38=0,"",H38/K38-1) -> -0.30417151 | M38: =SUM(于洪:武汉!M38) -> 82978.89 | N38: =SUM(于洪:武汉!N38) -> 82944.82 | O38: =IF(N38=0,"",M38/N38-1) -> 0.00041075501 | P38: =SUM(于洪:武汉!P38) -> 119251.93 | Q38: =IF(P38=0,"",M38/P38-1) -> -0.30417151 | R38: =SUM(于洪:武汉!R38) -> 1327526.5 | S38: =IF(R38=0,"",M38/R38-1) -> -0.93749361
G39: Laundry % 洗涤费占比 | H39: =IFERROR(H38/H16,0) -> 0.020251519 | I39: =IFERROR(I38/I16,0) -> 0.018500404 | J39: =IF(I39=0,"",H39/I39-1) -> 0.094652795 | K39: =IFERROR(K38/K16,0) -> 0.023841082 | L39: =IF(K39=0,"",H39/K39-1) -> -0.15056208 | M39: =IFERROR(M38/M16,0) -> 0.020251519 | N39: =IFERROR(N38/N16,0) -> 0.018500404 | O39: =IF(N39=0,"",M39/N39-1) -> 0.094652795 | P39: =IFERROR(P38/P16,0) -> 0.023841082 | Q39: =IF(P39=0,"",M39/P39-1) -> -0.15056208 | R39: =IFERROR(R38/R16,0) -> 0.020203206 | S39: =IF(R39=0,"",M39/R39-1) -> 0.002391343
G41: 预算明细组成 | H41: 实际 | I41: 预算 | J41: 差异率 | K41: 去年 | L41: 差异率 | M41: 实际 | N41: 预算 | O41: 差异率 | P41: 去年 | Q41: 差异率 | R41: 全年预算 | S41: 完成率
G42: ROOMS 客房
G43: Rooms Revenue 客房收入 | H43: =SUM(于洪:武汉!H43) -> 1706402 | I43: =SUM(于洪:武汉!I43) -> 1873318.6 | J43: =IF(I43=0,"",H43/I43-1) -> -0.089102094 | K43: =SUM(于洪:武汉!K43) -> 1726539.1 | L43: =IF(K43=0,"",H43/K43-1) -> -0.011663252 | M43: =SUM(于洪:武汉!M43) -> 1706402 | N43: =SUM(于洪:武汉!N43) -> 1873318.6 | O43: =IF(N43=0,"",M43/N43-1) -> -0.089102094 | P43: =SUM(于洪:武汉!P43) -> 1726539.1 | Q43: =IF(P43=0,"",M43/P43-1) -> -0.011663252 | R43: =SUM(于洪:武汉!R43) -> 32820784 | S43: =IF(R43=0,"",M43/R43-1) -> -0.94800849
G44: Salary & Wages 薪资 | H44: =SUM(于洪:武汉!H44) -> 307762.44 | I44: =SUM(于洪:武汉!I44) -> 428947.6 | J44: =IF(I44=0,"",H44/I44-1) -> -0.2825174 | K44: =SUM(于洪:武汉!K44) -> 297215.56 | L44: =IF(K44=0,"",H44/K44-1) -> 0.035485625 | M44: =SUM(于洪:武汉!M44) -> 307762.44 | N44: =SUM(于洪:武汉!N44) -> 428947.6 | O44: =IF(N44=0,"",M44/N44-1) -> -0.2825174 | P44: =SUM(于洪:武汉!P44) -> 297215.56 | Q44: =IF(P44=0,"",M44/P44-1) -> 0.035485625 | R44: =SUM(于洪:武汉!R44) -> 5315635.2 | S44: =IF(R44=0,"",M44/R44-1) -> -0.94210242
G45: Payroll Related Exp. 薪资相关费用 | H45: =SUM(于洪:武汉!H45) -> 154091.4 | I45: =SUM(于洪:武汉!I45) -> 182571.65 | J45: =IF(I45=0,"",H45/I45-1) -> -0.15599492 | K45: =SUM(于洪:武汉!K45) -> 196403.52 | L45: =IF(K45=0,"",H45/K45-1) -> -0.21543463 | M45: =SUM(于洪:武汉!M45) -> 154091.4 | N45: =SUM(于洪:武汉!N45) -> 182571.65 | O45: =IF(N45=0,"",M45/N45-1) -> -0.15599492 | P45: =SUM(于洪:武汉!P45) -> 196403.52 | Q45: =IF(P45=0,"",M45/P45-1) -> -0.21543463 | R45: =SUM(于洪:武汉!R45) -> 2258758.4 | S45: =IF(R45=0,"",M45/R45-1) -> -0.93178049
G46: All Other Rooms Expenses (including Reservation Fees) 其他客房支出(包括订房系统费用) | H46: =SUM(于洪:武汉!H46) -> 316862.74 | I46: =SUM(于洪:武汉!I46) -> 331752.95 | J46: =IF(I46=0,"",H46/I46-1) -> -0.044883429 | K46: =SUM(于洪:武汉!K46) -> 299174.8 | L46: =IF(K46=0,"",H46/K46-1) -> 0.059122426 | M46: =SUM(于洪:武汉!M46) -> 316862.74 | N46: =SUM(于洪:武汉!N46) -> 331752.95 | O46: =IF(N46=0,"",M46/N46-1) -> -0.044883429 | P46: =SUM(于洪:武汉!P46) -> 299174.8 | Q46: =IF(P46=0,"",M46/P46-1) -> 0.059122426 | R46: =SUM(于洪:武汉!R46) -> 6011937.1 | S46: =IF(R46=0,"",M46/R46-1) -> -0.9472944
G47: Total Rooms Expenses 客房总支出 | H47: =SUM(H44:H46) -> 778716.58 | I47: =SUM(I44:I46) -> 943272.2 | J47: =IF(I47=0,"",H47/I47-1) -> -0.17445189 | K47: =SUM(K44:K46) -> 792793.88 | L47: =IF(K47=0,"",H47/K47-1) -> -0.01775657 | M47: =SUM(M44:M46) -> 778716.58 | N47: =SUM(N44:N46) -> 943272.2 | O47: =IF(N47=0,"",M47/N47-1) -> -0.17445189 | P47: =SUM(P44:P46) -> 792793.88 | Q47: =IF(P47=0,"",M47/P47-1) -> -0.01775657 | R47: =SUM(R44:R46) -> 13586331 | S47: =IF(R47=0,"",M47/R47-1) -> -0.94268382
G48: Departmental Profit 客房经营利润 | H48: =H43-H47 -> 927685.41 | I48: =I43-I47 -> 930046.4 | J48: =IF(I48=0,"",H48/I48-1) -> -0.0025385723 | K48: =K43-K47 -> 933745.17 | L48: =IF(K48=0,"",H48/K48-1) -> -0.0064897364 | M48: =M43-M47 -> 927685.41 | N48: =N43-N47 -> 930046.4 | O48: =IF(N48=0,"",M48/N48-1) -> -0.0025385723 | P48: =P43-P47 -> 933745.17 | Q48: =IF(P48=0,"",M48/P48-1) -> -0.0064897364 | R48: =R43-R47 -> 19234453 | S48: =IF(R48=0,"",M48/R48-1) -> -0.9517696
G49: Departmental Profit % 客房经营利润率 | H49: =IFERROR(H48/H43,0) -> 0.54364998 | I49: =IFERROR(I48/I43,0) -> 0.49646995 | J49: =IF(I49=0,"",H49/I49-1) -> 0.095030981 | K49: =IFERROR(K48/K43,0) -> 0.54081903 | L49: =IF(K49=0,"",H49/K49-1) -> 0.0052345677 | M49: =IFERROR(M48/M43,0) -> 0.54364998 | N49: =IFERROR(N48/N43,0) -> 0.49646995 | O49: =IF(N49=0,"",M49/N49-1) -> 0.095030981 | P49: =IFERROR(P48/P43,0) -> 0.54081903 | Q49: =IF(P49=0,"",M49/P49-1) -> 0.0052345677 | R49: =IFERROR(R48/R43,0) -> 0.5860449 | S49: =IF(R49=0,"",M49/R49-1) -> -0.072340737
G51: FOOD & BEVERAGE 餐饮
G52: Food Revenue 食品收入 | H52: =SUM(于洪:武汉!H52) -> 1822787.8 | I52: =SUM(于洪:武汉!I52) -> 2194891.5 | J52: =IF(I52=0,"",H52/I52-1) -> -0.16953169 | K52: =SUM(于洪:武汉!K52) -> 1633950.6 | L52: =IF(K52=0,"",H52/K52-1) -> 0.11557094 | M52: =SUM(于洪:武汉!M52) -> 1822787.8 | N52: =SUM(于洪:武汉!N52) -> 2194891.5 | O52: =IF(N52=0,"",M52/N52-1) -> -0.16953169 | P52: =SUM(于洪:武汉!P52) -> 1633950.6 | Q52: =IF(P52=0,"",M52/P52-1) -> 0.11557094 | R52: =SUM(于洪:武汉!R52) -> 24886299 | S52: =IF(R52=0,"",M52/R52-1) -> -0.92675537
